Workbook
Name AliqImp: #REF!
Name Capex: #REF!
Name CPV: #REF!
Name Cresc: '[1]Fluxo de Caixa A-1'!$D$13
Name CtasPagar: #REF!
Name CtasReceber: #REF!
Name CxOperac: #REF!
Name Depreciacao: #REF!
Name DespGeraisAdm: #REF!
Name elast: #REF!
Name Estoque: #REF!
Name ImpComp: #REF!
Name ImpPagar: #REF!
Name InvCGL: #REF!
Name Objetivos: INDIRECT("Auxiliar_Slides!$C$303:$S$"&305+MAX(COUNTIF([2]Auxiliar_Slides!$F$305:$F$326,">"&0),COUNTIF([2]Auxiliar_Slides!$R$305:$R$326,">"&0)))
Name ppa: #REF!
Name ReceitaLiquida: #REF!
Name ResOperac: #REF!
Name SalEncPagar: #REF!
Name SegmentaçãodeDados_Centro_de_custos: #N/A
Name SegmentaçãodeDados_Centro_de_custos1: #N/A
Name SegmentaçãodeDados_Centro_de_custos2: #N/A
Name SegmentaçãodeDados_Empresa: #N/A
Name SegmentaçãodeDados_Empresa1: #N/A
Name SegmentaçãodeDados_Empresa2: #N/A
Name WACC: '[1]Fluxo de Caixa A-1'!$D$22
Name WACCBR: [1]WACC!$C$10

Sheet CNS
A2: AuM | B2: =Consolidated!E4 -> 290504767 | C2: =Consolidated!F4 -> 304511145 | D2: =Consolidated!G4 -> 309415143 | E2: =Consolidated!H4 -> 311856596 | F2: =Consolidated!I4 -> 312069591 | G2: =Consolidated!J4 -> 295791970 | H2: =Consolidated!K4 -> 254401486 | I2: =Consolidated!L4 -> 0 | ... M2: =Consolidated!P4 -> 0
A3: ROA m | B3: =IF(B9>0,B9/B2,0) -> 0.00060518525 | C3: =IF(C9>0,C9/C2,0) -> 0.00058541463 | D3: =IF(D9>0,D9/D2,0) -> 0.00059200574 | E3: =IF(E9>0,E9/E2,0) -> 0.00061552272 | F3: =IF(F9>0,F9/F2,0) -> 0.00061657497 | G3: =IF(G9>0,G9/G2,0) -> 0.00063406671 | H3: =IF(H9>0,H9/H2,0) -> 0.00068929086 | I3: =IF(I9>0,I9/I2,0) -> 0 | ... M3: =IF(M9>0,M9/M2,0) -> 0
A4: Roa A | B4: =IF(B3<>0,(1+B3)^(12/1)-1,"") -> 0.0072864443 | C4: =IF(C3<>0,(1+C3)^(12/1)-1,"") -> 0.0070476387 | D4: =IF(D3<>0,(1+D3)^(12/1)-1,"") -> 0.0071272456 | E4: =IF(E3<>0,(1+E3)^(12/1)-1,"") -> 0.0074113293 | F4: =IF(F3<>0,(1+F3)^(12/1)-1,"") -> 0.0074240422 | G4: =IF(G3<>0,(1+G3)^(12/1)-1,"") -> 0.0076353913 | H4: =IF(H3<>0,(1+H3)^(12/1)-1,"") -> 0.0083029206 | I4: =IF(I3<>0,(1+I3)^(12/1)-1,"") | ... M4: =IF(M3<>0,(1+M3)^(12/1)-1,"")
A6: DRE | B6: Mês da baixa
A7: Categoria | B7: Jan/2026 | C7: Fev/2026 | D7: Mar/2026 | E7: Abr/2026 | F7: 46143 | G7: 46174 | H7: 46204 | I7: 46235 | J7: 46266 | K7: 46296 | L7: 46327 | M7: 46357 | N7: Total
A8: 01 Receitas Operacionais | B8: 239855.2 | C8: 250631.14 | D8: 228175.54 | E8: 230080.36 | F8: 232914.3 | G8: 277490.46 | H8: 227626.62 | N8: =SUM(B8:M8) -> 1686773.6
A9: 01.1 Consultoria | B9: 175809.2 | C9: 178265.28 | D9: 183175.54 | E9: 191954.82 | F9: 192414.3 | G9: 187551.84 | H9: 175356.62 | N9: =SUM(B9:M9) -> 1284527.6
A10: 01.2 Planejamento | B10: 14700 | C10: 18900 | D10: 10400 | E10: 6500 | F10: 6500 | G10: 0,00 | H10: 18270 | N10: =SUM(B10:M10) -> 75270
A11: 01.3 Tesouro Mato Grosso | B11: 34000 | C11: 34000 | D11: 34000 | E11: 0,00 | F11: 34000 | G11: 83700 | H11: 34000 | N11: =SUM(B11:M11) -> 253700
A12: 01.4 RPPS | B12: 15346 | C12: 18715.86 | D12: 0,00 | E12: 30425.54 | F12: 0,00 | G12: 6238.62 | H12: 0,00 | N12: =SUM(B12:M12) -> 70726.02
A13: 01.5 Consulta | B13: 0,00 | C13: 750 | D13: 600 | E13: 1200 | F13: 0,00 | G13: 0,00 | H13: 0,00 | N13: =SUM(B13:M13) -> 2550
A14: 01.6 Valuation | B14: 0 | C14: 0,00 | D14: 0,00 | E14: 0,00 | F14: 0,00 | G14: 0,00 | H14: 0,00 | N14: =SUM(B14:M14) -> 0
A15: 01T Receita Bruta de Vendas | B15: 239855.2 | C15: 250631.14 | D15: 228175.54 | E15: 230080.36 | F15: 232914.3 | G15: 277490.46 | H15: 227626.62 | N15: =SUM(B15:M15) -> 1686773.6
A16: 02 Deduções da Receita Bruta | B16: -177743.88 | C16: -108921.69 | D16: -121072.98 | E16: -170232.02 | F16: -110761.27 | G16: -111550.61 | H16: -175776.84 | N16: =SUM(B16:M16) -> -976059.29
A17: 02.1 Impostos Sobre Vendas | B17: -93125.38 | C17: -22147.37 | D17: -24947.44 | E17: -81040.13 | F17: -20948.04 | G17: -23544.72 | H17: -96739.75 | N17: =SUM(B17:M17) -> -362492.83 | O17: =N17/N8 -> -0.21490307
A18: 02.2 Comissões Consultores | B18: -78563.01 | C18: -78042.82 | D18: -86512.28 | E18: -81040.02 | F18: -80187.14 | G18: -81460.06 | H18: -72271.88 | N18: =SUM(B18:M18) -> -558077.21
A19: 02.3 Comissões Mesa | B19: -5749.27 | C19: -5695.28 | D19: -7461.4 | E19: -5965.22 | F19: -8479.87 | G19: -6239.61 | H19: -6458.99 | N19: =SUM(B19:M19) -> -46049.64
A20: 02.4 Descontos Incondicionais | B20: 0,00 | C20: -2730 | D20: -420 | E20: -1880.43 | F20: -840 | G20: 0,00 | H20: 0,00 | N20: =SUM(B20:M20) -> -5870.43
A21: 02.5 Devoluções de Vendas | B21: 0,00 | C21: 0,00 | D21: -1425.64 | E21: 0,00 | F21: 0,00 | G21: 0,00 | H21: 0,00 | N21: =SUM(B21:M21) -> -1425.64
A22: 02.6 Comissões Parceiros | B22: -306.22 | C22: -306.22 | D22: -306.22 | E22: -306.22 | F22: -306.22 | G22: -306.22 | H22: -306.22 | N22: =SUM(B22:M22) -> -2143.54
A23: 02T Receita Líquida de Vendas | B23: 62111.32 | C23: 141709.45 | D23: 107102.56 | E23: 59848.34 | F23: 122153.03 | G23: 165939.85 | H23: 51849.78 | N23: =SUM(B23:M23) -> 710714.33
A24: 03 Custos Operacionais | B24: -45973.64 | C24: -39048.45 | D24: -52448.17 | E24: -47406.54 | F24: -60020.04 | G24: -47468.03 | H24: -43406.91 | N24: =SUM(B24:M24) -> -335771.78
A25: 03.1 Salários e Encargos | B25: -6659.05 | C25: -10429.4 | D25: -13062.59 | E25: -11040.54 | F25: -11647.38 | G25: -15156.07 | H25: -11933.16 | N25: =SUM(B25:M25) -> -79928.19
A26: 03.2 Sistemas | B26: -15303.94 | C26: -9519.05 | D26: -13097.35 | E26: -10678.38 | F26: -9918.7 | G26: -9939.96 | H26: -10299.93 | N26: =SUM(B26:M26) -> -78757.31
A27: 03.3 Custo Tesouro mato grosso | B27: -21367.88 | C27: -19100 | D27: -26235.23 | E27: -25581.62 | F27: -32735.46 | G27: -22372 | H27: -21173.82 | N27: =SUM(B27:M27) -> -168566.01
A28: 03.4 Custo RPPS | B28: -1119.18 | C28: 0,00 | D28: 0,00 | E28: 0,00 | F28: 0,00 | G28: 0,00 | H28: 0,00 | N28: =SUM(B28:M28) -> -1119.18
A29: 03.5 Regulatórias | B29: -1523.59 | C29: 0,00 | D29: -53 | E29: -106 | F29: -5718.5 | G29: 0 | H29: 0 | N29: =SUM(B29:M29) -> -7401.09
A30: 03T Lucro Bruto | B30: 16137.68 | C30: 102661 | D30: 54654.39 | E30: 12441.8 | F30: 62132.99 | G30: 118471.82 | H30: 8442.87 | N30: =SUM(B30:M30) -> 374942.55
A31: 04 Despesas Operacionais | B31: -22722.73 | C31: -22213.48 | D31: -23785.24 | E31: -20323.96 | F31: -19904.76 | G31: -19438.82 | H31: -29716.58 | N31: =SUM(B31:M31) -> -158105.57
A32: 04.1 Imóvel | B32: -10767.65 | C32: -7850.3 | D32: -8253.59 | E32: -8252.46 | F32: -9165.58 | G32: -8964.05 | H32: -8776.49 | N32: =SUM(B32:M32) -> -62030.12
A33: 04.10 Outras Despesas | B33: 0 | C33: 0,00 | D33: 0,00 | E33: 0,00 | F33: 0,00 | G33: 0,00 | H33: 0,00 | N33: =SUM(B33:M33) -> 0
A34: 04.2 Serviços | B34: -4432.61 | C34: -4617.94 | D34: -4617.94 | E34: -4617.94 | F34: -4617.94 | G34: -4617.94 | H34: -13617.94 | N34: =SUM(B34:M34) -> -41140.25
A35: 04.3 Comerciais | B35: -2598.88 | C35: -3044.37 | D35: -4764.36 | E35: -2982.44 | F35: -1595.19 | G35: -484.9 | H35: -195 | N35: =SUM(B35:M35) -> -15665.14
A36: 04.4 Administrativas | B36: -2058.78 | C36: -3995.84 | D36: -3193.74 | E36: -2495.51 | F36: -2050.44 | G36: -3396.32 | H36: -3290.59 | N36: =SUM(B36:M36) -> -20481.22
A37: 04.5 Colaboradores | B37: -1957.95 | C37: -1798.17 | D37: -2048.75 | E37: -1068.75 | F37: -1568.75 | G37: -1068.75 | H37: -2929.7 | N37: =SUM(B37:M37) -> -12440.82
A38: 04.6 Diretoria | B38: -906.86 | C38: -906.86 | D38: -906.86 | E38: -906.86 | F38: -906.86 | G38: -906.86 | H38: -906.86 | N38: =SUM(B38:M38) -> -6348.02
A39: 04.7 Imobilizados e equipamentos | B39: 0 | C39: 0,00 | D39: 0,00 | E39: 0,00 | F39: 0,00 | G39: 0,00 | H39: 0,00 | N39: =SUM(B39:M39) -> 0
A40: 04.8 Vendas | B40: 0 | C40: 0,00 | D40: 0,00 | E40: 0,00 | F40: 0,00 | G40: 0,00 | H40: 0,00 | N40: =SUM(B40:M40) -> 0
A41: 04.9 Veículos | B41: 0 | C41: 0,00 | D41: 0,00 | E41: 0,00 | F41: 0,00 | G41: 0,00 | H41: 0,00 | N41: =SUM(B41:M41) -> 0
A42: 04T Lucro / Prejuízo Operacional | B42: -6585.05 | C42: 80447.52 | D42: 30869.15 | E42: -7882.16 | F42: 42228.23 | G42: 99033 | H42: -21273.71 | N42: =SUM(B42:M42) -> 216836.98
A43: 05 Receitas e Despesas Financeiras | B43: -1256.57 | C43: -973.2 | D43: -337.75 | E43: -751.96 | F43: 271.08 | G43: -3502.97 | H43: -129.72 | N43: =SUM(B43:M43) -> -6681.09
A44: 06 Outras Receitas e Despesas Não Operacionais | B44: 8.63 | C44: 1.89 | D44: 0.6 | E44: 3.45 | F44: 5.19 | G44: 0,00 | H44: -50 | N44: =SUM(B44:M44) -> -30.24
A45: 06T Lucro / Prejuízo Líquido | B45: -7832.99 | C45: 79476.21 | D45: 30532 | E45: -8630.67 | F45: 42504.5 | G45: 95530.03 | H45: -21453.43 | N45: =SUM(B45:M45) -> 210125.65
A46: 07 Despesas com Investimentos e Empréstimos | B46: -10236.57 | C46: -10119.25 | D46: -8739.58 | E46: -10636.86 | F46: -9270.03 | G46: -9126.12 | H46: -9386.01 | N46: =SUM(B46:M46) -> -67514.42
A47: 07.1 Investimentos em Imobilizado | B47: 0,00 | C47: -278.09 | D47: 0,00 | E47: -558.89 | F47: 0,00 | G47: 0,00 | H47: 0,00 | N47: =SUM(B47:M47) -> -836.98
A48: 07.2 Empréstimos e Dívidas | B48: -10236.57 | C48: -9841.16 | D48: -8739.58 | E48: -10077.97 | F48: -9270.03 | G48: -9126.12 | H48: -9386.01 | N48: =SUM(B48:M48) -> -66677.44
A49: 07T Lucro / Prejuízo Final | B49: -18069.56 | C49: 69356.96 | D49: 21792.42 | E49: -19267.53 | F49: 33234.47 | G49: 86403.91 | H49: -30839.44 | N49: =SUM(B49:M49) -> 142611.23
A53: Mato Grosso | B53: =(B11*(1+$O$17))+B27 -> 5325.4156 | C53: =(C11*(1+$O$17))+C27 -> 7593.2956 | D53: =(D11*(1+$O$17))+D27 -> 458.06561 | E53: =(E11*(1+$O$17))+E27 -> -25581.62 | F53: =(F11*(1+$O$17))+F27 -> -6042.1644 | G53: =(G11*(1+$O$17))+G27 -> 43340.613 | H53: =(H11*(1+$O$17))+H27 -> 5519.4756 | I53: =(I11*(1+$O$17))+I27 -> 0 | ... N53: =(N11*(1+$O$17))+N27 -> 30613.081
A54: RPPS | B54: =(B12*(1+$O$17))+B28 -> 10928.917 | C54: =(C12*(1+$O$17))+C28 -> 14693.764 | D54: =(D12*(1+$O$17))+D28 -> 0 | E54: =(E12*(1+$O$17))+E28 -> 23886.998 | F54: =(F12*(1+$O$17))+F28 -> 0 | G54: =(G12*(1+$O$17))+G28 -> 4897.9214 | H54: =(H12*(1+$O$17))+H28 -> 0 | I54: =(I12*(1+$O$17))+I28 -> 0 | ... N54: =(N12*(1+$O$17))+N28 -> 54407.601
A58: AuM | B58: =B2 -> 290504767 | C58: =C2 -> 304511145 | D58: =D2 -> 309415143 | E58: =E2 -> 311856596 | F58: =F2 -> 312069591 | G58: =G2 -> 295791970 | H58: =H2 -> 254401486 | I58: =I2 -> 0 | ... M58: =M2 -> 0
A59: ROA Consultoria | B59: =IF(B58>0,B9/B2,"") -> 0.00060518525 | C59: =IF(C58>0,C9/C2,"") -> 0.00058541463 | D59: =IF(D58>0,D9/D2,"") -> 0.00059200574 | E59: =IF(E58>0,E9/E2,"") -> 0.00061552272 | F59: =IF(F58>0,F9/F2,"") -> 0.00061657497 | G59: =IF(G58>0,G9/G2,"") -> 0.00063406671 | H59: =IF(H58>0,H9/H2,"") -> 0.00068929086 | I59: =IF(I58>0,I9/I2,"") | ... M59: =IF(M58>0,M9/M2,"") | N59: =AVERAGE(B59:E59) -> 0.00059953208
A60: ROA Planejamento | B60: =IF(B58>0,B10/B2,"") -> 5.0601579e-05 | C60: =IF(C58>0,C10/C2,"") -> 6.2066694e-05 | D60: =IF(D58>0,D10/D2,"") -> 3.36118e-05 | E60: =IF(E58>0,E10/E2,"") -> 2.0842913e-05 | F60: =IF(F58>0,F10/F2,"") -> 2.0828688e-05 | G60: =IF(G58>0,G10/G2,"") -> 0 | H60: =IF(H58>0,H10/H2,"") -> 7.1815618e-05 | I60: =IF(I58>0,I10/I2,"") | ... M60: =IF(M58>0,M10/M2,"") | N60: =AVERAGE(B60:E60) -> 4.1780747e-05
A61: RPPS | B61: =B12 -> 15346 | C61: =C12 -> 18715.86 | D61: =D12 -> 0,00 | E61: =E12 -> 30425.54 | N61: =AVERAGE(B61:E61) -> 21495.8

Sheet CRR
A2: AuM | B2: =Consolidated!E4 -> 290504767 | C2: =Consolidated!F4 -> 304511145 | D2: =Consolidated!G4 -> 309415143 | E2: =Consolidated!H4 -> 311856596 | F2: =Consolidated!I4 -> 312069591 | G2: =Consolidated!J4 -> 295791970 | H2: =Consolidated!K4 -> 254401486 | I2: =Consolidated!L4 -> 0 | ... M2: =Consolidated!P4 -> 0
A6: DRE | B6: Mês da baixa
A7: Categoria | B7: Jan/2026 | C7: Fev/2026 | D7: Mar/2026 | E7: Abr/2026 | F7: 46143 | G7: 46174 | H7: 46204 | I7: 46235 | J7: 46266 | K7: 46296 | L7: 46327 | M7: 46357 | N7: Total
A8: 01 Receitas Operacionais | B8: 42588.73 | C8: 34365.1 | D8: 44620.81 | E8: 36640.27 | F8: 44420.28 | G8: 24067.41 | H8: 52992.46 | N8: =SUM(B8:M8) -> 279695.06
A9: 01.1 Câmbio/Bancários | B9: 2129.24 | C9: 4080.01 | D9: 7882.59 | E9: 3358.51 | F9: 4335.02 | G9: 0,00 | H9: 5592.59 | N9: =SUM(B9:M9) -> 27377.96
A10: 01.2 Consórcio | B10: 11277.6 | C10: 11277.6 | D10: 11277.6 | E10: 11277.6 | F10: 11277.6 | G10: 0,00 | H10: 17767.2 | N10: =SUM(B10:M10) -> 74155.2
A11: 01.3 Previdência | B11: 4958.36 | C11: 4860.28 | D11: 6325.28 | E11: 5913.91 | F11: 2187.12 | G11: 3486.48 | H11: 3208.11 | N11: =SUM(B11:M11) -> 30939.54
A12: 01.4 Seguro de vida | B12: 20365.39 | C12: 11096.95 | D12: 13782.61 | E12: 11693.06 | F12: 19858.71 | G12: 16176.26 | H12: 19179.52 | N12: =SUM(B12:M12) -> 112152.5
A13: 01.5 Outros | B13: 3858.14 | C13: 3050.26 | D13: 5352.73 | E13: 4397.19 | F13: 6761.83 | G13: 4404.67 | H13: 7245.04 | N13: =SUM(B13:M13) -> 35069.86
A14: 01T Receita Bruta de Vendas | B14: 42588.73 | C14: 34365.1 | D14: 44620.81 | E14: 36640.27 | F14: 44420.28 | G14: 24067.41 | H14: 52992.46 | N14: =SUM(B14:M14) -> 279695.06
A15: 02 Deduções da Receita Bruta | B15: -21072.77 | C15: -17399.4 | D15: -17108.46 | E15: -26182.42 | F15: -17964.84 | G15: -16506.11 | H15: -19508.79 | N15: =SUM(B15:M15) -> -135742.79
A16: 02.1 Impostos Sobre Vendas | B16: -8389.22 | C16: -1884.97 | D16: -2397 | E16: -8842.03 | F16: -2316.2 | G16: -1629.85 | H16: -11875.59 | N16: =SUM(B16:M16) -> -37334.86
A17: 02.2 Comissões Consultores | B17: -10887.62 | C17: -13833.49 | D17: -11755.75 | E17: -14623.74 | F17: -11725.19 | G17: -13404.29 | H17: -5997.6 | N17: =SUM(B17:M17) -> -82227.68
A18: 02.3 Comissões Mesa | B18: 0 | C18: 0,00 | D18: 0,00 | E18: 0,00 | F18: 0,00 | G18: 0,00 | H18: 0,00 | N18: =SUM(B18:M18) -> 0
A19: 02.4 Descontos Incondicionais | B19: 0 | C19: 0,00 | D19: 0,00 | E19: 0,00 | F19: 0,00 | G19: 0,00 | H19: 0,00 | N19: =SUM(B19:M19) -> 0
A20: 02.5 Devoluções de Vendas | B20: -1163.72 | C20: -1319.61 | D20: -2497.98 | E20: -1950.63 | F20: -3298.79 | G20: -1471.97 | H20: -55.4 | N20: =SUM(B20:M20) -> -11758.1
A21: 02.6 Comissões Parceiros | B21: -632.21 | C21: -361.33 | D21: -457.73 | E21: -766.02 | F21: -624.66 | G21: 0 | H21: -1580.2 | N21: =SUM(B21:M21) -> -4422.15
A22: 02T Receita Líquida de Vendas | B22: 21515.96 | C22: 16965.7 | D22: 27512.35 | E22: 10457.85 | F22: 26455.44 | G22: 7561.3 | H22: 33483.67 | N22: =SUM(B22:M22) -> 143952.27
A23: 03 Custos Operacionais | B23: -18986.62 | C23: -22249.18 | D23: -15494.05 | E23: -17168.59 | F23: -21352.85 | G23: -19144.68 | H23: -16275.98 | N23: =SUM(B23:M23) -> -130671.95
A24: 03.1 Salários e Encargos | B24: -18767.1 | C24: -22249.18 | D24: -15494.05 | E24: -17168.59 | F24: -21352.85 | G24: -19144.68 | H24: -16275.98 | N24: =SUM(B24:M24) -> -130452.43
A25: 03.2 Sistemas | B25: -219.52 | C25: 0,00 | D25: 0,00 | E25: 0,00 | F25: 0,00 | G25: 0,00 | H25: 0,00 | N25: =SUM(B25:M25) -> -219.52
A26: 03.3 Custo Tesouro mato grosso | B26: 0 | C26: 0,00 | D26: 0,00 | E26: 0,00 | F26: 0,00 | G26: 0,00 | H26: 0,00 | N26: =SUM(B26:M26) -> 0
A27: 03.4 Custo RPPS | B27: 0 | C27: 0,00 | D27: 0,00 | E27: 0,00 | F27: 0,00 | G27: 0,00 | H27: 0,00 | N27: =SUM(B27:M27) -> 0
A28: 03.5 Regulatórias | B28: 0 | C28: 0,00 | D28: 0,00 | E28: 0,00 | F28: 0,00 | G28: 0,00 | H28: 0,00 | N28: =SUM(B28:M28) -> 0
A29: 03T Lucro Bruto | B29: 2529.34 | C29: -5283.48 | D29: 12018.3 | E29: -6710.74 | F29: 5102.59 | G29: -11583.38 | H29: 17207.69 | N29: =SUM(B29:M29) -> 13280.32
A30: 04 Despesas Operacionais | B30: -758.77 | C30: -1958.77 | D30: -851.16 | E30: -807.81 | F30: -787.76 | G30: -829.74 | H30: -656.45 | N30: =SUM(B30:M30) -> -6650.46
A31: 04.1 Imóvel | B31: 0 | C31: 0,00 | D31: 0,00 | E31: 0,00 | F31: 0,00 | G31: 0,00 | H31: 0,00 | N31: =SUM(B31:M31) -> 0
A32: 04.10 Outras Despesas | B32: 0 | C32: 0,00 | D32: 0,00 | E32: 0,00 | F32: 0,00 | G32: 0,00 | H32: 0,00 | N32: =SUM(B32:M32) -> 0
A33: 04.2 Serviços | B33: 0 | C33: 0,00 | D33: 0,00 | E33: 0,00 | F33: 0,00 | G33: 0,00 | H33: 0,00 | N33: =SUM(B33:M33) -> 0
A34: 04.3 Comerciais | B34: 0,00 | C34: -1200 | D34: -63.4 | E34: -20.05 | F34: 0,00 | G34: 0,00 | H34: 0,00 | N34: =SUM(B34:M34) -> -1283.45
A35: 04.4 Administrativas | B35: 0,00 | C35: 0,00 | D35: 0,00 | E35: 0,00 | F35: 0,00 | G35: -476.1 | H35: -72 | N35: =SUM(B35:M35) -> -548.1
A36: 04.5 Colaboradores | B36: -758.77 | C36: -758.77 | D36: -787.76 | E36: -787.76 | F36: -787.76 | G36: -353.64 | H36: -584.45 | N36: =SUM(B36:M36) -> -4818.91
A37: 04.6 Diretoria | B37: 0 | C37: 0,00 | D37: 0,00 | E37: 0,00 | F37: 0,00 | G37: 0,00 | H37: 0,00 | N37: =SUM(B37:M37) -> 0
A38: 04.7 Imobilizados e equipamentos | B38: 0 | C38: 0,00 | D38: 0,00 | E38: 0,00 | F38: 0,00 | G38: 0,00 | H38: 0,00 | N38: =SUM(B38:M38) -> 0
A39: 04.8 Vendas | B39: 0 | C39: 0,00 | D39: 0,00 | E39: 0,00 | F39: 0,00 | G39: 0,00 | H39: 0,00 | N39: =SUM(B39:M39) -> 0
A40: 04.9 Veículos | B40: 0 | C40: 0,00 | D40: 0,00 | E40: 0,00 | F40: 0,00 | G40: 0,00 | H40: 0,00 | N40: =SUM(B40:M40) -> 0
A41: 04T Lucro / Prejuízo Operacional | B41: 1770.57 | C41: -7242.25 | D41: 11167.14 | E41: -7518.55 | F41: 4314.83 | G41: -12413.12 | H41: 16551.24 | N41: =SUM(B41:M41) -> 6629.86
A42: 05 Receitas e Despesas Financeiras | B42: -6.29 | C42: 0,00 | D42: 0,00 | E42: 0,00 | F42: 0,00 | G42: -13.47 | H42: 0,00 | N42: =SUM(B42:M42) -> -19.76
A43: 06 Outras Receitas e Despesas Não Operacionais | B43: 0 | C43: 0,00 | D43: 0,00 | E43: 0,00 | F43: 0,00 | G43: 0,00 | H43: 0,00 | N43: =SUM(B43:M43) -> 0
A44: 06T Lucro / Prejuízo Líquido | B44: 1764.28 | C44: -7242.25 | D44: 11167.14 | E44: -7518.55 | F44: 4314.83 | G44: -12426.59 | H44: 16551.24 | N44: =SUM(B44:M44) -> 6610.1
A45: 07 Despesas com Investimentos e Empréstimos | B45: 0 | C45: 0,00 | D45: 0,00 | E45: 0,00 | F45: 0,00 | G45: 0,00 | H45: 0,00 | N45: =SUM(B45:M45) -> 0
A46: 07.1 Investimentos em Imobilizado | B46: 0 | C46: 0,00 | D46: 0,00 | E46: 0,00 | F46: 0,00 | G46: 0,00 | H46: 0,00 | N46: =SUM(B46:M46) -> 0
A47: 07.2 Empréstimos e Dívidas | B47: 0 | C47: 0,00 | D47: 0,00 | E47: 0,00 | F47: 0,00 | G47: 0,00 | H47: 0,00 | N47: =SUM(B47:M47) -> 0
A48: 07T Lucro / Prejuízo Final | B48: 1764.28 | C48: -7242.25 | D48: 11167.14 | E48: -7518.55 | F48: 4314.83 | G48: -12426.59 | H48: 16551.24 | N48: =SUM(B48:M48) -> 6610.1
A53: AuM | B53: =B2 -> 290504767 | C53: =C2 -> 304511145 | D53: =D2 -> 309415143 | E53: =E2 -> 311856596 | F53: =F2 -> 312069591 | G53: =G2 -> 295791970 | H53: =H2 -> 254401486 | I53: =I2 -> 0 | ... M53: =M2 -> 0
A54: ROA Corretora | B54: =IF(B8>0,B8/B53,"") -> 0.00014660252 | C54: =IF(C8>0,C8/C53,"") -> 0.00011285334 | D54: =IF(D8>0,D8/D53,"") -> 0.00014421017 | E54: =IF(E8>0,E8/E53,"") -> 0.00011749076 | F54: =IF(F8>0,F8/F53,"") -> 0.00014234094 | G54: =IF(G8>0,G8/G53,"") -> 8.1366002e-05 | H54: =IF(H8>0,H8/H53,"") -> 0.00020830248 | I54: =IF(I8>0,I8/I53,"") | ... M54: =IF(M8>0,M8/M53,"") | N54: =AVERAGE(B54:E54) -> 0.0001302892
A55: ROA Vida | B55: =IF(B12>0,B12/B53,"") -> 7.0103462e-05 | C55: =IF(C12>0,C12/C53,"") -> 3.6441852e-05 | D55: =IF(D12>0,D12/D53,"") -> 4.4544071e-05 | E55: =IF(E12>0,E12/E53,"") -> 3.749499e-05 | F55: =IF(F12>0,F12/F53,"") -> 6.3635518e-05 | G55: =IF(G12>0,G12/G53,"") -> 5.4687962e-05 | H55: =IF(H12>0,H12/H53,"") -> 7.5390755e-05 | I55: =IF(I12>0,I12/I53,"") | ... M55: =IF(M12>0,M12/M53,"")
A56: ROA Previdência | B56: =IF(B11>0,B11/B53,"") -> 1.7068085e-05 | C56: =IF(C11>0,C11/C53,"") -> 1.5960926e-05 | D56: =IF(D11>0,D11/D53,"") -> 2.0442697e-05 | E56: =IF(E11>0,E11/E53,"") -> 1.8963556e-05 | F56: =IF(F11>0,F11/F53,"") -> 7.0084368e-06 | G56: =IF(G11>0,G11/G53,"") -> 1.1786933e-05 | H56: =IF(H11>0,H11/H53,"") -> 1.2610422e-05 | I56: =IF(I11>0,I11/I53,"") | ... M56: =IF(M11>0,M11/M53,"")

Sheet Consolidated
D2: Aum/1k | E2: =IF(E4>0,E4/1000,0) -> 290504.77 | F2: =IF(F4>0,F4/1000,0) -> 304511.15 | G2: =IF(G4>0,G4/1000,0) -> 309415.14 | H2: =IF(H4>0,H4/1000,0) -> 311856.6 | I2: =IF(I4>0,I4/1000,0) -> 312069.59 | J2: =IF(J4>0,J4/1000,0) -> 295791.97 | K2: =IF(K4>0,K4/1000,0) -> 254401.49 | L2: =IF(L4>0,L4/1000,0) -> 0 | ... P2: =IF(P4>0,P4/1000,0) -> 0
D4: AuM | E4: =AuM!C76 -> 290504767 | F4: =AuM!C77 -> 304511145 | G4: =AuM!C78 -> 309415143 | H4: =AuM!C79 -> 311856596 | I4: =AuM!C80 -> 312069591 | J4: =AuM!C81 -> 295791970 | K4: =AuM!C82 -> 254401486 | Q4: Média | U4: Média
D5: ROA Anualizado | E5: =IF(E4>0,(E7/E4)*12,"") -> 0.011667028 | F5: =IF(F4>0,(F7/F4)*12,"") -> 0.011230968 | G5: =IF(G4>0,(G7/G4)*12,"") -> 0.010579819 | H5: =IF(H4>0,(H7/H4)*12,"") -> 0.010263203 | I5: =IF(I4>0,(I7/I4)*12,"") -> 0.010664336 | J5: =IF(J4>0,(J7/J4)*12,"") -> 0.012233917 | K5: =IF(K4>0,(K7/K4)*12,"") -> 0.013236672 | L5: =IF(L4>0,(L7/L4)*12,"") | ... P5: =IF(P4>0,(P7/P4)*12,"") | Q5: =AVERAGE(E5:P5) -> 0.011410849 | U5: 7
D6: Categoria | E6: Jan/2026 | F6: Fev/2026 | G6: Mar/2026 | H6: Abr/2026 | I6: 46143 | J6: 46174 | K6: 46204 | L6: 46235 | M6: 46266 | N6: 46296 | O6: 46327 | P6: 46357 | Q6: Total | U6: Total
D7: 01 Receitas Operacionais | E7: =CNS!B8+CRR!B8 -> 282443.93 | F7: =CNS!C8+CRR!C8 -> 284996.24 | G7: =CNS!D8+CRR!D8 -> 272796.35 | H7: =CNS!E8+CRR!E8 -> 266720.63 | I7: =CNS!F8+CRR!F8 -> 277334.58 | J7: =CNS!G8+CRR!G8 -> 301557.87 | K7: =CNS!H8+CRR!H8 -> 280619.08 | L7: =CNS!I8+CRR!I8 -> 0 | ... P7: =CNS!M8+CRR!M8 -> 0 | Q7: =SUM(E7:P7) -> 1966468.7 | T7: 01 Receitas Operacionais | U7: =Q7/$U$5 -> 280924.1
D8: Consultoria | E8: =CNS!B9 -> 175809.2 | F8: =CNS!C9 -> 178265.28 | G8: =CNS!D9 -> 183175.54 | H8: =CNS!E9 -> 191954.82 | I8: =CNS!F9 -> 192414.3 | J8: =CNS!G9 -> 187551.84 | K8: =CNS!H9 -> 175356.62 | L8: =CNS!I9 -> 0 | ... P8: =CNS!M9 -> 0 | Q8: =SUM(E8:P8) -> 1284527.6 | R8: =Q8/$Q$7 -> 0.65321539 | T8: Consultoria | U8: =Q8/$U$5 -> 183503.94
D9: Planejamento | E9: =CNS!B10 -> 14700 | F9: =CNS!C10 -> 18900 | G9: =CNS!D10 -> 10400 | H9: =CNS!E10 -> 6500 | I9: =CNS!F10 -> 6500 | J9: =CNS!G10 -> 0,00 | K9: =CNS!H10 -> 18270 | L9: =CNS!I10 -> 0 | ... P9: =CNS!M10 -> 0 | Q9: =SUM(E9:P9) -> 75270 | R9: =Q9/$Q$7 -> 0.038276735 | T9: Planejamento | U9: =Q9/$U$5 -> 10752.857
D10: Tesouro Mato Grosso | E10: =CNS!B11 -> 34000 | F10: =CNS!C11 -> 34000 | G10: =CNS!D11 -> 34000 | H10: =CNS!E11 -> 0,00 | I10: =CNS!F11 -> 34000 | J10: =CNS!G11 -> 83700 | K10: =CNS!H11 -> 34000 | L10: =CNS!I11 -> 0 | ... P10: =CNS!M11 -> 0 | Q10: =SUM(E10:P10) -> 253700 | R10: =Q10/$Q$7 -> 0.12901299 | T10: Tesouro Mato Grosso | U10: =Q10/$U$5 -> 36242.857
D11: RPPS | E11: =CNS!B12 -> 15346 | F11: =CNS!C12 -> 18715.86 | G11: =CNS!D12 -> 0,00 | H11: =CNS!E12 -> 30425.54 | I11: =CNS!F12 -> 0,00 | J11: =CNS!G12 -> 6238.62 | K11: =CNS!H12 -> 0,00 | L11: =CNS!I12 -> 0 | ... P11: =CNS!M12 -> 0 | Q11: =SUM(E11:P11) -> 70726.02 | R11: =Q11/$Q$7 -> 0.035966004 | T11: RPPS | U11: =Q11/$U$5 -> 10103.717
D12: Consulta | E12: =CNS!B13 -> 0,00 | F12: =CNS!C13 -> 750 | G12: =CNS!D13 -> 600 | H12: =CNS!E13 -> 1200 | I12: =CNS!F13 -> 0,00 | J12: =CNS!G13 -> 0,00 | K12: =CNS!H13 -> 0,00 | L12: =CNS!I13 -> 0 | ... P12: =CNS!M13 -> 0 | Q12: =SUM(E12:P12) -> 2550 | R12: =Q12/$Q$7 -> 0.0012967407 | T12: Consulta | U12: =Q12/$U$5 -> 364.28571
D13: Valuation | E13: =CNS!B14 -> 0 | F13: =CNS!C14 -> 0,00 | G13: =CNS!D14 -> 0,00 | H13: =CNS!E14 -> 0,00 | I13: =CNS!F14 -> 0,00 | J13: =CNS!G14 -> 0,00 | K13: =CNS!H14 -> 0,00 | L13: =CNS!I14 -> 0 | ... P13: =CNS!M14 -> 0 | Q13: =SUM(E13:P13) -> 0 | R13: =Q13/$Q$7 -> 0 | T13: Valuation | U13: =Q13/$U$5 -> 0
D14: Câmbio/Bancários | E14: =CRR!B9 -> 2129.24 | F14: =CRR!C9 -> 4080.01 | G14: =CRR!D9 -> 7882.59 | H14: =CRR!E9 -> 3358.51 | I14: =CRR!F9 -> 4335.02 | J14: =CRR!G9 -> 0,00 | K14: =CRR!H9 -> 5592.59 | L14: =CRR!I9 -> 0 | ... P14: =CRR!M9 -> 0 | Q14: =SUM(E14:P14) -> 27377.96 | R14: =Q14/$Q$7 -> 0.013922398 | T14: Câmbio/Bancários | U14: =Q14/$U$5 -> 3911.1371
D15: Consórcio | E15: =CRR!B10 -> 11277.6 | F15: =CRR!C10 -> 11277.6 | G15: =CRR!D10 -> 11277.6 | H15: =CRR!E10 -> 11277.6 | I15: =CRR!F10 -> 11277.6 | J15: =CRR!G10 -> 0,00 | K15: =CRR!H10 -> 17767.2 | L15: =CRR!I10 -> 0 | ... P15: =CRR!M10 -> 0 | Q15: =SUM(E15:P15) -> 74155.2 | R15: =Q15/$Q$7 -> 0.03770983 | T15: Consórcio | U15: =Q15/$U$5 -> 10593.6
D16: Previdência | E16: =CRR!B11 -> 4958.36 | F16: =CRR!C11 -> 4860.28 | G16: =CRR!D11 -> 6325.28 | H16: =CRR!E11 -> 5913.91 | I16: =CRR!F11 -> 2187.12 | J16: =CRR!G11 -> 3486.48 | K16: =CRR!H11 -> 3208.11 | L16: =CRR!I11 -> 0 | ... P16: =CRR!M11 -> 0 | Q16: =SUM(E16:P16) -> 30939.54 | R16: =Q16/$Q$7 -> 0.015733553 | T16: Previdência | U16: =Q16/$U$5 -> 4419.9343
D17: Seguro de vida | E17: =CRR!B12 -> 20365.39 | F17: =CRR!C12 -> 11096.95 | G17: =CRR!D12 -> 13782.61 | H17: =CRR!E12 -> 11693.06 | I17: =CRR!F12 -> 19858.71 | J17: =CRR!G12 -> 16176.26 | K17: =CRR!H12 -> 19179.52 | L17: =CRR!I12 -> 0 | ... P17: =CRR!M12 -> 0 | Q17: =SUM(E17:P17) -> 112152.5 | R17: =Q17/$Q$7 -> 0.057032436 | T17: Seguro de vida | U17: =Q17/$U$5 -> 16021.786
D18: Outros Ramos | E18: =CRR!B13 -> 3858.14 | F18: =CRR!C13 -> 3050.26 | G18: =CRR!D13 -> 5352.73 | H18: =CRR!E13 -> 4397.19 | I18: =CRR!F13 -> 6761.83 | J18: =CRR!G13 -> 4404.67 | K18: =CRR!H13 -> 7245.04 | L18: =CRR!I13 -> 0 | ... P18: =CRR!M13 -> 0 | Q18: =SUM(E18:P18) -> 35069.86 | R18: =Q18/$Q$7 -> 0.017833928 | T18: Outros Ramos | U18: =Q18/$U$5 -> 5009.98
D19: 01T Receita Bruta de Vendas | Q19: =SUM(E19:P19) -> 0 | R19: =Q19/$Q$7 -> 0 | T19: 01T Receita Bruta de Vendas | U19: =Q19/$U$5 -> 0
D20: 02 Deduções da Receita Bruta | E20: =CNS!B16+CRR!B15 -> -198816.65 | F20: =CNS!C16+CRR!C15 -> -126321.09 | G20: =CNS!D16+CRR!D15 -> -138181.44 | H20: =CNS!E16+CRR!E15 -> -196414.44 | I20: =CNS!F16+CRR!F15 -> -128726.11 | J20: =CNS!G16+CRR!G15 -> -128056.72 | K20: =CNS!H16+CRR!H15 -> -195285.63 | L20: =CNS!I16+CRR!I15 -> 0 | ... P20: =CNS!M16+CRR!M15 -> 0 | Q20: =SUM(E20:P20) -> -1111802.1 | R20: =Q20/$Q$7 -> -0.56538001 | T20: 02 Deduções da Receita Bruta | U20: =Q20/$U$5 -> -158828.87
D21: 02.1 Impostos Sobre Vendas | E21: =CNS!B17+CRR!B16 -> -101514.6 | F21: =CNS!C17+CRR!C16 -> -24032.34 | G21: =CNS!D17+CRR!D16 -> -27344.44 | H21: =CNS!E17+CRR!E16 -> -89882.16 | I21: =CNS!F17+CRR!F16 -> -23264.24 | J21: =CNS!G17+CRR!G16 -> -25174.57 | K21: =CNS!H17+CRR!H16 -> -108615.34 | L21: =CNS!I17+CRR!I16 -> 0 | ... P21: =CNS!M17+CRR!M16 -> 0 | Q21: =SUM(E21:P21) -> -399827.69 | R21: =Q21/$Q$7 -> -0.20332268 | T21: 02.1 Impostos Sobre Vendas | U21: =Q21/$U$5 -> -57118.241
D22: 02.2 Comissões Consultores | E22: =CNS!B18+CRR!B17 -> -89450.63 | F22: =CNS!C18+CRR!C17 -> -91876.31 | G22: =CNS!D18+CRR!D17 -> -98268.03 | H22: =CNS!E18+CRR!E17 -> -95663.76 | I22: =CNS!F18+CRR!F17 -> -91912.33 | J22: =CNS!G18+CRR!G17 -> -94864.35 | K22: =CNS!H18+CRR!H17 -> -78269.48 | L22: =CNS!I18+CRR!I17 -> 0 | ... P22: =CNS!M18+CRR!M17 -> 0 | Q22: =SUM(E22:P22) -> -640304.89 | R22: =Q22/$Q$7 -> -0.32561154 | T22: 02.2 Comissões Consultores | U22: =Q22/$U$5 -> -91472.127
D23: 02.3 Comissões Mesa | E23: =CNS!B19+CRR!B18 -> -5749.27 | F23: =CNS!C19+CRR!C18 -> -5695.28 | G23: =CNS!D19+CRR!D18 -> -7461.4 | H23: =CNS!E19+CRR!E18 -> -5965.22 | I23: =CNS!F19+CRR!F18 -> -8479.87 | J23: =CNS!G19+CRR!G18 -> -6239.61 | K23: =CNS!H19+CRR!H18 -> -6458.99 | L23: =CNS!I19+CRR!I18 -> 0 | ... P23: =CNS!M19+CRR!M18 -> 0 | Q23: =SUM(E23:P23) -> -46049.64 | R23: =Q23/$Q$7 -> -0.023417429 | T23: 02.3 Comissões Mesa | U23: =Q23/$U$5 -> -6578.52
D24: 02.4 Descontos Incondicionais | E24: =CNS!B20+CRR!B19 -> 0 | F24: =CNS!C20+CRR!C19 -> -2730 | G24: =CNS!D20+CRR!D19 -> -420 | H24: =CNS!E20+CRR!E19 -> -1880.43 | I24: =CNS!F20+CRR!F19 -> -840 | J24: =CNS!G20+CRR!G19 -> 0 | K24: =CNS!H20+CRR!H19 -> 0 | L24: =CNS!I20+CRR!I19 -> 0 | ... P24: =CNS!M20+CRR!M19 -> 0 | Q24: =SUM(E24:P24) -> -5870.43 | R24: =Q24/$Q$7 -> -0.0029852649 | T24: 02.4 Descontos Incondicionais | U24: =Q24/$U$5 -> -838.63286
D25: 02.5 Devoluções de Vendas | E25: =CNS!B21+CRR!B20 -> -1163.72 | F25: =CNS!C21+CRR!C20 -> -1319.61 | G25: =CNS!D21+CRR!D20 -> -3923.62 | H25: =CNS!E21+CRR!E20 -> -1950.63 | I25: =CNS!F21+CRR!F20 -> -3298.79 | J25: =CNS!G21+CRR!G20 -> -1471.97 | K25: =CNS!H21+CRR!H20 -> -55.4 | L25: =CNS!I21+CRR!I20 -> 0 | ... P25: =CNS!M21+CRR!M20 -> 0 | Q25: =SUM(E25:P25) -> -13183.74 | R25: =Q25/$Q$7 -> -0.0067042715 | T25: 02.5 Devoluções de Vendas | U25: =Q25/$U$5 -> -1883.3914
D26: 02.6 Comissões Parceiros | E26: =CNS!B22+CRR!B21 -> -938.43 | F26: =CNS!C22+CRR!C21 -> -667.55 | G26: =CNS!D22+CRR!D21 -> -763.95 | H26: =CNS!E22+CRR!E21 -> -1072.24 | I26: =CNS!F22+CRR!F21 -> -930.88 | J26: =CNS!G22+CRR!G21 -> -306.22 | K26: =CNS!H22+CRR!H21 -> -1886.42 | L26: =CNS!I22+CRR!I21 -> 0 | ... P26: =CNS!M22+CRR!M21 -> 0 | Q26: =SUM(E26:P26) -> -6565.69 | R26: =Q26/$Q$7 -> -0.0033388226 | T26: 02.6 Comissões Parceiros | U26: =Q26/$U$5 -> -937.95571
D27: 02T Receita Líquida de Vendas | E27: =CNS!B23+CRR!B22 -> 83627.28 | F27: =CNS!C23+CRR!C22 -> 158675.15 | G27: =CNS!D23+CRR!D22 -> 134614.91 | H27: =CNS!E23+CRR!E22 -> 70306.19 | I27: =CNS!F23+CRR!F22 -> 148608.47 | J27: =CNS!G23+CRR!G22 -> 173501.15 | K27: =CNS!H23+CRR!H22 -> 85333.45 | L27: =CNS!I23+CRR!I22 -> 0 | ... P27: =CNS!M23+CRR!M22 -> 0 | Q27: =SUM(E27:P27) -> 854666.6 | R27: =Q27/$Q$7 -> 0.43461999 | T27: 02T Receita Líquida de Vendas | U27: =Q27/$U$5 -> 122095.23
D28: 03 Custos Operacionais | E28: =CNS!B24+CRR!B23 -> -64960.26 | F28: =CNS!C24+CRR!C23 -> -61297.63 | G28: =CNS!D24+CRR!D23 -> -67942.22 | H28: =CNS!E24+CRR!E23 -> -64575.13 | I28: =CNS!F24+CRR!F23 -> -81372.89 | J28: =CNS!G24+CRR!G23 -> -66612.71 | K28: =CNS!H24+CRR!H23 -> -59682.89 | L28: =CNS!I24+CRR!I23 -> 0 | ... P28: =CNS!M24+CRR!M23 -> 0 | Q28: =SUM(E28:P28) -> -466443.73 | R28: =Q28/$Q$7 -> -0.23719866 | T28: 03 Custos Operacionais | U28: =Q28/$U$5 -> -66634.819
D29: 03.1 Salários e Encargos | E29: =CNS!B25+CRR!B24 -> -25426.15 | F29: =CNS!C25+CRR!C24 -> -32678.58 | G29: =CNS!D25+CRR!D24 -> -28556.64 | H29: =CNS!E25+CRR!E24 -> -28209.13 | I29: =CNS!F25+CRR!F24 -> -33000.23 | J29: =CNS!G25+CRR!G24 -> -34300.75 | K29: =CNS!H25+CRR!H24 -> -28209.14 | L29: =CNS!I25+CRR!I24 -> 0 | ... P29: =CNS!M25+CRR!M24 -> 0 | Q29: =SUM(E29:P29) -> -210380.62 | R29: =Q29/$Q$7 -> -0.10698397 | T29: 03.1 Salários e Encargos | U29: =Q29/$U$5 -> -30054.374
D30: 03.2 Sistemas | E30: =CNS!B26+CRR!B25 -> -15523.46 | F30: =CNS!C26+CRR!C25 -> -9519.05 | G30: =CNS!D26+CRR!D25 -> -13097.35 | H30: =CNS!E26+CRR!E25 -> -10678.38 | I30: =CNS!F26+CRR!F25 -> -9918.7 | J30: =CNS!G26+CRR!G25 -> -9939.96 | K30: =CNS!H26+CRR!H25 -> -10299.93 | L30: =CNS!I26+CRR!I25 -> 0 | ... P30: =CNS!M26+CRR!M25 -> 0 | Q30: =SUM(E30:P30) -> -78976.83 | R30: =Q30/$Q$7 -> -0.040161753 | T30: 03.2 Sistemas | U30: =Q30/$U$5 -> -11282.404
D31: 03.3 Custo Tesouro mato grosso | E31: =CNS!B27+CRR!B26 -> -21367.88 | F31: =CNS!C27+CRR!C26 -> -19100 | G31: =CNS!D27+CRR!D26 -> -26235.23 | H31: =CNS!E27+CRR!E26 -> -25581.62 | I31: =CNS!F27+CRR!F26 -> -32735.46 | J31: =CNS!G27+CRR!G26 -> -22372 | K31: =CNS!H27+CRR!H26 -> -21173.82 | L31: =CNS!I27+CRR!I26 -> 0 | ... P31: =CNS!M27+CRR!M26 -> 0 | Q31: =SUM(E31:P31) -> -168566.01 | R31: =Q31/$Q$7 -> -0.08572016 | T31: 03.3 Custo Tesouro mato grosso | U31: =Q31/$U$5 -> -24080.859
... D45: 04.9 Veículos | E45: =CNS!B41+CRR!B40 -> 0 | F45: =CNS!C41+CRR!C40 -> 0 | G45: =CNS!D41+CRR!D40 -> 0 | H45: =CNS!E41+CRR!E40 -> 0 | I45: =CNS!F41+CRR!F40 -> 0 | J45: =CNS!G41+CRR!G40 -> 0 | K45: =CNS!H41+CRR!H40 -> 0 | L45: =CNS!I41+CRR!I40 -> 0 | ... P45: =CNS!M41+CRR!M40 -> 0 | Q45: =SUM(E45:P45) -> 0 | R45: =Q45/$Q$7 -> 0 | T45: 04.9 Veículos | U45: =Q45/$U$5 -> 0
D46: 04T Lucro / Prejuízo Operacional | E46: =CNS!B42+CRR!B41 -> -4814.48 | F46: =CNS!C42+CRR!C41 -> 73205.27 | G46: =CNS!D42+CRR!D41 -> 42036.29 | H46: =CNS!E42+CRR!E41 -> -15400.71 | I46: =CNS!F42+CRR!F41 -> 46543.06 | J46: =CNS!G42+CRR!G41 -> 86619.88 | K46: =CNS!H42+CRR!H41 -> -4722.47 | L46: =CNS!I42+CRR!I41 -> 0 | ... P46: =CNS!M42+CRR!M41 -> 0 | Q46: =SUM(E46:P46) -> 223466.84 | R46: =Q46/$Q$7 -> 0.11363865 | S46: =Q46/$Q$27 -> 0.26146668 | T46: 04T Lucro / Prejuízo Operacional | U46: =Q46/$U$5 -> 31923.834
D47: 05 Receitas e Despesas Financeiras | E47: =CNS!B43+CRR!B42 -> -1262.86 | F47: =CNS!C43+CRR!C42 -> -973.2 | G47: =CNS!D43+CRR!D42 -> -337.75 | H47: =CNS!E43+CRR!E42 -> -751.96 | I47: =CNS!F43+CRR!F42 -> 271.08 | J47: =CNS!G43+CRR!G42 -> -3516.44 | K47: =CNS!H43+CRR!H42 -> -129.72 | L47: =CNS!I43+CRR!I42 -> 0 | ... P47: =CNS!M43+CRR!M42 -> 0 | Q47: =SUM(E47:P47) -> -6700.85 | R47: =Q47/$Q$7 -> -0.0034075549 | T47: 05 Receitas e Despesas Financeiras | U47: =Q47/$U$5 -> -957.26429
D48: 06 Outras Receitas e Despesas Não Operacionais | E48: =CNS!B44+CRR!B43 -> 8.63 | F48: =CNS!C44+CRR!C43 -> 1.89 | G48: =CNS!D44+CRR!D43 -> 0.6 | H48: =CNS!E44+CRR!E43 -> 3.45 | I48: =CNS!F44+CRR!F43 -> 5.19 | J48: =CNS!G44+CRR!G43 -> 0 | K48: =CNS!H44+CRR!H43 -> -50 | L48: =CNS!I44+CRR!I43 -> 0 | ... P48: =CNS!M44+CRR!M43 -> 0 | Q48: =SUM(E48:P48) -> -30.24 | R48: =Q48/$Q$7 -> -1.5377819e-05 | T48: 06 Outras Receitas e Despesas Não Operacionais | U48: =Q48/$U$5 -> -4.32
D49: 06T Lucro / Prejuízo Líquido | E49: =CNS!B45+CRR!B44 -> -6068.71 | F49: =CNS!C45+CRR!C44 -> 72233.96 | G49: =CNS!D45+CRR!D44 -> 41699.14 | H49: =CNS!E45+CRR!E44 -> -16149.22 | I49: =CNS!F45+CRR!F44 -> 46819.33 | J49: =CNS!G45+CRR!G44 -> 83103.44 | K49: =CNS!H45+CRR!H44 -> -4902.19 | L49: =CNS!I45+CRR!I44 -> 0 | ... P49: =CNS!M45+CRR!M44 -> 0 | Q49: =SUM(E49:P49) -> 216735.75 | R49: =Q49/$Q$7 -> 0.11021571 | S49: =Q49/$Q$27 -> 0.25359099 | T49: 06T Lucro / Prejuízo Líquido | U49: =Q49/$U$5 -> 30962.25
D50: 07 Despesas com Investimentos e Empréstimos | E50: =CNS!B46+CRR!B45 -> -10236.57 | F50: =CNS!C46+CRR!C45 -> -10119.25 | G50: =CNS!D46+CRR!D45 -> -8739.58 | H50: =CNS!E46+CRR!E45 -> -10636.86 | I50: =CNS!F46+CRR!F45 -> -9270.03 | J50: =CNS!G46+CRR!G45 -> -9126.12 | K50: =CNS!H46+CRR!H45 -> -9386.01 | L50: =CNS!I46+CRR!I45 -> 0 | ... P50: =CNS!M46+CRR!M45 -> 0 | Q50: =SUM(E50:P50) -> -67514.42 | R50: =Q50/$Q$7 -> -0.034332822 | T50: 07 Despesas com Investimentos e Empréstimos | U50: =Q50/$U$5 -> -9644.9171
D51: 07.1 Investimentos em Imobilizado | E51: =CNS!B47+CRR!B46 -> 0 | F51: =CNS!C47+CRR!C46 -> -278.09 | G51: =CNS!D47+CRR!D46 -> 0 | H51: =CNS!E47+CRR!E46 -> -558.89 | I51: =CNS!F47+CRR!F46 -> 0 | J51: =CNS!G47+CRR!G46 -> 0 | K51: =CNS!H47+CRR!H46 -> 0 | L51: =CNS!I47+CRR!I46 -> 0 | ... P51: =CNS!M47+CRR!M46 -> 0 | Q51: =SUM(E51:P51) -> -836.98 | R51: =Q51/$Q$7 -> -0.0004256259 | T51: 07.1 Investimentos em Imobilizado | U51: =Q51/$U$5 -> -119.56857
D52: 07.2 Empréstimos e Dívidas | E52: =CNS!B48+CRR!B47 -> -10236.57 | F52: =CNS!C48+CRR!C47 -> -9841.16 | G52: =CNS!D48+CRR!D47 -> -8739.58 | H52: =CNS!E48+CRR!E47 -> -10077.97 | I52: =CNS!F48+CRR!F47 -> -9270.03 | J52: =CNS!G48+CRR!G47 -> -9126.12 | K52: =CNS!H48+CRR!H47 -> -9386.01 | L52: =CNS!I48+CRR!I47 -> 0 | ... P52: =CNS!M48+CRR!M47 -> 0 | Q52: =SUM(E52:P52) -> -66677.44 | R52: =Q52/$Q$7 -> -0.033907197 | T52: 07.2 Empréstimos e Dívidas | U52: =Q52/$U$5 -> -9525.3486
D53: 07T Lucro / Prejuízo Final | E53: =CNS!B49+CRR!B48 -> -16305.28 | F53: =CNS!C49+CRR!C48 -> 62114.71 | G53: =CNS!D49+CRR!D48 -> 32959.56 | H53: =CNS!E49+CRR!E48 -> -26786.08 | I53: =CNS!F49+CRR!F48 -> 37549.3 | J53: =CNS!G49+CRR!G48 -> 73977.32 | K53: =CNS!H49+CRR!H48 -> -14288.2 | L53: =CNS!I49+CRR!I48 -> 0 | ... P53: =CNS!M49+CRR!M48 -> 0 | Q53: =SUM(E53:P53) -> 149221.33 | R53: =Q53/$Q$7 -> 0.075882892 | S53: =Q53/$Q$27 -> 0.17459595 | T53: 07T Lucro / Prejuízo Final | U53: =Q53/$U$5 -> 21317.333
D58: EBITDA | E58: =E46+(-E21) -> 96700.12 | F58: =F46+(-F21) -> 97237.61 | G58: =G46+(-G21) -> 69380.73 | H58: =H46+(-H21) -> 74481.45 | I58: =I46+(-I21) -> 69807.3 | J58: =J46+(-J21) -> 111794.45 | K58: =K46+(-K21) -> 103892.87 | L58: =L46+(-L21) -> 0 | ... Q58: =Q46+(-Q21) -> 623294.53
D59: Caixa | E59: =IF(E7>0,Caixa!F6,0) -> 328679.42 | F59: =IF(F7>0,Caixa!G6,0) -> 326651.91 | G59: =IF(G7>0,Caixa!H6,0) -> 359161.59 | H59: =IF(H7>0,Caixa!I6,0) -> 358806.96 | I59: =IF(I7>0,Caixa!J6,0) -> 423235.48 | J59: =IF(J7>0,Caixa!K6,0) -> 430815.65 | K59: =IF(K7>0,Caixa!L6,0) -> 358819.06 | L59: =IF(L7>0,Caixa!M6,0) -> 0 | ... P59: =IF(P7>0,Caixa!Q6,0) -> 0
D60: Caixa projetado | E60: ='Orçamento 2026'!C129 -> 328679.42 | F60: ='Orçamento 2026'!D129 -> 375009.95 | G60: ='Orçamento 2026'!E129 -> 422405.78 | H60: ='Orçamento 2026'!F129 -> 390575.13 | I60: ='Orçamento 2026'!G129 -> 437901.91 | J60: ='Orçamento 2026'!H129 -> 427111.48 | K60: ='Orçamento 2026'!I129 -> 365928.65 | L60: ='Orçamento 2026'!J129 -> 332532.8 | ... P60: ='Orçamento 2026'!N129 -> 372170.37
D61: Variação | E61: =IF(E59>0,E59-E60,0) -> 0 | F61: =IF(F59>0,F59-F60,0) -> -48358.043 | G61: =IF(G59>0,G59-G60,0) -> -63244.188 | H61: =IF(H59>0,H59-H60,0) -> -31768.175 | I61: =IF(I59>0,I59-I60,0) -> -14666.434 | J61: =IF(J59>0,J59-J60,0) -> 3704.1715 | K61: =IF(K59>0,K59-K60,0) -> -7109.5936 | L61: =IF(L59>0,L59-L60,0) -> 0 | ... P61: =IF(P59>0,P59-P60,0) -> 0
D63: Margem EBITDA | E63: =IF(E58<>0,E58/E7,"") -> 0.34236926 | F63: =IF(F58<>0,F58/F7,"") -> 0.3411891 | G63: =IF(G58<>0,G58/G7,"") -> 0.25433159 | H63: =IF(H58<>0,H58/H7,"") -> 0.27924893 | I63: =IF(I58<>0,I58/I7,"") -> 0.25170788 | J63: =IF(J58<>0,J58/J7,"") -> 0.37072304 | K63: =IF(K58<>0,K58/K7,"") -> 0.37022739 | L63: =IF(L58<>0,L58/L7,"") | ... Q63: =IF(Q58<>0,Q58/Q7,"") -> 0.31696133
D64: Margem Bruta | E64: =IF(E34<>0,E34/E7,"") -> 0.066091065 | F64: =IF(F34<>0,F34/F7,"") -> 0.34168002 | G64: =IF(G34<>0,G34/G7,"") -> 0.24440463 | H64: =IF(H34<>0,H34/H7,"") -> 0.021487127 | I64: =IF(I34<>0,I34/I7,"") -> 0.2424349 | J64: =IF(J34<>0,J34/J7,"") -> 0.35445416 | K64: =IF(K34<>0,K34/K7,"") -> 0.091407042 | L64: =IF(L34<>0,L34/L7,"") | ... Q64: =IF(Q34<>0,Q34/Q7,"") -> 0.19742133
D65: Margem Lucro Liquido | E65: =IF(E49<>0,E49/E7,"") -> -0.021486424 | F65: =IF(F49<>0,F49/F7,"") -> 0.25345584 | G65: =IF(G49<>0,G49/G7,"") -> 0.15285813 | H65: =IF(H49<>0,H49/H7,"") -> -0.060547322 | I65: =IF(I49<>0,I49/I7,"") -> 0.16881894 | J65: =IF(J49<>0,J49/J7,"") -> 0.27558041 | K65: =IF(K49<>0,K49/K7,"") -> -0.017469197 | L65: =IF(L49<>0,L49/L7,"") | ... Q65: =IF(Q49<>0,Q49/Q7,"") -> 0.11021571
D66: Margem Lucro Final | E66: =IF(E53<>0,E53/E7,"") -> -0.057729263 | F66: =IF(F53<>0,F53/F7,"") -> 0.21794923 | G66: =IF(G53<>0,G53/G7,"") -> 0.12082112 | H66: =IF(H53<>0,H53/H7,"") -> -0.10042748 | I66: =IF(I53<>0,I53/I7,"") -> 0.1353935 | J66: =IF(J53<>0,J53/J7,"") -> 0.24531716 | K66: =IF(K53<>0,K53/K7,"") -> -0.050916709 | L66: =IF(L53<>0,L53/L7,"") | ... Q66: =IF(Q53<>0,Q53/Q7,"") -> 0.075882892

Sheet Caixa
T4: Distribuição
D5: CNPJ | E5: dez/25 | F5: 46023 | G5: fev/26 | H5: 46082 | I5: 46113 | J5: 46143 | K5: 46174 | L5: jul/26 | M5: ago/26 | N5: set/26 | O5: out/26 | P5: nov/26 | Q5: dez/26 | R5: Caixa final
D6: Caixa | E6: =E7+E10+E13+E16 -> 503909.51 | F6: =F7+F10+F13+F16 -> 328679.42 | G6: =G7+G10+G13+G16 -> 326651.91 | H6: =H7+H10+H13+H16 -> 359161.59 | I6: =I7+I10+I13+I16 -> 358806.96 | J6: =J7+J10+J13+J16 -> 423235.48 | K6: =K7+K10+K13+K16 -> 430815.65 | L6: =L7+L10+L13+L16 -> 358819.06 | ... Q6: =Q7+Q10+Q13+Q16 -> 0 | R6: =Q6 -> 0 | T6: Caixa final | U6: =R6 -> 0
D7: 1. BTG | E7: =E8+E9 -> 357656.17 | F7: =F8+F9 -> 224733.63 | G7: =G8+G9 -> 153902.69 | H7: =H8+H9 -> 228703.26 | I7: =I8+I9 -> 275711.18 | J7: =J8+J9 -> 307601.17 | K7: =K8+K9 -> 238663.08 | L7: =L8+L9 -> 252485.61 | ... Q7: =Q8+Q9 -> 0 | T7: -> Caixa | U7: 0
D8: 1.1 Investimentos | E8: 119132.9 | F8: 173160.08 | G8: =117727.34 -> 117727.34 | H8: 225718.41 | I8: =226743.76+971 -> 227714.76 | J8: =15000+254766.64 -> 269766.64 | K8: 148542.94 | L8: =252449.43 -> 252449.43 | T8: Bônus | U8: 0
D9: 1.2 Conta | E9: 238523.27 | F9: 51573.55 | G9: 36175.35 | H9: 2984.85 | I9: 47996.42 | J9: 37834.53 | K9: 90120.14 | L9: 36.18 | T9: Distribuição | U9: =U13 -> 59688.532
D10: 2. Consultoria | E10: =E11+E12 -> 102101.99 | F10: =F11+F12 -> 65399.48 | G10: =G11+G12 -> 137635.28 | H10: =H11+H12 -> 89865.77 | I10: =I11+I12 -> 49977.98 | J10: =J11+J12 -> 75090.4 | K10: =K11+K12 -> 163543.77 | L10: =L11+L12 -> 72044.26 | ... Q10: =Q11+Q12 -> 0 | T10: Saldo | U10: =U6-U8-U9 -> -59688.532
D11: 2.1 Investimentos | E11: 95400 | F11: 56600 | G11: 85600 | H11: 86880.92 | I11: 49432.66 | J11: 70999.62 | K11: 71750.61 | L11: 39676.26
D12: 2.2 Conta | E12: 6701.99 | F12: 8799.48 | G12: 52035.28 | H12: 2984.85 | I12: 545.32 | J12: 4090.78 | K12: 91793.16 | L12: 32368 | T12: Lucro Final | U12: =Consolidated!Q53 -> 149221.33
D13: 3. Corretora | E13: =E14+E15 -> 44151.35 | F13: =F14+F15 -> 38546.31 | G13: =G14+G15 -> 35113.94 | H13: =H14+H15 -> 40592.56 | I13: =I14+I15 -> 33117.8 | J13: =J14+J15 -> 40543.91 | K13: =K14+K15 -> 28608.8 | L13: =L14+L15 -> 34289.19 | ... Q13: =Q14+Q15 -> 0 | T13: 0.4 | U13: =U12*T13 -> 59688.532
D14: 3.1 Investimentos | E14: 29000 | F14: 23500 | G14: 17500 | H14: 27378.48 | I14: 18567.39 | J14: 29948.48 | K14: 10714.04 | L14: 10844.25 | T14: Distribuição | U14: =U9/Consolidated!Q53 -> 0.4
D15: 3.2 Conta | E15: 15151.35 | F15: 15046.31 | G15: 17613.94 | H15: 13214.08 | I15: 14550.41 | J15: 10595.43 | K15: 17894.76 | L15: 23444.94
D16: 4. Holding | E16: =E17+E18 -> 0 | F16: =F17+F18 -> 0 | G16: =G17+G18 -> 0 | H16: =H17+H18 -> 0 | I16: =I17+I18 -> 0 | J16: =J17+J18 -> 0 | K16: =K17+K18 -> 0 | L16: =L17+L18 -> 0 | ... Q16: =Q17+Q18 -> 0
D17: 4.1 Investimentos
D18: 4.2 Conta
D19: Δ Caixa | F19: =F6-E6 -> -175230.09 | G19: =G6-F6 -> -2027.51 | H19: =H6-G6 -> 32509.68 | I19: =IF(I6>0,I6-H6,0) -> -354.63 | J19: =IF(J6>0,J6-I6,0) -> 64428.52 | K19: =IF(K6>0,K6-J6,0) -> 7580.17 | L19: =IF(L6>0,L6-K6,0) -> -71996.59 | M19: =IF(M6>0,M6-L6,0) -> 0 | N19: =IF(N6>0,N6-M6,0) -> 0 | O19: =IF(O6>0,O6-N6,0) -> 0 | P19: =IF(P6>0,P6-O6,0) -> 0 | Q19: =IF(Q6>0,Q6-P6,0) -> 0
A42: Sim | D42: Check | F42: Meta | H42: =SUM(H43:H57) -> 30000
A43: Não | D43: Não | F43: Gaioso | G43: 15000 | H43: =IF(D43=$A$42,G43,0) -> 0
D44: Sim | F44: Augusto | G44: 15000 | H44: =IF(D44=$A$42,G44,0) -> 15000
D45: Não | F45: Sidney | G45: 15000 | H45: =IF(D45=$A$42,G45,0) -> 0
D46: Sim | F46: Lamour (+R) | G46: 15000 | H46: =IF(D46=$A$42,G46,0) -> 15000
D47: Não | F47: Pedro | G47: 15000 | H47: =IF(D47=$A$42,G47,0) -> 0
D48: Não | F48: Cris | G48: 15000 | H48: =IF(D48=$A$42,G48,0) -> 0
D49: Não | F49: Bruno | G49: 15000 | H49: =IF(D49=$A$42,G49,0) -> 0
D50: Não | F50: Mario | H50: =IF(D50=$A$42,G50,0) -> 0
D51: Não | F51: Elias | H51: =IF(D51=$A$42,G51,0) -> 0
D52: Não | F52: Igor | H52: =IF(D52=$A$42,G52,0) -> 0
D53: Não | F53: Nhat | H53: =IF(D53=$A$42,G53,0) -> 0
D54: Não | F54: Samuel | H54: =IF(D54=$A$42,G54,0) -> 0
D55: Não | F55: Bianka | H55: =IF(D55=$A$42,G55,0) -> 0
D56: Não | F56: Noemy | H56: =IF(D56=$A$42,G56,0) -> 0
D57: Não | F57: Vale | H57: =IF(D57=$A$42,G57,0) -> 0
D61: Lucro | G61: =I6 -> 358806.96 | H61: Total
D62: Gaioso | E62: 0.2847 | G62: =$G$61*E62 -> 102152.34 | H62: =G62+H43 -> 102152.34
D63: Augusto | E63: 0.2847 | G63: =$G$61*E63 -> 102152.34 | H63: =G63+H44 -> 117152.34
D64: Sidney | E64: 0.2847 | G64: =$G$61*E64 -> 102152.34 | H64: =G64+H45 -> 102152.34
D65: Lamour | E65: 0.0657 | G65: =$G$61*E65 -> 23573.617 | H65: =G65+H46 -> 38573.617
D66: Pedro | E66: 0.05 | G66: =$G$61*E66 -> 17940.348 | H66: =G66+H47 -> 17940.348
D67: Igor | E67: 0.03 | G67: =$G$61*E67 -> 10764.209 | H67: =G67+H52 -> 10764.209
D68: Cris | E68: 0.0001 | G68: =$G$61*E68 -> 35.880696 | H68: =G68+H48 -> 35.880696
D69: Elias | E69: 0.0001 | G69: =$G$61*E69 -> 35.880696 | H69: =G69+H50 -> 35.880696
C77: TOTAL | D77: 44622 | F77: %
C78: SIDNEY | D78: 1491 | F78: =D78/$D$77 -> 0.033414011
C79: AUGUSTO | D79: 1491 | F79: =D79/$D$77 -> 0.033414011
C80: GAIOSO | D80: 1491 | F80: =D80/$D$77 -> 0.033414011
B81: 10000 | C81: HOLDING | D81: 40149 | F81: =D81/$D$77 -> 0.89975797
C82: Sidney | D82: 2570 | F82: =D82/$B$81 -> 0.257
C83: Augusto | D83: 2570 | F83: =D83/$B$81 -> 0.257
C84: Gaioso | D84: 2570 | F84: =D84/$B$81 -> 0.257
C85: Pedro | D85: 668 | F85: =D85/$B$81 -> 0.0668
C86: Igor | D86: 150 | F86: =D86/$B$81 -> 0.015
C87: Thiago | D87: 150 | F87: =D87/$B$81 -> 0.015
C88: Dyogo | D88: 320 | F88: =D88/$B$81 -> 0.032
C89: Mario | D89: 1 | F89: =D89/$B$81 -> 0.0001
C90: Cristiano | D90: 1 | F90: =D90/$B$81 -> 0.0001
C91: Elias | D91: 1 | F91: =D91/$B$81 -> 0.0001
C92: Tesouraria | D92: 999 | F92: =D92/$B$81 -> 0.0999

Sheet Orçamento 2026
B1: ORÇAMENTO 2026 – DRE CONSOLIDADA (Grupo CVM + SUSEP)
B2: Premissas: AuM × ROA médio | Custos: IPCA 5,5% a.a. | Realizado: alimentado automaticamente da aba Consolidated
B4: PARÂMETROS E PREMISSAS (azul = entrada manual | preto = calculado automaticamente)
B5: AuM Alvo Dez/26 (R$) | C5: =J6 -> 280000000 | D5: Meta de AuM para Dez/26 – EDITÁVEL | I5: Aum0 | J5: 300000000 | K5: ROA | L5: 0.010918698 | N5: Consultoria | O5: 0.84359677 | T5: Consultoria | U5: Corretora
B6: ROA Médio Mensal (% a.m.) | C6: =(1+L5)^(1/12)-1 -> 0.00090536954 | D6: Calculado automaticamente – Jan–Abr/26 | I6: Meta | J6: 280000000 | K6: g | L6: 0 | N6: Corretora | O6: 0.15640323 | S6: Presunção | T6: 0.32 | U6: 0.32
B7: IPCA Anual 2026 | C7: 0.055 | D7: Taxa IPCA projetada – EDITÁVEL | I7: Cap | J7: =J6-J5 -> -20000000 | S7: IRPJ + CSLL | T7: 0.15 | U7: 0.15
B8: IPCA Mensal (composto) | C8: =(1+C7)^(1/12)-1 -> 0.0044716989 | D8: Calculado a partir do IPCA anual | I8: Cap mensal | J8: =J7/12 -> -1666666.7 | S8: Add IRPJ - 240k | T8: -0.1 | U8: 0.1
B9: IR Trimestral | C9: -0.06 | S9: CSLL | T9: 0.09 | U9: 0.068 | V9: =(T9*$O$5)+(U9*$O$6) -> 0.086559129
B10: % Impostos s/ Receita Bruta | C10: -0.14 | I10: Impostos sobre Receita | S10: PIS/COFINS | T10: 0.0365 | U10: 0.0365 | V10: =(T10*$O$5)+(U10*$O$6) -> 0.0365
B11: % Comissões s/ Receita Bruta | C11: -0.43 | I11: PIS | J11: -0.0065 | S11: ISS | T11: 0.05 | U11: 0.05 | V11: =(T11*$O$5)+(U11*$O$6) -> 0.05
B12: Descontos Incondicionais (méd. mensal) | C12: =AVERAGE(Consolidated!E24:H24) -> -1257.6075 | D12: Média Jan–Abr/26 | I12: COFINS | J12: -0.03 | S12: MÉDIA | T12: 18,5 - 19 | U12: 0.16
B13: Devoluções de Vendas (méd. mensal) | C13: 0 | D13: Média Jan–Abr/26 | I13: ISS | J13: -0.05
B14: Base Custos Operacionais (méd.) | C14: =AVERAGE(Consolidated!E28:H28) -> -64693.81 | D14: Média Jan–Abr/26 – IPCA composto mês a mês | J14: =SUM(J11:J13) -> -0.0865 | S14: Sidney | T14: 46360714 | U14: 29004.77
B15: Base Despesas Operacionais (méd.) | C15: =AVERAGE(Consolidated!E35:H35) -> -23355.48 | D15: Média Jan–Abr/26 – IPCA composto mês a mês | I15: Impostos sobre Presunção | K15: Excedente | L15: -0.1 | S15: Pedro | T15: 19600204 | U15: 16584.42
B16: Base Desp. Financeiras Líq. (méd.) | C16: =-0.4% -> -0.004 | D16: Média Jan–Abr/26 | I16: IRPJ | J16: -0.15 | S16: Total | T16: =T14+T15 -> 65960919 | U16: =U14+U15 -> 45589.19
B17: Base Desp. Invest./Empréstimos (méd.) | C17: -0.039277297 | D17: Média Jan–Abr/26 – IPCA composto mês a mês | I17: CSLL | J17: -0.086559129
B18: Base Outras Rec./Desp. N.Op. (méd.) | C18: 0 | D18: Média Jan–Abr/26 (valor imaterial) | J18: =J16+J17 -> -0.23655913
B19: ROA Consultoria | C19: 0.0005983766
B20: ROA Planejamento | C20: 4.1748034e-05 | S20: *Jan-Abril com números projetados
B21: RPPS | C21: 21495.8
B22: ROA Corretora | C22: 0.00013013201
B23: Mato grosso | C23: 34000
B25: TRAJETÓRIA DE AuM (Jan–Abr = realizados da aba Consolidado | Mai–Dez = interpolação linear até meta)
B26: AuM (R$) | C26: Jan/26 | D26: Fev/26 | E26: Mar/26 | F26: Abr/26 | G26: Mai/26 | H26: Jun/26 | I26: Jul/26 | J26: Ago/26 | K26: Set/26 | L26: Out/26 | M26: Nov/26 | N26: Dez/26 | O26: Total 2026
B27: AuM Projetado (R$) | C27: =Consolidated!E4 -> 290504767 | D27: =Consolidated!F4 -> 304511145 | E27: =Consolidated!G4 -> 309415143 | F27: =Consolidated!H4 -> 311856596 | G27: =F27*(1+$L$6) -> 311856596 | H27: =G27-T15 -> 2.9225639e+08 | I27: =H27*(1+$L$6) -> 2.9225639e+08 | J27: =I27-T14 -> 2.4589568e+08 | K27: =J27*(1+$L$6) -> 2.4589568e+08 | L27: =K27*(1+$L$6) -> 2.4589568e+08 | M27: =L27*(1+$L$6) -> 2.4589568e+08 | N27: =M27*(1+$L$6) -> 2.4589568e+08 | O27: =N27 -> 2.4589568e+08
B29: DRE ORÇADA 2026
B30: Categoria | C30: Jan/26 | D30: Fev/26 | E30: Mar/26 | F30: Abr/26 | G30: Mai/26 | H30: Jun/26 | I30: Jul/26 | J30: Ago/26 | K30: Set/26 | L30: Out/26 | M30: Nov/26 | N30: Dez/26 | O30: Total 2026 | X30: YTD (maio)
B31: 01 Receitas Operacionais | C31: =SUM(C32:C36) -> 279259.03 | D31: =SUM(D32:D36) -> 290047.53 | E31: =SUM(E32:E36) -> 293824.87 | F31: =SUM(F32:F36) -> 261705.42 | G31: =SUM(G32:G36) -> 295705.42 | H31: =SUM(H32:H36) -> 275752.11 | I31: =SUM(I32:I36) -> 275752.11 | J31: =SUM(J32:J36) -> 238778.86 | ... N31: =SUM(N32:N36) -> 238778.86 | O31: =SUM(C31:N31) -> 3165940.8 | W31: 01 Receitas Operacionais | X31: =SUM(C31:G31) -> 1420542.3
B32: Consultoria | C32: =C27*$C$19 -> 173831.26 | D32: =D27*$C$19 -> 182212.34 | E32: =E27*$C$19 -> 185146.78 | F32: =F27*$C$19 -> 186607.69 | G32: =G27*$C$19 -> 186607.69 | H32: =G32-U15 -> 170023.27 | I32: =H32*(1+$L$6) -> 170023.27 | J32: =I32*(1+$L$6)-U14 -> 141018.5 | K32: =J32*(1+$L$6) -> 141018.5 | L32: =K32*(1+$L$6) -> 141018.5 | M32: =L32*(1+$L$6) -> 141018.5 | N32: =M32*(1+$L$6) -> 141018.5 | O32: =SUM(C32:N32) -> 1959544.8 | W32: Consultoria | X32: =SUM(C32:G32) -> 914405.76
B33: Planejamento | C33: =C27*$C$20 -> 12128.003 | D33: =D27*$C$20 -> 12712.742 | E33: =E27*$C$20 -> 12917.474 | F33: =F27*$C$20 -> 13019.4 | G33: =G27*$C$20 -> 13019.4 | H33: =H27*$C$20 -> 12201.13 | I33: =I27*$C$20 -> 12201.13 | J33: =J27*$C$20 -> 10265.661 | ... N33: =N27*$C$20 -> 10265.661 | O33: =SUM(C33:N33) -> 139527.58 | W33: Planejamento | X33: =SUM(C33:G33) -> 63797.019
B34: Mato Grosso | C34: =CNS!B11 -> 34000 | D34: =CNS!C11 -> 34000 | E34: =CNS!D11 -> 34000 | F34: =CNS!E11 -> 0,00 | G34: =$C$23 -> 34000 | H34: =$C$23 -> 34000 | I34: =$C$23 -> 34000 | J34: =$C$23 -> 34000 | K34: =$C$23 -> 34000 | L34: =$C$23 -> 34000 | M34: =$C$23 -> 34000 | N34: =$C$23 -> 34000 | O34: =SUM(C34:N34) -> 374000 | W34: Mato Grosso | X34: =SUM(C34:G34) -> 136000
B35: RPPS | C35: =$C$21 -> 21495.8 | D35: =$C$21 -> 21495.8 | E35: =$C$21 -> 21495.8 | F35: =$C$21 -> 21495.8 | G35: =$C$21 -> 21495.8 | H35: =$C$21 -> 21495.8 | I35: =$C$21 -> 21495.8 | J35: =$C$21 -> 21495.8 | ... N35: =$C$21 -> 21495.8 | O35: =SUM(C35:N35) -> 257949.6 | W35: RPPS | X35: =SUM(C35:G35) -> 107479
B36: Corretora | C36: =C27*$C$22 -> 37803.97 | D36: =D27*$C$22 -> 39626.649 | E36: =E27*$C$22 -> 40264.816 | F36: =F27*$C$22 -> 40582.527 | G36: =G27*$C$22 -> 40582.527 | H36: =H27*$C$22 -> 38031.913 | I36: =I27*$C$22 -> 38031.913 | J36: =J27*$C$22 -> 31998.9 | ... N36: =N27*$C$22 -> 31998.9 | O36: =SUM(C36:N36) -> 434918.81 | W36: Corretora | X36: =SUM(C36:G36) -> 198860.49
B37: Presunção | C37: =C31*$T$6 -> 89362.889 | D37: =D31*$T$6 -> 92815.211 | E37: =E31*$T$6 -> 94023.959 | F37: =F31*$T$6 -> 83745.733 | G37: =G31*$T$6 -> 94625.733 | H37: =H31*$T$6 -> 88240.676 | I37: =I31*$T$6 -> 88240.676 | J37: =J31*$T$6 -> 76409.235 | ... N37: =N31*$T$6 -> 76409.235 | O37: =SUM(C37:N37) -> 1013101.1
B38: 02 Deduções da Receita Bruta | C38: =SUM(C39:C43) -> -198990.4 | D38: =SUM(D39:D43) -> -142721.51 | E38: =SUM(E39:E43) -> -144874.59 | F38: =SUM(F39:F43) -> -192974.39 | G38: =SUM(G39:G43) -> -145946.5 | H38: =SUM(H39:H43) -> -134573.12 | I38: =SUM(I39:I43) -> -184562.89 | J38: =SUM(J39:J43) -> -113498.36 | ... N38: =SUM(N39:N43) -> -113498.36 | O38: =SUM(C38:N38) -> -1757333.8
B39: 02.1 Impostos Sobre Vendas | C39: =Consolidated!E21-'Orçamento 2026'!C40 -> -55400.75 | D39: =D31*$C$10 -> -40606.655 | E39: =E31*$C$10 -> -41135.482 | F39: =F31*$C$10 -> -36638.758 | G39: =G31*$C$10 -> -41398.758 | H39: =H31*$C$10 -> -38605.296 | I39: =I31*$C$10 -> -38605.296 | J39: =J31*$C$10 -> -33429.041 | K39: =K31*$C$10 -> -33429.041 | ... O39: =O31*$C$10 -> -443231.71
B40: 02. 1. 1 - IRPJ Trimestral | C40: -46113.85 | F40: =SUM(C31:E31)*$C$9 -> -51787.886 | I40: =SUM(F31:H31)*$C$9 -> -49989.777 | L40: =SUM(I31:K31)*$C$9 -> -45198.59 | O40: =SUM(C40:N40) -> -193090.1
B41: 02.2 Comissões Sobre Vendas | C41: =(C32+C33+C36)*$C$11 -> -96218.188 | D41: =(D32+D33+D36)*$C$11 -> -100857.25 | E41: =(E32+E33+E36)*$C$11 -> -102481.5 | F41: =(F32+F33+F36)*$C$11 -> -103290.14 | G41: =(G32+G33+G36)*$C$11 -> -103290.14 | H41: =(H32+H33+H36)*$C$11 -> -94710.214 | I41: =(I32+I33+I36)*$C$11 -> -94710.214 | J41: =(J32+J33+J36)*$C$11 -> -78811.716 | ... N41: =(N32+N33+N36)*$C$11 -> -78811.716 | O41: =SUM(C41:N41) -> -1089616.2
B42: 02.3 Descontos Incondicionais | C42: =$C$12 -> -1257.6075 | D42: =$C$12 -> -1257.6075 | E42: =$C$12 -> -1257.6075 | F42: =$C$12 -> -1257.6075 | G42: =$C$12 -> -1257.6075 | H42: =$C$12 -> -1257.6075 | I42: =$C$12 -> -1257.6075 | J42: =$C$12 -> -1257.6075 | ... N42: =$C$12 -> -1257.6075 | O42: =SUM(C42:N42) -> -15091.29
B43: 02.4 Devoluções de Vendas | C43: =$C$13 -> 0 | D43: =$C$13 -> 0 | E43: =$C$13 -> 0 | F43: =$C$13 -> 0 | G43: =$C$13 -> 0 | H43: =$C$13 -> 0 | I43: =$C$13 -> 0 | J43: =$C$13 -> 0 | ... N43: =$C$13 -> 0 | O43: =SUM(C43:N43) -> 0
B44: 02T Receita Líquida de Vendas | C44: =C31+C38 -> 80268.633 | D44: =D31+D38 -> 147326.03 | E44: =E31+E38 -> 148950.28 | F44: =F31+F38 -> 68731.03 | G44: =G31+G38 -> 149758.92 | H44: =H31+H38 -> 141178.99 | I44: =I31+I38 -> 91189.218 | J44: =J31+J38 -> 125280.5 | ... N44: =N31+N38 -> 125280.5 | O44: =SUM(C44:N44) -> 1408607
B45: 03 Custos Operacionais | C45: =$C$14*(1+$C$8)^0 -> -64693.81 | D45: =$C$14*(1+$C$8)^1 -> -64983.101 | E45: =$C$14*(1+$C$8)^2 -> -65273.686 | F45: =$C$14*(1+$C$8)^3 -> -65565.57 | G45: =$C$14*(1+$C$8)^4 -> -65858.76 | H45: =$C$14*(1+$C$8)^5 -> -66153.26 | I45: =$C$14*(1+$C$8)^6 -> -66449.078 | J45: =$C$14*(1+$C$8)^7 -> -66746.218 | K45: =$C$14*(1+$C$8)^8 -> -67044.687 | L45: =$C$14*(1+$C$8)^9 -> -67344.491 | M45: =$C$14*(1+$C$8)^10 -> -67645.635 | N45: =$C$14*(1+$C$8)^11 -> -67948.126 | O45: =SUM(C45:N45) -> -795706.42
B46: 03T Lucro Bruto | C46: =C44+C45 -> 15574.823 | D46: =D44+D45 -> 82342.925 | E46: =E44+E45 -> 83676.595 | F46: =F44+F45 -> 3165.4592 | G46: =G44+G45 -> 83900.156 | H46: =H44+H45 -> 75025.734 | I46: =I44+I45 -> 24740.14 | J46: =J44+J45 -> 58534.278 | ... N46: =N44+N45 -> 57332.371 | O46: =SUM(C46:N46) -> 612900.57
B47: 04 Despesas Operacionais | C47: =$C$15*(1+$C$8)^0 -> -23355.48 | D47: =$C$15*(1+$C$8)^1 -> -23459.919 | E47: =$C$15*(1+$C$8)^2 -> -23564.824 | F47: =$C$15*(1+$C$8)^3 -> -23670.199 | G47: =$C$15*(1+$C$8)^4 -> -23776.045 | H47: =$C$15*(1+$C$8)^5 -> -23882.364 | I47: =$C$15*(1+$C$8)^6 -> -23989.159 | J47: =$C$15*(1+$C$8)^7 -> -24096.432 | K47: =$C$15*(1+$C$8)^8 -> -24204.184 | L47: =$C$15*(1+$C$8)^9 -> -24312.417 | M47: =$C$15*(1+$C$8)^10 -> -24421.135 | N47: =$C$15*(1+$C$8)^11 -> -24530.339 | O47: =SUM(C47:N47) -> -287262.5
B48: 04T Lucro / Prejuízo Operacional | C48: =C46+C47 -> -7780.6573 | D48: =D46+D47 -> 58883.006 | E48: =E46+E47 -> 60111.771 | F48: =F46+F47 -> -20504.74 | G48: =G46+G47 -> 60124.111 | H48: =H46+H47 -> 51143.37 | I48: =I46+I47 -> 750.98104 | J48: =J46+J47 -> 34437.847 | ... N48: =N46+N47 -> 32802.032 | O48: =SUM(C48:N48) -> 325638.07
B49: 05 Rec. e Despesas Financeiras | C49: =C31*$C$16 -> -1117.0361 | D49: =D31*$C$16 -> -1160.1901 | E49: =E31*$C$16 -> -1175.2995 | F49: =F31*$C$16 -> -1046.8217 | G49: =G31*$C$16 -> -1182.8217 | H49: =H31*$C$16 -> -1103.0085 | I49: =I31*$C$16 -> -1103.0085 | J49: =J31*$C$16 -> -955.11544 | ... N49: =N31*$C$16 -> -955.11544 | O49: =SUM(C49:N49) -> -12663.763
B50: 06 Outras Rec./Despesas N.Op. | C50: =$C$18 -> 0 | D50: =$C$18 -> 0 | E50: =$C$18 -> 0 | F50: =$C$18 -> 0 | G50: =$C$18 -> 0 | H50: =$C$18 -> 0 | I50: =$C$18 -> 0 | J50: =$C$18 -> 0 | ... N50: =$C$18 -> 0 | O50: =SUM(C50:N50) -> 0
B51: 06T Lucro / Prejuízo Líquido | C51: =C48+C49+C50 -> -8897.6935 | D51: =D48+D49+D50 -> 57722.816 | E51: =E48+E49+E50 -> 58936.471 | F51: =F48+F49+F50 -> -21551.562 | G51: =G48+G49+G50 -> 58941.289 | H51: =H48+H49+H50 -> 50040.362 | I51: =I48+I49+I50 -> -352.02741 | J51: =J48+J49+J50 -> 33482.731 | ... N51: =N48+N49+N50 -> 31846.916 | O51: =SUM(C51:N51) -> 312974.31
B52: 07 Despesas com Invest. e Empréstimos | C52: =C31*$C$17 -> -10968.54 | D52: =D31*$C$17 -> -11392.283 | E52: =E31*$C$17 -> -11540.647 | F52: =F31*$C$17 -> -10279.081 | G52: =G31*$C$17 -> -11614.509 | H52: =H31*$C$17 -> -10830.797 | I52: =I31*$C$17 -> -10830.797 | J52: =J31*$C$17 -> -9378.5881 | ... N52: =N31*$C$17 -> -9378.5881 | O52: =SUM(C52:N52) -> -124349.6
B53: 07T Lucro / Prejuízo Final | C53: =C51+C52 -> -19866.233 | D53: =D51+D52 -> 46330.533 | E53: =E51+E52 -> 47395.825 | F53: =F51+F52 -> -31830.643 | G53: =G51+G52 -> 47326.78 | H53: =H51+H52 -> 39209.564 | I53: =I51+I52 -> -11182.825 | J53: =J51+J52 -> 24104.143 | ... N53: =N51+N52 -> 22468.328 | O53: =SUM(C53:N53) -> 188624.71
B55: INDICADORES (calculados automaticamente)
B56: Indicador | C56: Jan/26 | D56: Fev/26 | E56: Mar/26 | F56: Abr/26 | G56: Mai/26 | H56: Jun/26 | I56: Jul/26 | J56: Ago/26 | K56: Set/26 | L56: Out/26 | M56: Nov/26 | N56: Dez/26 | O56: Total 2026
B57: EBITDA (R$) | C57: =C31+C41+C42+C43+C45+C47 -> 93733.943 | D57: =D31+D41+D42+D43+D45+D47 -> 99489.661 | E57: =E31+E41+E42+E43+E45+E47 -> 101247.25 | F57: =F31+F41+F42+F43+F45+F47 -> 67921.904 | G57: =G31+G41+G42+G43+G45+G47 -> 101522.87 | H57: =H31+H41+H42+H43+H45+H47 -> 89748.666 | I57: =I31+I41+I42+I43+I45+I47 -> 89346.054 | J57: =J31+J41+J42+J43+J45+J47 -> 67866.887 | ... N57: =N31+N41+N42+N43+N45+N47 -> 66231.072 | O57: =SUM(C57:N57) -> 978264.37
B58: Margem EBITDA | C58: =IFERROR(C57/C31,0) -> 0.33565233 | D58: =IFERROR(D57/D31,0) -> 0.34301157 | E58: =IFERROR(E57/E31,0) -> 0.34458367 | F58: =IFERROR(F57/F31,0) -> 0.25953572 | G58: =IFERROR(G57/G31,0) -> 0.34332435 | H58: =IFERROR(H57/H31,0) -> 0.32546864 | I58: =IFERROR(I57/I31,0) -> 0.32400859 | J58: =IFERROR(J57/J31,0) -> 0.28422486 | ... N58: =IFERROR(N57/N31,0) -> 0.2773741 | O58: =AVERAGE(C58:N58) -> 0.30663504
B59: Margem Bruta | C59: =IFERROR(C46/C31,0) -> 0.055771958 | D59: =IFERROR(D46/D31,0) -> 0.28389459 | E59: =IFERROR(E46/E31,0) -> 0.28478391 | F59: =IFERROR(F46/F31,0) -> 0.012095505 | G59: =IFERROR(G46/G31,0) -> 0.28372884 | H59: =IFERROR(H46/H31,0) -> 0.27207674 | I59: =IFERROR(I46/I31,0) -> 0.08971877 | J59: =IFERROR(J46/J31,0) -> 0.24514012 | ... N59: =IFERROR(N46/N31,0) -> 0.24010656 | O59: =AVERAGE(C59:N59) -> 0.19216037
B60: Margem Lucro Líquido | C60: =IFERROR(C51/C31,0) -> -0.031861793 | D60: =IFERROR(D51/D31,0) -> 0.19901157 | E60: =IFERROR(E51/E31,0) -> 0.20058367 | F60: =IFERROR(F51/F31,0) -> -0.082350461 | G60: =IFERROR(G51/G31,0) -> 0.19932435 | H60: =IFERROR(H51/H31,0) -> 0.18146864 | I60: =IFERROR(I51/I31,0) -> -0.0012766082 | J60: =IFERROR(J51/J31,0) -> 0.14022486 | ... N60: =IFERROR(N51/N31,0) -> 0.1333741 | O60: =AVERAGE(C60:N60) -> 0.096637033
B61: Margem Lucro Final | C61: =IFERROR(C53/C31,0) -> -0.07113909 | D61: =IFERROR(D53/D31,0) -> 0.15973428 | E61: =IFERROR(E53/E31,0) -> 0.16130637 | F61: =IFERROR(F53/F31,0) -> -0.12162776 | G61: =IFERROR(G53/G31,0) -> 0.16004705 | H61: =IFERROR(H53/H31,0) -> 0.14219135 | I61: =IFERROR(I53/I31,0) -> -0.040553905 | J61: =IFERROR(J53/J31,0) -> 0.10094756 | ... N61: =IFERROR(N53/N31,0) -> 0.094096805 | O61: =AVERAGE(C61:N61) -> 0.057359736
B63: COMPARATIVO REAL × ORÇADO – TODOS OS 12 MESES
B64: 🟢 Verde > +10% do orçado | 🔴 Vermelho < -10% do orçado | Em branco = mês ainda não encerrado no Consolidado
B66: Assets under management
C67: Jan/26 | D67: Fev/26 | E67: Mar/26 | F67: Abr/26 | G67: Mai/26 | H67: Jun/26 | I67: Jul/26 | J67: Ago/26 | K67: Set/26 | L67: Out/26 | M67: Nov/26 | N67: Dez/26 | O67: Total YTD | Q67: =$C$73&" - "&$G$73 -> Jan/26 - Mai/26
B68: Orçado | C68: =J5+J8 -> 2.9833333e+08 | D68: =C68+$J$8 -> 2.9666667e+08 | E68: =D68+$J$8 -> 2.95e+08 | F68: =E68+$J$8 -> 2.9333333e+08 | G68: =F68+$J$8 -> 2.9166667e+08 | H68: =G68+$J$8 -> 2.9e+08 | I68: =H68+$J$8 -> 2.8833333e+08 | J68: =I68+$J$8 -> 2.8666667e+08 | K68: =J68+$J$8 -> 2.85e+08 | ... N68: =M68+$J$8 -> 2.8e+08 | O68: =N68 -> 2.8e+08 | Q68: =SUM(C68:G68) -> 1.475e+09
B69: Realizado | C69: =IF(OR(Consolidated!E4=0,Consolidated!E4=""),"",Consolidated!E4) -> 290504767 | D69: =IF(OR(Consolidated!F4=0,Consolidated!F4=""),"",Consolidated!F4) -> 304511145 | E69: =IF(OR(Consolidated!G4=0,Consolidated!G4=""),"",Consolidated!G4) -> 309415143 | F69: =IF(OR(Consolidated!H4=0,Consolidated!H4=""),"",Consolidated!H4) -> 311856596 | G69: =IF(OR(Consolidated!I4=0,Consolidated!I4=""),"",Consolidated!I4) -> 312069591 | H69: =IF(OR(Consolidated!J4=0,Consolidated!J4=""),"",Consolidated!J4) -> 295791970 | I69: =IF(OR(Consolidated!K4=0,Consolidated!K4=""),"",Consolidated!K4) -> 254401486 | J69: =IF(OR(Consolidated!L4=0,Consolidated!L4=""),"",Consolidated!L4) | ... N69: =IF(OR(Consolidated!P4=0,Consolidated!P4=""),"",Consolidated!P4) | O69: {=INDEX(C69:N69,1,MAX((C69:N69<>0)*(C69:N69<>"")*COLUMN(C69:N69))-COLUMN(C69)+1)} -> 254401486 | Q69: =SUM(C69:G69) -> 1528357242
B70: Δ% Real vs. Orçado | C70: =IFERROR(IF(C69="","",(C69-C68)/ABS(C68)),"—") -> -0.026241004 | D70: =IFERROR(IF(D69="","",(D69-D68)/ABS(D68)),"—") -> 0.026442062 | E70: =IFERROR(IF(E69="","",(E69-E68)/ABS(E68)),"—") -> 0.048864892 | F70: =IFERROR(IF(F69="","",(F69-F68)/ABS(F68)),"—") -> 0.063147486 | G70: =IFERROR(IF(G69="","",(G69-G68)/ABS(G68)),"—") -> 0.069952883 | H70: =IFERROR(IF(H69="","",(H69-H68)/ABS(H68)),"—") -> 0.01997231 | I70: =IFERROR(IF(I69="","",(I69-I68)/ABS(I68)),"—") -> -0.11768271 | J70: =IFERROR(IF(J69="","",(J69-J68)/ABS(J68)),"—") | ... N70: =IFERROR(IF(N69="","",(N69-N68)/ABS(N68)),"—") | O70: =IFERROR(IF(O69=0,"",(O69-O68)/ABS(O68)),"—") -> -0.091423264 | Q70: =IFERROR(IF(Q69=0,"",(Q69-Q68)/ABS(Q68)),"—") -> 0.036174401
B72: 01 Receitas Operacionais
C73: Jan/26 | D73: Fev/26 | E73: Mar/26 | F73: Abr/26 | G73: Mai/26 | H73: Jun/26 | I73: Jul/26 | J73: Ago/26 | K73: Set/26 | L73: Out/26 | M73: Nov/26 | N73: Dez/26 | O73: Total YTD | Q73: =$C$73&" - "&$G$73 -> Jan/26 - Mai/26
B74: Orçado | C74: =C31 -> 279259.03 | D74: =D31 -> 290047.53 | E74: =E31 -> 293824.87 | F74: =F31 -> 261705.42 | G74: =G31 -> 295705.42 | H74: =H31 -> 275752.11 | I74: =I31 -> 275752.11 | J74: =J31 -> 238778.86 | ... O74: =O31 -> 3165940.8 | Q74: =SUM(C74:G74) -> 1420542.3
B75: Realizado | C75: =IF(OR(Consolidated!E7=0,Consolidated!E7=""),"",Consolidated!E7) -> 282443.93 | D75: =IF(OR(Consolidated!F7=0,Consolidated!F7=""),"",Consolidated!F7) -> 284996.24 | E75: =IF(OR(Consolidated!G7=0,Consolidated!G7=""),"",Consolidated!G7) -> 272796.35 | F75: =IF(OR(Consolidated!H7=0,Consolidated!H7=""),"",Consolidated!H7) -> 266720.63 | G75: =IF(OR(Consolidated!I7=0,Consolidated!I7=""),"",Consolidated!I7) -> 277334.58 | H75: =IF(OR(Consolidated!J7=0,Consolidated!J7=""),"",Consolidated!J7) -> 301557.87 | I75: =IF(OR(Consolidated!K7=0,Consolidated!K7=""),"",Consolidated!K7) -> 280619.08 | J75: =IF(OR(Consolidated!L7=0,Consolidated!L7=""),"",Consolidated!L7) | ... N75: =IF(OR(Consolidated!P7=0,Consolidated!P7=""),"",Consolidated!P7) | O75: =SUMIF(C75:N75,"<>") -> 1966468.7 | Q75: =SUM(C75:G75) -> 1384291.7
B76: Δ% Real vs. Orçado | C76: =IFERROR(IF(C75="","",(C75-C74)/ABS(C74)),"—") -> 0.01140483 | D76: =IFERROR(IF(D75="","",(D75-D74)/ABS(D74)),"—") -> -0.017415401 | E76: =IFERROR(IF(E75="","",(E75-E74)/ABS(E74)),"—") -> -0.071568214 | F76: =IFERROR(IF(F75="","",(F75-F74)/ABS(F74)),"—") -> 0.019163583 | G76: =IFERROR(IF(G75="","",(G75-G74)/ABS(G74)),"—") -> -0.062125465 | H76: =IFERROR(IF(H75="","",(H75-H74)/ABS(H74)),"—") -> 0.093583172 | I76: =IFERROR(IF(I75="","",(I75-I74)/ABS(I74)),"—") -> 0.017649792 | J76: =IFERROR(IF(J75="","",(J75-J74)/ABS(J74)),"—") | ... N76: =IFERROR(IF(N75="","",(N75-N74)/ABS(N74)),"—") | O76: =IFERROR(IF(O75=0,"",(O75-O74)/ABS(O74)),"—") -> -0.37886751 | Q76: =IFERROR(IF(Q75=0,"",(Q75-Q74)/ABS(Q74)),"—") -> -0.025518802
B78: 02 Deduções da Receita Bruta
C79: Jan/26 | D79: Fev/26 | E79: Mar/26 | F79: Abr/26 | G79: Mai/26 | H79: Jun/26 | I79: Jul/26 | J79: Ago/26 | K79: Set/26 | L79: Out/26 | M79: Nov/26 | N79: Dez/26 | O79: Total YTD | Q79: =$Q$73 -> Jan/26 - Mai/26
B80: Orçado | C80: =C38 -> -198990.4 | D80: =D38 -> -142721.51 | E80: =E38 -> -144874.59 | F80: =F38 -> -192974.39 | G80: =G38 -> -145946.5 | H80: =H38 -> -134573.12 | I80: =I38 -> -184562.89 | J80: =J38 -> -113498.36 | ... O80: =O38 -> -1757333.8 | Q80: =SUM(C80:G80) -> -825507.38
B81: Realizado | C81: =IF(OR(Consolidated!E20=0,Consolidated!E20=""),"",Consolidated!E20) -> -198816.65 | D81: =IF(OR(Consolidated!F20=0,Consolidated!F20=""),"",Consolidated!F20) -> -126321.09 | E81: =IF(OR(Consolidated!G20=0,Consolidated!G20=""),"",Consolidated!G20) -> -138181.44 | F81: =IF(OR(Consolidated!H20=0,Consolidated!H20=""),"",Consolidated!H20) -> -196414.44 | G81: =IF(OR(Consolidated!I20=0,Consolidated!I20=""),"",Consolidated!I20) -> -128726.11 | H81: =IF(OR(Consolidated!J20=0,Consolidated!J20=""),"",Consolidated!J20) -> -128056.72 | I81: =IF(OR(Consolidated!K20=0,Consolidated!K20=""),"",Consolidated!K20) -> -195285.63 | J81: =IF(OR(Consolidated!L20=0,Consolidated!L20=""),"",Consolidated!L20) | ... N81: =IF(OR(Consolidated!P20=0,Consolidated!P20=""),"",Consolidated!P20) | O81: =SUMIF(C81:N81,"<>") -> -1111802.1 | Q81: =SUM(C81:G81) -> -788459.73
B82: Δ% Real vs. Orçado | C82: =IFERROR(IF(C81="","",(C81-C80)/ABS(C80)),"—") -> 0.00087313607 | D82: =IFERROR(IF(D81="","",(D81-D80)/ABS(D80)),"—") -> 0.11491203 | E82: =IFERROR(IF(E81="","",(E81-E80)/ABS(E80)),"—") -> 0.046199614 | F82: =IFERROR(IF(F81="","",(F81-F80)/ABS(F80)),"—") -> -0.017826475 | G82: =IFERROR(IF(G81="","",(G81-G80)/ABS(G80)),"—") -> 0.11799112 | H82: =IFERROR(IF(H81="","",(H81-H80)/ABS(H80)),"—") -> 0.048422729 | I82: =IFERROR(IF(I81="","",(I81-I80)/ABS(I80)),"—") -> -0.058098003 | J82: =IFERROR(IF(J81="","",(J81-J80)/ABS(J80)),"—") | ... N82: =IFERROR(IF(N81="","",(N81-N80)/ABS(N80)),"—") | O82: =IFERROR(IF(O81=0,"",(O81-O80)/ABS(O80)),"—") -> 0.36733586 | Q82: =IFERROR(IF(Q81=0,"",(Q81-Q80)/ABS(Q80)),"—") -> 0.044878644
B84: 03 Custos Operacionais
C85: Jan/26 | D85: Fev/26 | E85: Mar/26 | F85: Abr/26 | G85: Mai/26 | H85: Jun/26 | I85: Jul/26 | J85: Ago/26 | K85: Set/26 | L85: Out/26 | M85: Nov/26 | N85: Dez/26 | O85: Total YTD | Q85: =$Q$73 -> Jan/26 - Mai/26
B86: Orçado | C86: =C45 -> -64693.81 | D86: =D45 -> -64983.101 | E86: =E45 -> -65273.686 | F86: =F45 -> -65565.57 | G86: =G45 -> -65858.76 | H86: =H45 -> -66153.26 | I86: =I45 -> -66449.078 | J86: =J45 -> -66746.218 | ... O86: =O45 -> -795706.42 | Q86: =SUM(C86:G86) -> -326374.93
B87: Realizado | C87: =IF(OR(Consolidated!E28=0,Consolidated!E28=""),"",Consolidated!E28) -> -64960.26 | D87: =IF(OR(Consolidated!F28=0,Consolidated!F28=""),"",Consolidated!F28) -> -61297.63 | E87: =IF(OR(Consolidated!G28=0,Consolidated!G28=""),"",Consolidated!G28) -> -67942.22 | F87: =IF(OR(Consolidated!H28=0,Consolidated!H28=""),"",Consolidated!H28) -> -64575.13 | G87: =IF(OR(Consolidated!I28=0,Consolidated!I28=""),"",Consolidated!I28) -> -81372.89 | H87: =IF(OR(Consolidated!J28=0,Consolidated!J28=""),"",Consolidated!J28) -> -66612.71 | I87: =IF(OR(Consolidated!K28=0,Consolidated!K28=""),"",Consolidated!K28) -> -59682.89 | J87: =IF(OR(Consolidated!L28=0,Consolidated!L28=""),"",Consolidated!L28) | ... N87: =IF(OR(Consolidated!P28=0,Consolidated!P28=""),"",Consolidated!P28) | O87: =SUMIF(C87:N87,"<>") -> -466443.73 | Q87: =SUM(C87:G87) -> -340148.13
B88: Δ% Real vs. Orçado | C88: =IFERROR(IF(C87="","",(C87-C86)/ABS(C86)),"—") -> -0.0041186321 | D88: =IFERROR(IF(D87="","",(D87-D86)/ABS(D86)),"—") -> 0.056714302 | E88: =IFERROR(IF(E87="","",(E87-E86)/ABS(E86)),"—") -> -0.040882231 | F88: =IFERROR(IF(F87="","",(F87-F86)/ABS(F86)),"—") -> 0.015106105 | G88: =IFERROR(IF(G87="","",(G87-G86)/ABS(G86)),"—") -> -0.23556669 | H88: =IFERROR(IF(H87="","",(H87-H86)/ABS(H86)),"—") -> -0.0069452297 | I88: =IFERROR(IF(I87="","",(I87-I86)/ABS(I86)),"—") -> 0.10182516 | J88: =IFERROR(IF(J87="","",(J87-J86)/ABS(J86)),"—") | ... N88: =IFERROR(IF(N87="","",(N87-N86)/ABS(N86)),"—") | O88: =IFERROR(IF(O87=0,"",(O87-O86)/ABS(O86)),"—") -> 0.41379921 | Q88: =IFERROR(IF(Q87=0,"",(Q87-Q86)/ABS(Q86)),"—") -> -0.042200553
B90: 03T Lucro Bruto
C91: Jan/26 | D91: Fev/26 | E91: Mar/26 | F91: Abr/26 | G91: Mai/26 | H91: Jun/26 | I91: Jul/26 | J91: Ago/26 | K91: Set/26 | L91: Out/26 | M91: Nov/26 | N91: Dez/26 | O91: Total YTD | Q91: =$Q$73 -> Jan/26 - Mai/26
B92: Orçado | C92: =C46 -> 15574.823 | D92: =D46 -> 82342.925 | E92: =E46 -> 83676.595 | F92: =F46 -> 3165.4592 | G92: =G46 -> 83900.156 | H92: =H46 -> 75025.734 | I92: =I46 -> 24740.14 | J92: =J46 -> 58534.278 | ... O92: =O46 -> 612900.57 | Q92: =SUM(C92:G92) -> 268659.96
B93: Realizado | C93: =IF(OR(Consolidated!E34=0,Consolidated!E34=""),"",Consolidated!E34) -> 18667.02 | D93: =IF(OR(Consolidated!F34=0,Consolidated!F34=""),"",Consolidated!F34) -> 97377.52 | E93: =IF(OR(Consolidated!G34=0,Consolidated!G34=""),"",Consolidated!G34) -> 66672.69 | F93: =IF(OR(Consolidated!H34=0,Consolidated!H34=""),"",Consolidated!H34) -> 5731.06 | G93: =IF(OR(Consolidated!I34=0,Consolidated!I34=""),"",Consolidated!I34) -> 67235.58 | H93: =IF(OR(Consolidated!J34=0,Consolidated!J34=""),"",Consolidated!J34) -> 106888.44 | I93: =IF(OR(Consolidated!K34=0,Consolidated!K34=""),"",Consolidated!K34) -> 25650.56 | J93: =IF(OR(Consolidated!L34=0,Consolidated!L34=""),"",Consolidated!L34) | ... N93: =IF(OR(Consolidated!P34=0,Consolidated!P34=""),"",Consolidated!P34) | O93: =SUMIF(C93:N93,"<>") -> 388222.87 | Q93: =SUM(C93:G93) -> 255683.87
B94: Δ% Real vs. Orçado | C94: =IFERROR(IF(C93="","",(C93-C92)/ABS(C92)),"—") -> 0.19853821 | D94: =IFERROR(IF(D93="","",(D93-D92)/ABS(D92)),"—") -> 0.18258515 | E94: =IFERROR(IF(E93="","",(E93-E92)/ABS(E92)),"—") -> -0.20320981 | F94: =IFERROR(IF(F93="","",(F93-F92)/ABS(F92)),"—") -> 0.81049875 | G94: =IFERROR(IF(G93="","",(G93-G92)/ABS(G92)),"—") -> -0.1986239 | H94: =IFERROR(IF(H93="","",(H93-H92)/ABS(H92)),"—") -> 0.42469035 | I94: =IFERROR(IF(I93="","",(I93-I92)/ABS(I92)),"—") -> 0.036799295 | J94: =IFERROR(IF(J93="","",(J93-J92)/ABS(J92)),"—") | ... N94: =IFERROR(IF(N93="","",(N93-N92)/ABS(N92)),"—") | O94: =IFERROR(IF(O93=0,"",(O93-O92)/ABS(O92)),"—") -> -0.36658099 | Q94: =IFERROR(IF(Q93=0,"",(Q93-Q92)/ABS(Q92)),"—") -> -0.048299299
B96: 04 Despesas Operacionais
C97: Jan/26 | D97: Fev/26 | E97: Mar/26 | F97: Abr/26 | G97: Mai/26 | H97: Jun/26 | I97: Jul/26 | J97: Ago/26 | K97: Set/26 | L97: Out/26 | M97: Nov/26 | N97: Dez/26 | O97: Total YTD | Q97: =$Q$73 -> Jan/26 - Mai/26
B98: Orçado | C98: =C47 -> -23355.48 | D98: =D47 -> -23459.919 | E98: =E47 -> -23564.824 | F98: =F47 -> -23670.199 | G98: =G47 -> -23776.045 | H98: =H47 -> -23882.364 | I98: =I47 -> -23989.159 | J98: =J47 -> -24096.432 | ... O98: =O47 -> -287262.5 | Q98: =SUM(C98:G98) -> -117826.47
B99: Realizado | C99: =IF(OR(Consolidated!E35=0,Consolidated!E35=""),"",Consolidated!E35) -> -23481.5 | D99: =IF(OR(Consolidated!F35=0,Consolidated!F35=""),"",Consolidated!F35) -> -24172.25 | E99: =IF(OR(Consolidated!G35=0,Consolidated!G35=""),"",Consolidated!G35) -> -24636.4 | F99: =IF(OR(Consolidated!H35=0,Consolidated!H35=""),"",Consolidated!H35) -> -21131.77 | G99: =IF(OR(Consolidated!I35=0,Consolidated!I35=""),"",Consolidated!I35) -> -20692.52 | H99: =IF(OR(Consolidated!J35=0,Consolidated!J35=""),"",Consolidated!J35) -> -20268.56 | I99: =IF(OR(Consolidated!K35=0,Consolidated!K35=""),"",Consolidated!K35) -> -30373.03 | J99: =IF(OR(Consolidated!L35=0,Consolidated!L35=""),"",Consolidated!L35) | ... N99: =IF(OR(Consolidated!P35=0,Consolidated!P35=""),"",Consolidated!P35) | O99: =SUMIF(C99:N99,"<>") -> -164756.03 | Q99: =SUM(C99:G99) -> -114114.44
B100: Δ% Real vs. Orçado | C100: =IFERROR(IF(C99="","",(C99-C98)/ABS(C98)),"—") -> -0.0053957358 | D100: =IFERROR(IF(D99="","",(D99-D98)/ABS(D98)),"—") -> -0.030363759 | E100: =IFERROR(IF(E99="","",(E99-E98)/ABS(E98)),"—") -> -0.045473525 | F100: =IFERROR(IF(F99="","",(F99-F98)/ABS(F98)),"—") -> 0.10724156 | G100: =IFERROR(IF(G99="","",(G99-G98)/ABS(G98)),"—") -> 0.12969042 | H100: =IFERROR(IF(H99="","",(H99-H98)/ABS(H98)),"—") -> 0.15131686 | I100: =IFERROR(IF(I99="","",(I99-I98)/ABS(I98)),"—") -> -0.26611482 | J100: =IFERROR(IF(J99="","",(J99-J98)/ABS(J98)),"—") | ... N100: =IFERROR(IF(N99="","",(N99-N98)/ABS(N98)),"—") | O100: =IFERROR(IF(O99=0,"",(O99-O98)/ABS(O98)),"—") -> 0.42646175 | Q100: =IFERROR(IF(Q99=0,"",(Q99-Q98)/ABS(Q98)),"—") -> 0.03150419
B102: 04T Lucro / Prej. Operacional
C103: Jan/26 | D103: Fev/26 | E103: Mar/26 | F103: Abr/26 | G103: Mai/26 | H103: Jun/26 | I103: Jul/26 | J103: Ago/26 | K103: Set/26 | L103: Out/26 | M103: Nov/26 | N103: Dez/26 | O103: Total YTD | Q103: =$Q$73 -> Jan/26 - Mai/26
B104: Orçado | C104: =C48 -> -7780.6573 | D104: =D48 -> 58883.006 | E104: =E48 -> 60111.771 | F104: =F48 -> -20504.74 | G104: =G48 -> 60124.111 | H104: =H48 -> 51143.37 | I104: =I48 -> 750.98104 | J104: =J48 -> 34437.847 | ... O104: =O48 -> 325638.07 | Q104: =SUM(C104:G104) -> 150833.49
B105: Realizado | C105: =IF(OR(Consolidated!E46=0,Consolidated!E46=""),"",Consolidated!E46) -> -4814.48 | D105: =IF(OR(Consolidated!F46=0,Consolidated!F46=""),"",Consolidated!F46) -> 73205.27 | E105: =IF(OR(Consolidated!G46=0,Consolidated!G46=""),"",Consolidated!G46) -> 42036.29 | F105: =IF(OR(Consolidated!H46=0,Consolidated!H46=""),"",Consolidated!H46) -> -15400.71 | G105: =IF(OR(Consolidated!I46=0,Consolidated!I46=""),"",Consolidated!I46) -> 46543.06 | H105: =IF(OR(Consolidated!J46=0,Consolidated!J46=""),"",Consolidated!J46) -> 86619.88 | I105: =IF(OR(Consolidated!K46=0,Consolidated!K46=""),"",Consolidated!K46) -> -4722.47 | J105: =IF(OR(Consolidated!L46=0,Consolidated!L46=""),"",Consolidated!L46) | ... N105: =IF(OR(Consolidated!P46=0,Consolidated!P46=""),"",Consolidated!P46) | O105: =SUMIF(C105:N105,"<>") -> 223466.84 | Q105: =SUM(C105:G105) -> 141569.43
B106: Δ% Real vs. Orçado | C106: =IFERROR(IF(C105="","",(C105-C104)/ABS(C104)),"—") -> 0.38122452 | D106: =IFERROR(IF(D105="","",(D105-D104)/ABS(D104)),"—") -> 0.24323255 | E106: =IFERROR(IF(E105="","",(E105-E104)/ABS(E104)),"—") -> -0.30069786 | F106: =IFERROR(IF(F105="","",(F105-F104)/ABS(F104)),"—") -> 0.24891952 | G106: =IFERROR(IF(G105="","",(G105-G104)/ABS(G104)),"—") -> -0.2258836 | H106: =IFERROR(IF(H105="","",(H105-H104)/ABS(H104)),"—") -> 0.69366782 | I106: =IFERROR(IF(I105="","",(I105-I104)/ABS(I104)),"—") -> -7.2884011 | J106: =IFERROR(IF(J105="","",(J105-J104)/ABS(J104)),"—") | ... N106: =IFERROR(IF(N105="","",(N105-N104)/ABS(N104)),"—") | O106: =IFERROR(IF(O105=0,"",(O105-O104)/ABS(O104)),"—") -> -0.31375702 | Q106: =IFERROR(IF(Q105=0,"",(Q105-Q104)/ABS(Q104)),"—") -> -0.06141912
B108: 06T Lucro / Prej. Líquido
C109: Jan/26 | D109: Fev/26 | E109: Mar/26 | F109: Abr/26 | G109: Mai/26 | H109: Jun/26 | I109: Jul/26 | J109: Ago/26 | K109: Set/26 | L109: Out/26 | M109: Nov/26 | N109: Dez/26 | O109: Total YTD | Q109: =$Q$73 -> Jan/26 - Mai/26
B110: Orçado | C110: =C51 -> -8897.6935 | D110: =D51 -> 57722.816 | E110: =E51 -> 58936.471 | F110: =F51 -> -21551.562 | G110: =G51 -> 58941.289 | H110: =H51 -> 50040.362 | I110: =I51 -> -352.02741 | J110: =J51 -> 33482.731 | ... O110: =O51 -> 312974.31 | Q110: =SUM(C110:G110) -> 145151.32
B111: Realizado | C111: =IF(OR(Consolidated!E49=0,Consolidated!E49=""),"",Consolidated!E49) -> -6068.71 | D111: =IF(OR(Consolidated!F49=0,Consolidated!F49=""),"",Consolidated!F49) -> 72233.96 | E111: =IF(OR(Consolidated!G49=0,Consolidated!G49=""),"",Consolidated!G49) -> 41699.14 | F111: =IF(OR(Consolidated!H49=0,Consolidated!H49=""),"",Consolidated!H49) -> -16149.22 | G111: =IF(OR(Consolidated!I49=0,Consolidated!I49=""),"",Consolidated!I49) -> 46819.33 | H111: =IF(OR(Consolidated!J49=0,Consolidated!J49=""),"",Consolidated!J49) -> 83103.44 | I111: =IF(OR(Consolidated!K49=0,Consolidated!K49=""),"",Consolidated!K49) -> -4902.19 | J111: =IF(OR(Consolidated!L49=0,Consolidated!L49=""),"",Consolidated!L49) | ... N111: =IF(OR(Consolidated!P49=0,Consolidated!P49=""),"",Consolidated!P49) | O111: =SUMIF(C111:N111,"<>") -> 216735.75 | Q111: =SUM(C111:G111) -> 138534.5
B112: Δ% Real vs. Orçado | C112: =IFERROR(IF(C111="","",(C111-C110)/ABS(C110)),"—") -> 0.31794571 | D112: =IFERROR(IF(D111="","",(D111-D110)/ABS(D110)),"—") -> 0.25139355 | E112: =IFERROR(IF(E111="","",(E111-E110)/ABS(E110)),"—") -> -0.29247308 | F112: =IFERROR(IF(F111="","",(F111-F110)/ABS(F110)),"—") -> 0.25067054 | G112: =IFERROR(IF(G111="","",(G111-G110)/ABS(G110)),"—") -> -0.20566159 | H112: =IFERROR(IF(H111="","",(H111-H110)/ABS(H110)),"—") -> 0.66072821 | I112: =IFERROR(IF(I111="","",(I111-I110)/ABS(I110)),"—") -> -12.925592 | J112: =IFERROR(IF(J111="","",(J111-J110)/ABS(J110)),"—") | ... N112: =IFERROR(IF(N111="","",(N111-N110)/ABS(N110)),"—") | O112: =IFERROR(IF(O111=0,"",(O111-O110)/ABS(O110)),"—") -> -0.30749667 | Q112: =IFERROR(IF(Q111=0,"",(Q111-Q110)/ABS(Q110)),"—") -> -0.045585677
B114: 07 Desp. Invest./Empréstimos
...

Sheet Gráficos 2026
B1: GRÁFICOS – REAL × ORÇADO 2026

Sheet Projeção
D2: Realizado
D3: Projetado
E5: Realizado | F5: Realizado | G5: Realizado | H5: Realizado | I5: Realizado | J5: Realizado | K5: Realizado | L5: Projetado | M5: Projetado | N5: Projetado | O5: Projetado | P5: Projetado
D7: AuM | E7: =AuM!C76 -> 290504767 | F7: =AuM!C77 -> 304511145 | G7: =AuM!C78 -> 309415143 | H7: =AuM!C79 -> 311856596 | I7: =IF(I5=$D$2,Consolidated!I4,'Orçamento 2026'!G27) -> 312069591 | J7: =IF(J5=$D$2,Consolidated!J4,'Orçamento 2026'!H27) -> 295791970 | K7: =IF(K5=$D$2,Consolidated!K4,'Orçamento 2026'!I27) -> 254401486 | L7: =IF(L5=$D$2,Consolidated!L4,'Orçamento 2026'!J27) -> 2.4589568e+08 | M7: =IF(M5=$D$2,Consolidated!M4,'Orçamento 2026'!K27) -> 2.4589568e+08 | N7: =IF(N5=$D$2,Consolidated!N4,'Orçamento 2026'!L27) -> 2.4589568e+08 | O7: =IF(O5=$D$2,Consolidated!O4,'Orçamento 2026'!M27) -> 2.4589568e+08 | P7: =IF(P5=$D$2,Consolidated!P4,'Orçamento 2026'!N27) -> 2.4589568e+08 | Q7: Média | U7: Média
D8: ROA Anualizado | E8: =IF(E7>0,(E10/E7)*12,"") -> 0.011667028 | F8: =IF(F7>0,(F10/F7)*12,"") -> 0.011230968 | G8: =IF(G7>0,(G10/G7)*12,"") -> 0.010579819 | H8: =IF(H7>0,(H10/H7)*12,"") -> 0.010263203 | I8: =IF(I7>0,(I10/I7)*12,"") -> 0.010664336 | J8: =IF(J7>0,(J10/J7)*12,"") -> 0.012233917 | K8: =IF(K7>0,(K10/K7)*12,"") -> 0.013236672 | L8: =IF(L7>0,(L10/L7)*12,"") -> 0.011652691 | ... P8: =IF(P7>0,(P10/P7)*12,"") -> 0.011652691 | Q8: =AVERAGE(E8:P8) -> 0.011511616 | U8: 12
D9: Categoria | E9: Jan/2026 | F9: Fev/2026 | G9: Mar/2026 | H9: Abr/2026 | I9: 46143 | J9: 46174 | K9: 46204 | L9: 46235 | M9: 46266 | N9: 46296 | O9: 46327 | P9: 46357 | Q9: Total | U9: Total
D10: 01 Receitas Operacionais | E10: =CNS!B8+CRR!B8 -> 282443.93 | F10: =CNS!C8+CRR!C8 -> 284996.24 | G10: =CNS!D8+CRR!D8 -> 272796.35 | H10: =CNS!E8+CRR!E8 -> 266720.63 | I10: =IF(I5=$D$2,Consolidated!I7,SUM(I11:I21)) -> 277334.58 | J10: =IF(J5=$D$2,Consolidated!J7,SUM(J11:J21)) -> 301557.87 | K10: =IF(K5=$D$2,Consolidated!K7,SUM(K11:K21)) -> 280619.08 | L10: =IF(L5=$D$2,Consolidated!L7,SUM(L11:L21)) -> 238778.86 | M10: =IF(M5=$D$2,Consolidated!M7,SUM(M11:M21)) -> 238778.86 | N10: =IF(N5=$D$2,Consolidated!N7,SUM(N11:N21)) -> 238778.86 | O10: =IF(O5=$D$2,Consolidated!O7,SUM(O11:O21)) -> 238778.86 | P10: =IF(P5=$D$2,Consolidated!P7,SUM(P11:P21)) -> 238778.86 | Q10: =SUM(E10:P10) -> 3160363 | T10: 01 Receitas Operacionais | U10: =Q10/$U$8 -> 263363.58
D11: Consultoria | E11: =CNS!B9 -> 175809.2 | F11: =CNS!C9 -> 178265.28 | G11: =CNS!D9 -> 183175.54 | H11: =CNS!E9 -> 191954.82 | I11: =IF(I5=$D$2,CNS!F9,'Orçamento 2026'!G32) -> 192414.3 | J11: =IF(J5=$D$2,CNS!G9,'Orçamento 2026'!H32) -> 187551.84 | K11: =IF(K5=$D$2,CNS!H9,'Orçamento 2026'!I32) -> 175356.62 | L11: =IF(L5=$D$2,CNS!I9,'Orçamento 2026'!J32) -> 141018.5 | M11: =IF(M5=$D$2,CNS!J9,'Orçamento 2026'!K32) -> 141018.5 | N11: =IF(N5=$D$2,CNS!K9,'Orçamento 2026'!L32) -> 141018.5 | O11: =IF(O5=$D$2,CNS!L9,'Orçamento 2026'!M32) -> 141018.5 | P11: =IF(P5=$D$2,CNS!M9,'Orçamento 2026'!N32) -> 141018.5 | Q11: =SUM(E11:P11) -> 1989620.1 | R11: =Q11/$Q$10 -> 0.6295543 | T11: Consultoria | U11: =Q11/$U$8 -> 165801.67
D12: Planejamento | E12: =CNS!B10 -> 14700 | F12: =CNS!C10 -> 18900 | G12: =CNS!D10 -> 10400 | H12: =CNS!E10 -> 6500 | I12: =IF(I5=$D$2,CNS!F10,'Orçamento 2026'!G33) -> 6500 | J12: =IF(J5=$D$2,CNS!G10,'Orçamento 2026'!H33) -> 0,00 | K12: =IF(K5=$D$2,CNS!H10,'Orçamento 2026'!I33) -> 18270 | L12: =IF(L5=$D$2,CNS!I10,'Orçamento 2026'!J33) -> 10265.661 | M12: =IF(M5=$D$2,CNS!J10,'Orçamento 2026'!K33) -> 10265.661 | N12: =IF(N5=$D$2,CNS!K10,'Orçamento 2026'!L33) -> 10265.661 | O12: =IF(O5=$D$2,CNS!L10,'Orçamento 2026'!M33) -> 10265.661 | P12: =IF(P5=$D$2,CNS!M10,'Orçamento 2026'!N33) -> 10265.661 | Q12: =SUM(E12:P12) -> 126598.31 | R12: =Q12/$Q$10 -> 0.040058154 | T12: Planejamento | U12: =Q12/$U$8 -> 10549.859
D13: Tesouro Mato Grosso | E13: =CNS!B11 -> 34000 | F13: =CNS!C11 -> 34000 | G13: =CNS!D11 -> 34000 | H13: =CNS!E11 -> 0,00 | I13: =IF(I5=$D$2,CNS!F11,'Orçamento 2026'!G34) -> 34000 | J13: =IF(J5=$D$2,CNS!G11,'Orçamento 2026'!H34) -> 83700 | K13: =IF(K5=$D$2,CNS!H11,'Orçamento 2026'!I34) -> 34000 | L13: =IF(L5=$D$2,CNS!I11,'Orçamento 2026'!J34) -> 34000 | M13: =IF(M5=$D$2,CNS!J11,'Orçamento 2026'!K34) -> 34000 | N13: =IF(N5=$D$2,CNS!K11,'Orçamento 2026'!L34) -> 34000 | O13: =IF(O5=$D$2,CNS!L11,'Orçamento 2026'!M34) -> 34000 | P13: =IF(P5=$D$2,CNS!M11,'Orçamento 2026'!N34) -> 34000 | Q13: =SUM(E13:P13) -> 423700 | R13: =Q13/$Q$10 -> 0.13406688 | T13: Tesouro Mato Grosso | U13: =Q13/$U$8 -> 35308.333
D14: RPPS | E14: =CNS!B12 -> 15346 | F14: =CNS!C12 -> 18715.86 | G14: =CNS!D12 -> 0,00 | H14: =CNS!E12 -> 30425.54 | I14: =IF(I5=$D$2,CNS!F12,'Orçamento 2026'!G35) -> 0,00 | J14: =IF(J5=$D$2,CNS!G12,'Orçamento 2026'!H35) -> 6238.62 | K14: =IF(K5=$D$2,CNS!H12,'Orçamento 2026'!I35) -> 0,00 | L14: =IF(L5=$D$2,CNS!I12,'Orçamento 2026'!J35) -> 21495.8 | M14: =IF(M5=$D$2,CNS!J12,'Orçamento 2026'!K35) -> 21495.8 | N14: =IF(N5=$D$2,CNS!K12,'Orçamento 2026'!L35) -> 21495.8 | O14: =IF(O5=$D$2,CNS!L12,'Orçamento 2026'!M35) -> 21495.8 | P14: =IF(P5=$D$2,CNS!M12,'Orçamento 2026'!N35) -> 21495.8 | Q14: =SUM(E14:P14) -> 178205.02 | R14: =Q14/$Q$10 -> 0.056387517 | T14: RPPS | U14: =Q14/$U$8 -> 14850.418
D15: Consulta | E15: =CNS!B13 -> 0,00 | F15: =CNS!C13 -> 750 | G15: =CNS!D13 -> 600 | H15: =CNS!E13 -> 1200 | I15: =IF(I5=$D$2,CNS!F13,0) -> 0,00 | J15: =IF(J5=$D$2,CNS!G13,0) -> 0,00 | K15: =IF(K5=$D$2,CNS!H13,0) -> 0,00 | L15: =IF(L5=$D$2,CNS!I13,0) -> 0 | M15: =IF(M5=$D$2,CNS!J13,0) -> 0 | N15: =IF(N5=$D$2,CNS!K13,0) -> 0 | O15: =IF(O5=$D$2,CNS!L13,0) -> 0 | P15: =IF(P5=$D$2,CNS!M13,0) -> 0 | Q15: =SUM(E15:P15) -> 2550 | R15: =Q15/$Q$10 -> 0.00080686934 | T15: Consulta | U15: =Q15/$U$8 -> 212.5
D16: Valuation | E16: =CNS!B14 -> 0 | F16: =CNS!C14 -> 0,00 | G16: =CNS!D14 -> 0,00 | H16: =CNS!E14 -> 0,00 | I16: =IF(I5=$D$2,CNS!F14,0) -> 0,00 | J16: =IF(J5=$D$2,CNS!G14,0) -> 0,00 | K16: =IF(K5=$D$2,CNS!H14,0) -> 0,00 | L16: =IF(L5=$D$2,CNS!I14,0) -> 0 | M16: =IF(M5=$D$2,CNS!J14,0) -> 0 | N16: =IF(N5=$D$2,CNS!K14,0) -> 0 | O16: =IF(O5=$D$2,CNS!L14,0) -> 0 | P16: =IF(P5=$D$2,CNS!M14,0) -> 0 | Q16: =SUM(E16:P16) -> 0 | R16: =Q16/$Q$10 -> 0 | T16: Valuation | U16: =Q16/$U$8 -> 0
D17: Câmbio/Bancários | E17: =CRR!B9 -> 2129.24 | F17: =CRR!C9 -> 4080.01 | G17: =CRR!D9 -> 7882.59 | H17: =CRR!E9 -> 3358.51 | I17: =IF(I5=$D$2,CRR!F9,'Orçamento 2026'!G36) -> 4335.02 | J17: =IF(J5=$D$2,CRR!G9,'Orçamento 2026'!H36) -> 0,00 | K17: =IF(K5=$D$2,CRR!H9,'Orçamento 2026'!I36) -> 5592.59 | L17: =IF(L5=$D$2,CRR!I9,'Orçamento 2026'!J36) -> 31998.9 | M17: =IF(M5=$D$2,CRR!J9,'Orçamento 2026'!K36) -> 31998.9 | N17: =IF(N5=$D$2,CRR!K9,'Orçamento 2026'!L36) -> 31998.9 | O17: =IF(O5=$D$2,CRR!L9,'Orçamento 2026'!M36) -> 31998.9 | P17: =IF(P5=$D$2,CRR!M9,'Orçamento 2026'!N36) -> 31998.9 | Q17: =SUM(E17:P17) -> 187372.46 | R17: =Q17/$Q$10 -> 0.059288271 | T17: Câmbio/Bancários | U17: =Q17/$U$8 -> 15614.372
D18: Consórcio | E18: =CRR!B10 -> 11277.6 | F18: =CRR!C10 -> 11277.6 | G18: =CRR!D10 -> 11277.6 | H18: =CRR!E10 -> 11277.6 | I18: =IF(I5=$D$2,CRR!F10,0) -> 11277.6 | J18: =IF(J5=$D$2,CRR!G10,0) -> 0,00 | K18: =IF(K5=$D$2,CRR!H10,0) -> 17767.2 | L18: =IF(L5=$D$2,CRR!I10,0) -> 0 | M18: =IF(M5=$D$2,CRR!J10,0) -> 0 | N18: =IF(N5=$D$2,CRR!K10,0) -> 0 | O18: =IF(O5=$D$2,CRR!L10,0) -> 0 | P18: =IF(P5=$D$2,CRR!M10,0) -> 0 | Q18: =SUM(E18:P18) -> 74155.2 | R18: =Q18/$Q$10 -> 0.02346414 | T18: Consórcio | U18: =Q18/$U$8 -> 6179.6
D19: Previdência | E19: =CRR!B11 -> 4958.36 | F19: =CRR!C11 -> 4860.28 | G19: =CRR!D11 -> 6325.28 | H19: =CRR!E11 -> 5913.91 | I19: =IF(I5=$D$2,CRR!F11,0) -> 2187.12 | J19: =IF(J5=$D$2,CRR!G11,0) -> 3486.48 | K19: =IF(K5=$D$2,CRR!H11,0) -> 3208.11 | L19: =IF(L5=$D$2,CRR!I11,0) -> 0 | M19: =IF(M5=$D$2,CRR!J11,0) -> 0 | N19: =IF(N5=$D$2,CRR!K11,0) -> 0 | O19: =IF(O5=$D$2,CRR!L11,0) -> 0 | P19: =IF(P5=$D$2,CRR!M11,0) -> 0 | Q19: =SUM(E19:P19) -> 30939.54 | R19: =Q19/$Q$10 -> 0.0097898691 | T19: Previdência | U19: =Q19/$U$8 -> 2578.295
D20: Seguro de vida | E20: =CRR!B12 -> 20365.39 | F20: =CRR!C12 -> 11096.95 | G20: =CRR!D12 -> 13782.61 | H20: =CRR!E12 -> 11693.06 | I20: =IF(I5=$D$2,CRR!F12,0) -> 19858.71 | J20: =IF(J5=$D$2,CRR!G12,0) -> 16176.26 | K20: =IF(K5=$D$2,CRR!H12,0) -> 19179.52 | L20: =IF(L5=$D$2,CRR!I12,0) -> 0 | M20: =IF(M5=$D$2,CRR!J12,0) -> 0 | N20: =IF(N5=$D$2,CRR!K12,0) -> 0 | O20: =IF(O5=$D$2,CRR!L12,0) -> 0 | P20: =IF(P5=$D$2,CRR!M12,0) -> 0 | Q20: =SUM(E20:P20) -> 112152.5 | R20: =Q20/$Q$10 -> 0.035487221 | T20: Seguro de vida | U20: =Q20/$U$8 -> 9346.0417
D21: Outros Ramos | E21: =CRR!B13 -> 3858.14 | F21: =CRR!C13 -> 3050.26 | G21: =CRR!D13 -> 5352.73 | H21: =CRR!E13 -> 4397.19 | I21: =IF(I5=$D$2,CRR!F13,0) -> 6761.83 | J21: =IF(J5=$D$2,CRR!G13,0) -> 4404.67 | K21: =IF(K5=$D$2,CRR!H13,0) -> 7245.04 | L21: =IF(L5=$D$2,CRR!I13,0) -> 0 | M21: =IF(M5=$D$2,CRR!J13,0) -> 0 | N21: =IF(N5=$D$2,CRR!K13,0) -> 0 | O21: =IF(O5=$D$2,CRR!L13,0) -> 0 | P21: =IF(P5=$D$2,CRR!M13,0) -> 0 | Q21: =SUM(E21:P21) -> 35069.86 | R21: =Q21/$Q$10 -> 0.011096782 | T21: Outros Ramos | U21: =Q21/$U$8 -> 2922.4883
D22: 01T Receita Bruta de Vendas | Q22: =SUM(E22:P22) -> 0 | R22: =Q22/$Q$10 -> 0 | T22: 01T Receita Bruta de Vendas | U22: =Q22/$U$8 -> 0
D23: 02 Deduções da Receita Bruta | E23: =CNS!B16+CRR!B15 -> -198816.65 | F23: =CNS!C16+CRR!C15 -> -126321.09 | G23: =CNS!D16+CRR!D15 -> -138181.44 | H23: =CNS!E16+CRR!E15 -> -196414.44 | I23: =IF(I5=$D$2,Consolidated!I20,SUM(Projeção!I24:I29)) -> -128726.11 | J23: =IF(J5=$D$2,Consolidated!J20,SUM(Projeção!J24:J29)) -> -128056.72 | K23: =IF(K5=$D$2,Consolidated!K20,SUM(Projeção!K24:K29)) -> -195285.63 | L23: =IF(L5=$D$2,Consolidated!L20,SUM(Projeção!L24:L29)) -> -113498.36 | M23: =IF(M5=$D$2,Consolidated!M20,SUM(Projeção!M24:M29)) -> -113498.36 | N23: =IF(N5=$D$2,Consolidated!N20,SUM(Projeção!N24:N29)) -> -158696.95 | O23: =IF(O5=$D$2,Consolidated!O20,SUM(Projeção!O24:O29)) -> -113498.36 | P23: =IF(P5=$D$2,Consolidated!P20,SUM(Projeção!P24:P29)) -> -113498.36 | Q23: =SUM(E23:P23) -> -1724492.5 | R23: =Q23/$Q$10 -> -0.54566279 | T23: 02 Deduções da Receita Bruta | U23: =Q23/$U$8 -> -143707.71
D24: 02.1 Impostos Sobre Vendas | E24: =CNS!B17+CRR!B16 -> -101514.6 | F24: =CNS!C17+CRR!C16 -> -24032.34 | G24: =CNS!D17+CRR!D16 -> -27344.44 | H24: =CNS!E17+CRR!E16 -> -89882.16 | I24: =IF(I5=$D$2,Consolidated!I21,'Orçamento 2026'!G39+'Orçamento 2026'!G40) -> -23264.24 | J24: =IF(J5=$D$2,Consolidated!J21,'Orçamento 2026'!H39+'Orçamento 2026'!H40) -> -25174.57 | K24: =IF(K5=$D$2,Consolidated!K21,'Orçamento 2026'!I39+'Orçamento 2026'!I40) -> -108615.34 | L24: =IF(L5=$D$2,Consolidated!L21,'Orçamento 2026'!J39+'Orçamento 2026'!J40) -> -33429.041 | M24: =IF(M5=$D$2,Consolidated!M21,'Orçamento 2026'!K39+'Orçamento 2026'!K40) -> -33429.041 | N24: =IF(N5=$D$2,Consolidated!N21,'Orçamento 2026'!L39+'Orçamento 2026'!L40) -> -78627.631 | O24: =IF(O5=$D$2,Consolidated!O21,'Orçamento 2026'!M39+'Orçamento 2026'!M40) -> -33429.041 | P24: =IF(P5=$D$2,Consolidated!P21,'Orçamento 2026'!N39+'Orçamento 2026'!N40) -> -33429.041 | Q24: =SUM(E24:P24) -> -612171.48 | R24: =Q24/$Q$10 -> -0.1937029 | T24: 02.1 Impostos Sobre Vendas | U24: =Q24/$U$8 -> -51014.29
D25: 02.2 Comissões Consultores | E25: =CNS!B18+CRR!B17 -> -89450.63 | F25: =CNS!C18+CRR!C17 -> -91876.31 | G25: =CNS!D18+CRR!D17 -> -98268.03 | H25: =CNS!E18+CRR!E17 -> -95663.76 | I25: =IF(I5=$D$2,Consolidated!I22,'Orçamento 2026'!G41) -> -91912.33 | J25: =IF(J5=$D$2,Consolidated!J22,'Orçamento 2026'!H41) -> -94864.35 | K25: =IF(K5=$D$2,Consolidated!K22,'Orçamento 2026'!I41) -> -78269.48 | L25: =IF(L5=$D$2,Consolidated!L22,'Orçamento 2026'!J41) -> -78811.716 | M25: =IF(M5=$D$2,Consolidated!M22,'Orçamento 2026'!K41) -> -78811.716 | N25: =IF(N5=$D$2,Consolidated!N22,'Orçamento 2026'!L41) -> -78811.716 | O25: =IF(O5=$D$2,Consolidated!O22,'Orçamento 2026'!M41) -> -78811.716 | P25: =IF(P5=$D$2,Consolidated!P22,'Orçamento 2026'!N41) -> -78811.716 | Q25: =SUM(E25:P25) -> -1034363.5 | R25: =Q25/$Q$10 -> -0.32729262 | T25: 02.2 Comissões Consultores | U25: =Q25/$U$8 -> -86196.956
D26: 02.3 Comissões Mesa | E26: =CNS!B19+CRR!B18 -> -5749.27 | F26: =CNS!C19+CRR!C18 -> -5695.28 | G26: =CNS!D19+CRR!D18 -> -7461.4 | H26: =CNS!E19+CRR!E18 -> -5965.22 | I26: =IF(I5=$D$2,Consolidated!I23,0) -> -8479.87 | J26: =IF(J5=$D$2,Consolidated!J23,0) -> -6239.61 | K26: =IF(K5=$D$2,Consolidated!K23,0) -> -6458.99 | L26: =IF(L5=$D$2,Consolidated!L23,0) -> 0 | M26: =IF(M5=$D$2,Consolidated!M23,0) -> 0 | N26: =IF(N5=$D$2,Consolidated!N23,0) -> 0 | O26: =IF(O5=$D$2,Consolidated!O23,0) -> 0 | P26: =IF(P5=$D$2,Consolidated!P23,0) -> 0 | Q26: =SUM(E26:P26) -> -46049.64 | R26: =Q26/$Q$10 -> -0.014570997 | T26: 02.3 Comissões Mesa | U26: =Q26/$U$8 -> -3837.47
D27: 02.4 Descontos Incondicionais | E27: =CNS!B20+CRR!B19 -> 0 | F27: =CNS!C20+CRR!C19 -> -2730 | G27: =CNS!D20+CRR!D19 -> -420 | H27: =CNS!E20+CRR!E19 -> -1880.43 | I27: =IF(I5=$D$2,Consolidated!I24,'Orçamento 2026'!G42) -> -840 | J27: =IF(J5=$D$2,Consolidated!J24,'Orçamento 2026'!H42) -> 0 | K27: =IF(K5=$D$2,Consolidated!K24,'Orçamento 2026'!I42) -> 0 | L27: =IF(L5=$D$2,Consolidated!L24,'Orçamento 2026'!J42) -> -1257.6075 | M27: =IF(M5=$D$2,Consolidated!M24,'Orçamento 2026'!K42) -> -1257.6075 | N27: =IF(N5=$D$2,Consolidated!N24,'Orçamento 2026'!L42) -> -1257.6075 | O27: =IF(O5=$D$2,Consolidated!O24,'Orçamento 2026'!M42) -> -1257.6075 | P27: =IF(P5=$D$2,Consolidated!P24,'Orçamento 2026'!N42) -> -1257.6075 | Q27: =SUM(E27:P27) -> -12158.468 | R27: =Q27/$Q$10 -> -0.0038471744 | T27: 02.4 Descontos Incondicionais | U27: =Q27/$U$8 -> -1013.2056
D28: 02.5 Devoluções de Vendas | E28: =CNS!B21+CRR!B20 -> -1163.72 | F28: =CNS!C21+CRR!C20 -> -1319.61 | G28: =CNS!D21+CRR!D20 -> -3923.62 | H28: =CNS!E21+CRR!E20 -> -1950.63 | I28: =IF(I5=$D$2,Consolidated!I25,'Orçamento 2026'!G43) -> -3298.79 | J28: =CNS!G21+CRR!G20 -> -1471.97 | K28: =CNS!H21+CRR!H20 -> -55.4 | L28: =CNS!I21+CRR!I20 -> 0 | M28: =CNS!J21+CRR!J20 -> 0 | N28: =CNS!K21+CRR!K20 -> 0 | O28: =CNS!L21+CRR!L20 -> 0 | P28: =CNS!M21+CRR!M20 -> 0 | Q28: =SUM(E28:P28) -> -13183.74 | R28: =Q28/$Q$10 -> -0.0041715904 | T28: 02.5 Devoluções de Vendas | U28: =Q28/$U$8 -> -1098.645
D29: 02.6 Comissões Parceiros | E29: =CNS!B22+CRR!B21 -> -938.43 | F29: =CNS!C22+CRR!C21 -> -667.55 | G29: =CNS!D22+CRR!D21 -> -763.95 | H29: =CNS!E22+CRR!E21 -> -1072.24 | I29: =IF(I5=$D$2,Consolidated!I26,0) -> -930.88 | J29: =IF(J5=$D$2,Consolidated!J26,0) -> -306.22 | K29: =IF(K5=$D$2,Consolidated!K26,0) -> -1886.42 | L29: =IF(L5=$D$2,Consolidated!L26,0) -> 0 | M29: =IF(M5=$D$2,Consolidated!M26,0) -> 0 | N29: =IF(N5=$D$2,Consolidated!N26,0) -> 0 | O29: =IF(O5=$D$2,Consolidated!O26,0) -> 0 | P29: =IF(P5=$D$2,Consolidated!P26,0) -> 0 | Q29: =SUM(E29:P29) -> -6565.69 | R29: =Q29/$Q$10 -> -0.0020775114 | T29: 02.6 Comissões Parceiros | U29: =Q29/$U$8 -> -547.14083
D30: 02T Receita Líquida de Vendas | E30: =CNS!B23+CRR!B22 -> 83627.28 | F30: =CNS!C23+CRR!C22 -> 158675.15 | G30: =CNS!D23+CRR!D22 -> 134614.91 | H30: =CNS!E23+CRR!E22 -> 70306.19 | I30: =I10+I23 -> 148608.47 | J30: =J10+J23 -> 173501.15 | K30: =K10+K23 -> 85333.45 | L30: =L10+L23 -> 125280.5 | M30: =M10+M23 -> 125280.5 | N30: =N10+N23 -> 80081.907 | O30: =O10+O23 -> 125280.5 | P30: =P10+P23 -> 125280.5 | Q30: =SUM(E30:P30) -> 1435870.5 | R30: =Q30/$Q$10 -> 0.45433721 | T30: 02T Receita Líquida de Vendas | U30: =Q30/$U$8 -> 119655.87
D31: 03 Custos Operacionais | E31: =CNS!B24+CRR!B23 -> -64960.26 | F31: =CNS!C24+CRR!C23 -> -61297.63 | G31: =CNS!D24+CRR!D23 -> -67942.22 | H31: =CNS!E24+CRR!E23 -> -64575.13 | I31: =IF(I5=$D$2,Consolidated!I28,'Orçamento 2026'!G45) -> -81372.89 | J31: =IF(J5=$D$2,Consolidated!J28,'Orçamento 2026'!H45) -> -66612.71 | K31: =IF(K5=$D$2,Consolidated!K28,'Orçamento 2026'!I45) -> -59682.89 | L31: =IF(L5=$D$2,Consolidated!L28,'Orçamento 2026'!J45) -> -66746.218 | M31: =IF(M5=$D$2,Consolidated!M28,'Orçamento 2026'!K45) -> -67044.687 | N31: =IF(N5=$D$2,Consolidated!N28,'Orçamento 2026'!L45) -> -67344.491 | O31: =IF(O5=$D$2,Consolidated!O28,'Orçamento 2026'!M45) -> -67645.635 | P31: =IF(P5=$D$2,Consolidated!P28,'Orçamento 2026'!N45) -> -67948.126 | Q31: =SUM(E31:P31) -> -803172.89 | R31: =Q31/$Q$10 -> -0.25413944 | T31: 03 Custos Operacionais | U31: =Q31/$U$8 -> -66931.074
D32: 03.1 Salários e Encargos | E32: =CNS!B25+CRR!B24 -> -25426.15 | F32: =CNS!C25+CRR!C24 -> -32678.58 | G32: =CNS!D25+CRR!D24 -> -28556.64 | H32: =CNS!E25+CRR!E24 -> -28209.13 | I32: =IF(I5=$D$2,Consolidated!I29,0) -> -33000.23 | J32: =IF(J5=$D$2,Consolidated!J29,0) -> -34300.75 | K32: =IF(K5=$D$2,Consolidated!K29,0) -> -28209.14 | L32: =IF(L5=$D$2,Consolidated!L29,0) -> 0 | M32: =IF(M5=$D$2,Consolidated!M29,0) -> 0 | N32: =IF(N5=$D$2,Consolidated!N29,0) -> 0 | O32: =IF(O5=$D$2,Consolidated!O29,0) -> 0 | P32: =IF(P5=$D$2,Consolidated!P29,0) -> 0 | Q32: =SUM(E32:P32) -> -210380.62 | R32: =Q32/$Q$10 -> -0.066568499 | T32: 03.1 Salários e Encargos | U32: =Q32/$U$8 -> -17531.718
D33: 03.2 Sistemas | E33: =CNS!B26+CRR!B25 -> -15523.46 | F33: =CNS!C26+CRR!C25 -> -9519.05 | G33: =CNS!D26+CRR!D25 -> -13097.35 | H33: =CNS!E26+CRR!E25 -> -10678.38 | I33: =IF(I5=$D$2,Consolidated!I30,0) -> -9918.7 | J33: =IF(J5=$D$2,Consolidated!J30,0) -> -9939.96 | K33: =IF(K5=$D$2,Consolidated!K30,0) -> -10299.93 | L33: =IF(L5=$D$2,Consolidated!L30,0) -> 0 | M33: =IF(M5=$D$2,Consolidated!M30,0) -> 0 | N33: =IF(N5=$D$2,Consolidated!N30,0) -> 0 | O33: =IF(O5=$D$2,Consolidated!O30,0) -> 0 | P33: =IF(P5=$D$2,Consolidated!P30,0) -> 0 | Q33: =SUM(E33:P33) -> -78976.83 | R33: =Q33/$Q$10 -> -0.024989797 | T33: 03.2 Sistemas | U33: =Q33/$U$8 -> -6581.4025
D34: 03.3 Custo Tesouro mato grosso | E34: =CNS!B27+CRR!B26 -> -21367.88 | F34: =CNS!C27+CRR!C26 -> -19100 | G34: =CNS!D27+CRR!D26 -> -26235.23 | H34: =CNS!E27+CRR!E26 -> -25581.62 | I34: =IF(I5=$D$2,Consolidated!I31,0) -> -32735.46 | J34: =IF(J5=$D$2,Consolidated!J31,0) -> -22372 | K34: =IF(K5=$D$2,Consolidated!K31,0) -> -21173.82 | L34: =IF(L5=$D$2,Consolidated!L31,0) -> 0 | M34: =IF(M5=$D$2,Consolidated!M31,0) -> 0 | N34: =IF(N5=$D$2,Consolidated!N31,0) -> 0 | O34: =IF(O5=$D$2,Consolidated!O31,0) -> 0 | P34: =IF(P5=$D$2,Consolidated!P31,0) -> 0 | Q34: =SUM(E34:P34) -> -168566.01 | R34: =Q34/$Q$10 -> -0.053337547 | T34: 03.3 Custo Tesouro mato grosso | U34: =Q34/$U$8 -> -14047.168
D35: 03.4 Custo RPPS | E35: =CNS!B28+CRR!B27 -> -1119.18 | F35: =CNS!C28+CRR!C27 -> 0 | G35: =CNS!D28+CRR!D27 -> 0 | H35: =CNS!E28+CRR!E27 -> 0 | I35: =IF(I5=$D$2,Consolidated!I32,0) -> 0 | J35: =IF(J5=$D$2,Consolidated!J32,0) -> 0 | K35: =IF(K5=$D$2,Consolidated!K32,0) -> 0 | L35: =IF(L5=$D$2,Consolidated!L32,0) -> 0 | M35: =IF(M5=$D$2,Consolidated!M32,0) -> 0 | N35: =IF(N5=$D$2,Consolidated!N32,0) -> 0 | O35: =IF(O5=$D$2,Consolidated!O32,0) -> 0 | P35: =IF(P5=$D$2,Consolidated!P32,0) -> 0 | Q35: =SUM(E35:P35) -> -1119.18 | R35: =Q35/$Q$10 -> -0.00035413021 | T35: 03.4 Custo RPPS | U35: =Q35/$U$8 -> -93.265
D36: 03.5 Regulatórias | E36: =CNS!B29+CRR!B28 -> -1523.59 | F36: =CNS!C29+CRR!C28 -> 0 | G36: =CNS!D29+CRR!D28 -> -53 | H36: =CNS!E29+CRR!E28 -> -106 | I36: =IF(I5=$D$2,Consolidated!I33,0) -> -5718.5 | J36: =IF(J5=$D$2,Consolidated!J33,0) -> 0 | K36: =IF(K5=$D$2,Consolidated!K33,0) -> 0 | L36: =IF(L5=$D$2,Consolidated!L33,0) -> 0 | M36: =IF(M5=$D$2,Consolidated!M33,0) -> 0 | N36: =IF(N5=$D$2,Consolidated!N33,0) -> 0 | O36: =IF(O5=$D$2,Consolidated!O33,0) -> 0 | P36: =IF(P5=$D$2,Consolidated!P33,0) -> 0 | Q36: =SUM(E36:P36) -> -7401.09 | R36: =Q36/$Q$10 -> -0.0023418481 | T36: 03.5 Regulatórias | U36: =Q36/$U$8 -> -616.7575
D37: 03T Lucro Bruto | E37: =CNS!B30+CRR!B29 -> 18667.02 | F37: =CNS!C30+CRR!C29 -> 97377.52 | G37: =CNS!D30+CRR!D29 -> 66672.69 | H37: =CNS!E30+CRR!E29 -> 5731.06 | I37: =I30+I31 -> 67235.58 | J37: =J30+J31 -> 106888.44 | K37: =K30+K31 -> 25650.56 | L37: =L30+L31 -> 58534.278 | M37: =M30+M31 -> 58235.809 | N37: =N30+N31 -> 12737.416 | O37: =O30+O31 -> 57634.862 | P37: =P30+P31 -> 57332.371 | Q37: =SUM(E37:P37) -> 632697.61 | R37: =Q37/$Q$10 -> 0.20019776 | T37: 03T Lucro Bruto | U37: =Q37/$U$8 -> 52724.8
D38: 04 Despesas Operacionais | E38: =CNS!B31+CRR!B30 -> -23481.5 | F38: =CNS!C31+CRR!C30 -> -24172.25 | G38: =CNS!D31+CRR!D30 -> -24636.4 | H38: =CNS!E31+CRR!E30 -> -21131.77 | I38: =IF(I5=$D$2,Consolidated!I35,'Orçamento 2026'!G47) -> -20692.52 | J38: =IF(J5=$D$2,Consolidated!J35,'Orçamento 2026'!H47) -> -20268.56 | K38: =IF(K5=$D$2,Consolidated!K35,'Orçamento 2026'!I47) -> -30373.03 | L38: =IF(L5=$D$2,Consolidated!L35,'Orçamento 2026'!J47) -> -24096.432 | M38: =IF(M5=$D$2,Consolidated!M35,'Orçamento 2026'!K47) -> -24204.184 | N38: =IF(N5=$D$2,Consolidated!N35,'Orçamento 2026'!L47) -> -24312.417 | O38: =IF(O5=$D$2,Consolidated!O35,'Orçamento 2026'!M47) -> -24421.135 | P38: =IF(P5=$D$2,Consolidated!P35,'Orçamento 2026'!N47) -> -24530.339 | Q38: =SUM(E38:P38) -> -286320.54 | R38: =Q38/$Q$10 -> -0.090597358 | T38: 04 Despesas Operacionais | U38: =Q38/$U$8 -> -23860.045
D39: 04.1 Imóvel | E39: =CNS!B32+CRR!B31 -> -10767.65 | F39: =CNS!C32+CRR!C31 -> -7850.3 | G39: =CNS!D32+CRR!D31 -> -8253.59 | H39: =CNS!E32+CRR!E31 -> -8252.46 | I39: =IF(I5=$D$2,Consolidated!I36,0) -> -9165.58 | J39: =IF(J5=$D$2,Consolidated!J36,0) -> -8964.05 | K39: =IF(K5=$D$2,Consolidated!K36,0) -> -8776.49 | L39: =IF(L5=$D$2,Consolidated!L36,0) -> 0 | M39: =IF(M5=$D$2,Consolidated!M36,0) -> 0 | N39: =IF(N5=$D$2,Consolidated!N36,0) -> 0 | O39: =IF(O5=$D$2,Consolidated!O36,0) -> 0 | P39: =IF(P5=$D$2,Consolidated!P36,0) -> 0 | Q39: =SUM(E39:P39) -> -62030.12 | R39: =Q39/$Q$10 -> -0.01962753 | T39: 04.1 Imóvel | U39: =Q39/$U$8 -> -5169.1767
D40: 04.10 Outras Despesas | E40: =CNS!B33+CRR!B32 -> 0 | F40: =CNS!C33+CRR!C32 -> 0 | G40: =CNS!D33+CRR!D32 -> 0 | H40: =CNS!E33+CRR!E32 -> 0 | I40: =IF(I5=$D$2,Consolidated!I37,0) -> 0 | J40: =IF(J5=$D$2,Consolidated!J37,0) -> 0 | K40: =IF(K5=$D$2,Consolidated!K37,0) -> 0 | L40: =IF(L5=$D$2,Consolidated!L37,0) -> 0 | M40: =IF(M5=$D$2,Consolidated!M37,0) -> 0 | N40: =IF(N5=$D$2,Consolidated!N37,0) -> 0 | O40: =IF(O5=$D$2,Consolidated!O37,0) -> 0 | P40: =IF(P5=$D$2,Consolidated!P37,0) -> 0 | Q40: =SUM(E40:P40) -> 0 | R40: =Q40/$Q$10 -> 0 | T40: 04.10 Outras Despesas | U40: =Q40/$U$8 -> 0
D41: 04.2 Serviços | E41: =CNS!B34+CRR!B33 -> -4432.61 | F41: =CNS!C34+CRR!C33 -> -4617.94 | G41: =CNS!D34+CRR!D33 -> -4617.94 | H41: =CNS!E34+CRR!E33 -> -4617.94 | I41: =IF(I5=$D$2,Consolidated!I38,0) -> -4617.94 | J41: =IF(J5=$D$2,Consolidated!J38,0) -> -4617.94 | K41: =IF(K5=$D$2,Consolidated!K38,0) -> -13617.94 | L41: =IF(L5=$D$2,Consolidated!L38,0) -> 0 | M41: =IF(M5=$D$2,Consolidated!M38,0) -> 0 | N41: =IF(N5=$D$2,Consolidated!N38,0) -> 0 | O41: =IF(O5=$D$2,Consolidated!O38,0) -> 0 | P41: =IF(P5=$D$2,Consolidated!P38,0) -> 0 | Q41: =SUM(E41:P41) -> -41140.25 | R41: =Q41/$Q$10 -> -0.013017571 | T41: 04.2 Serviços | U41: =Q41/$U$8 -> -3428.3542
D42: 04.3 Comerciais | E42: =CNS!B35+CRR!B34 -> -2598.88 | F42: =CNS!C35+CRR!C34 -> -4244.37 | G42: =CNS!D35+CRR!D34 -> -4827.76 | H42: =CNS!E35+CRR!E34 -> -3002.49 | I42: =IF(I5=$D$2,Consolidated!I39,0) -> -1595.19 | J42: =IF(J5=$D$2,Consolidated!J39,0) -> -484.9 | K42: =IF(K5=$D$2,Consolidated!K39,0) -> -195 | L42: =IF(L5=$D$2,Consolidated!L39,0) -> 0 | M42: =IF(M5=$D$2,Consolidated!M39,0) -> 0 | N42: =IF(N5=$D$2,Consolidated!N39,0) -> 0 | O42: =IF(O5=$D$2,Consolidated!O39,0) -> 0 | P42: =IF(P5=$D$2,Consolidated!P39,0) -> 0 | Q42: =SUM(E42:P42) -> -16948.59 | R42: =Q42/$Q$10 -> -0.0053628618 | T42: 04.3 Comerciais | U42: =Q42/$U$8 -> -1412.3825
D43: 04.4 Administrativas | E43: =CNS!B36+CRR!B35 -> -2058.78 | F43: =CNS!C36+CRR!C35 -> -3995.84 | G43: =CNS!D36+CRR!D35 -> -3193.74 | H43: =CNS!E36+CRR!E35 -> -2495.51 | I43: =IF(I5=$D$2,Consolidated!I40,0) -> -2050.44 | J43: =IF(J5=$D$2,Consolidated!J40,0) -> -3872.42 | K43: =IF(K5=$D$2,Consolidated!K40,0) -> -3362.59 | L43: =IF(L5=$D$2,Consolidated!L40,0) -> 0 | M43: =IF(M5=$D$2,Consolidated!M40,0) -> 0 | N43: =IF(N5=$D$2,Consolidated!N40,0) -> 0 | O43: =IF(O5=$D$2,Consolidated!O40,0) -> 0 | P43: =IF(P5=$D$2,Consolidated!P40,0) -> 0 | Q43: =SUM(E43:P43) -> -21029.32 | R43: =Q43/$Q$10 -> -0.0066540838 | T43: 04.4 Administrativas | U43: =Q43/$U$8 -> -1752.4433
D44: 04.5 Colaboradores | E44: =CNS!B37+CRR!B36 -> -2716.72 | F44: =CNS!C37+CRR!C36 -> -2556.94 | G44: =CNS!D37+CRR!D36 -> -2836.51 | H44: =CNS!E37+CRR!E36 -> -1856.51 | I44: =IF(I5=$D$2,Consolidated!I41,0) -> -2356.51 | J44: =IF(J5=$D$2,Consolidated!J41,0) -> -1422.39 | K44: =IF(K5=$D$2,Consolidated!K41,0) -> -3514.15 | L44: =IF(L5=$D$2,Consolidated!L41,0) -> 0 | M44: =IF(M5=$D$2,Consolidated!M41,0) -> 0 | N44: =IF(N5=$D$2,Consolidated!N41,0) -> 0 | O44: =IF(O5=$D$2,Consolidated!O41,0) -> 0 | P44: =IF(P5=$D$2,Consolidated!P41,0) -> 0 | Q44: =SUM(E44:P44) -> -17259.73 | R44: =Q44/$Q$10 -> -0.0054613125 | T44: 04.5 Colaboradores | U44: =Q44/$U$8 -> -1438.3108
D45: 04.6 Diretoria | E45: =CNS!B38+CRR!B37 -> -906.86 | F45: =CNS!C38+CRR!C37 -> -906.86 | G45: =CNS!D38+CRR!D37 -> -906.86 | H45: =CNS!E38+CRR!E37 -> -906.86 | I45: =IF(I5=$D$2,Consolidated!I42,0) -> -906.86 | J45: =IF(J5=$D$2,Consolidated!J42,0) -> -906.86 | K45: =IF(K5=$D$2,Consolidated!K42,0) -> -906.86 | L45: =IF(L5=$D$2,Consolidated!L42,0) -> 0 | M45: =IF(M5=$D$2,Consolidated!M42,0) -> 0 | N45: =IF(N5=$D$2,Consolidated!N42,0) -> 0 | O45: =IF(O5=$D$2,Consolidated!O42,0) -> 0 | P45: =IF(P5=$D$2,Consolidated!P42,0) -> 0 | Q45: =SUM(E45:P45) -> -6348.02 | R45: =Q45/$Q$10 -> -0.0020086364 | T45: 04.6 Diretoria | U45: =Q45/$U$8 -> -529.00167
D46: 04.7 Imobilizados e equipamentos | E46: =CNS!B39+CRR!B38 -> 0 | F46: =CNS!C39+CRR!C38 -> 0 | G46: =CNS!D39+CRR!D38 -> 0 | H46: =CNS!E39+CRR!E38 -> 0 | I46: =CNS!F39+CRR!F38 -> 0 | J46: =CNS!G39+CRR!G38 -> 0 | K46: =CNS!H39+CRR!H38 -> 0 | L46: =CNS!I39+CRR!I38 -> 0 | ... P46: =CNS!M39+CRR!M38 -> 0 | Q46: =SUM(E46:P46) -> 0 | R46: =Q46/$Q$10 -> 0 | T46: 04.7 Imobilizados e equipamentos | U46: =Q46/$U$8 -> 0
D47: 04.8 Vendas | E47: =CNS!B40+CRR!B39 -> 0 | F47: =CNS!C40+CRR!C39 -> 0 | G47: =CNS!D40+CRR!D39 -> 0 | H47: =CNS!E40+CRR!E39 -> 0 | I47: =CNS!F40+CRR!F39 -> 0 | J47: =CNS!G40+CRR!G39 -> 0 | K47: =CNS!H40+CRR!H39 -> 0 | L47: =CNS!I40+CRR!I39 -> 0 | ... P47: =CNS!M40+CRR!M39 -> 0 | Q47: =SUM(E47:P47) -> 0 | R47: =Q47/$Q$10 -> 0 | T47: 04.8 Vendas | U47: =Q47/$U$8 -> 0
D48: 04.9 Veículos | E48: =CNS!B41+CRR!B40 -> 0 | F48: =CNS!C41+CRR!C40 -> 0 | G48: =CNS!D41+CRR!D40 -> 0 | H48: =CNS!E41+CRR!E40 -> 0 | I48: =CNS!F41+CRR!F40 -> 0 | J48: =CNS!G41+CRR!G40 -> 0 | K48: =CNS!H41+CRR!H40 -> 0 | L48: =CNS!I41+CRR!I40 -> 0 | ... P48: =CNS!M41+CRR!M40 -> 0 | Q48: =SUM(E48:P48) -> 0 | R48: =Q48/$Q$10 -> 0 | T48: 04.9 Veículos | U48: =Q48/$U$8 -> 0
D49: 04T Lucro / Prejuízo Operacional | E49: =CNS!B42+CRR!B41 -> -4814.48 | F49: =CNS!C42+CRR!C41 -> 73205.27 | G49: =CNS!D42+CRR!D41 -> 42036.29 | H49: =CNS!E42+CRR!E41 -> -15400.71 | I49: =I37+I38 -> 46543.06 | J49: =J37+J38 -> 86619.88 | K49: =K37+K38 -> -4722.47 | L49: =L37+L38 -> 34437.847 | M49: =M37+M38 -> 34031.626 | N49: =N37+N38 -> -11575.002 | O49: =O37+O38 -> 33213.726 | P49: =P37+P38 -> 32802.032 | Q49: =SUM(E49:P49) -> 346377.07 | R49: =Q49/$Q$10 -> 0.10960041 | S49: =Q49/$Q$30 -> 0.24123141 | T49: 04T Lucro / Prejuízo Operacional | U49: =Q49/$U$8 -> 28864.756
D50: 05 Receitas e Despesas Financeiras | E50: =CNS!B43+CRR!B42 -> -1262.86 | F50: =CNS!C43+CRR!C42 -> -973.2 | G50: =CNS!D43+CRR!D42 -> -337.75 | H50: =CNS!E43+CRR!E42 -> -751.96 | I50: =IF(I5=$D$2,Consolidated!I47,'Orçamento 2026'!G49) -> 271.08 | J50: =IF(J5=$D$2,Consolidated!J47,'Orçamento 2026'!H49) -> -3516.44 | K50: =IF(K5=$D$2,Consolidated!K47,'Orçamento 2026'!I49) -> -129.72 | L50: =IF(L5=$D$2,Consolidated!L47,'Orçamento 2026'!J49) -> -955.11544 | M50: =IF(M5=$D$2,Consolidated!M47,'Orçamento 2026'!K49) -> -955.11544 | N50: =IF(N5=$D$2,Consolidated!N47,'Orçamento 2026'!L49) -> -955.11544 | O50: =IF(O5=$D$2,Consolidated!O47,'Orçamento 2026'!M49) -> -955.11544 | P50: =IF(P5=$D$2,Consolidated!P47,'Orçamento 2026'!N49) -> -955.11544 | Q50: =SUM(E50:P50) -> -11476.427 | R50: =Q50/$Q$10 -> -0.0036313636 | T50: 05 Receitas e Despesas Financeiras | U50: =Q50/$U$8 -> -956.36893
D51: 06 Outras Receitas e Despesas Não Operacionais | E51: =CNS!B44+CRR!B43 -> 8.63 | F51: =CNS!C44+CRR!C43 -> 1.89 | G51: =CNS!D44+CRR!D43 -> 0.6 | H51: =CNS!E44+CRR!E43 -> 3.45 | I51: =IF(I5=$D$2,Consolidated!I48,'Orçamento 2026'!G50) -> 5.19 | J51: =IF(J5=$D$2,Consolidated!J48,'Orçamento 2026'!H50) -> 0 | K51: =IF(K5=$D$2,Consolidated!K48,'Orçamento 2026'!I50) -> -50 | L51: =IF(L5=$D$2,Consolidated!L48,'Orçamento 2026'!J50) -> 0 | M51: =IF(M5=$D$2,Consolidated!M48,'Orçamento 2026'!K50) -> 0 | N51: =IF(N5=$D$2,Consolidated!N48,'Orçamento 2026'!L50) -> 0 | O51: =IF(O5=$D$2,Consolidated!O48,'Orçamento 2026'!M50) -> 0 | P51: =IF(P5=$D$2,Consolidated!P48,'Orçamento 2026'!N50) -> 0 | Q51: =SUM(E51:P51) -> -30.24 | R51: =Q51/$Q$10 -> -9.5685211e-06 | T51: 06 Outras Receitas e Despesas Não Operacionais | U51: =Q51/$U$8 -> -2.52
D52: 06T Lucro / Prejuízo Líquido | E52: =CNS!B45+CRR!B44 -> -6068.71 | F52: =CNS!C45+CRR!C44 -> 72233.96 | G52: =CNS!D45+CRR!D44 -> 41699.14 | H52: =CNS!E45+CRR!E44 -> -16149.22 | I52: =I49+I50+I51 -> 46819.33 | J52: =J49+J50+J51 -> 83103.44 | K52: =K49+K50+K51 -> -4902.19 | L52: =L49+L50+L51 -> 33482.731 | M52: =M49+M50+M51 -> 33076.511 | N52: =N49+N50+N51 -> -12530.117 | O52: =O49+O50+O51 -> 32258.611 | P52: =P49+P50+P51 -> 31846.916 | Q52: =SUM(E52:P52) -> 334870.4 | R52: =Q52/$Q$10 -> 0.10595947 | S52: =Q52/$Q$30 -> 0.23321769 | T52: 06T Lucro / Prejuízo Líquido | U52: =Q52/$U$8 -> 27905.867
D53: 07 Despesas com Investimentos e Empréstimos | E53: =CNS!B46+CRR!B45 -> -10236.57 | F53: =CNS!C46+CRR!C45 -> -10119.25 | G53: =CNS!D46+CRR!D45 -> -8739.58 | H53: =CNS!E46+CRR!E45 -> -10636.86 | I53: =IF(I5=$D$2,Consolidated!I50,'Orçamento 2026'!G52) -> -9270.03 | J53: =IF(J5=$D$2,Consolidated!J50,'Orçamento 2026'!H52) -> -9126.12 | K53: =IF(K5=$D$2,Consolidated!K50,'Orçamento 2026'!I52) -> -9386.01 | L53: =IF(L5=$D$2,Consolidated!L50,'Orçamento 2026'!J52) -> -9378.5881 | M53: =IF(M5=$D$2,Consolidated!M50,'Orçamento 2026'!K52) -> -9378.5881 | N53: =IF(N5=$D$2,Consolidated!N50,'Orçamento 2026'!L52) -> -9378.5881 | O53: =IF(O5=$D$2,Consolidated!O50,'Orçamento 2026'!M52) -> -9378.5881 | P53: =IF(P5=$D$2,Consolidated!P50,'Orçamento 2026'!N52) -> -9378.5881 | Q53: =SUM(E53:P53) -> -114407.36 | R53: =Q53/$Q$10 -> -0.036200703 | T53: 07 Despesas com Investimentos e Empréstimos | U53: =Q53/$U$8 -> -9533.9467
D54: 07.1 Investimentos em Imobilizado | E54: =CNS!B47+CRR!B46 -> 0 | F54: =CNS!C47+CRR!C46 -> -278.09 | G54: =CNS!D47+CRR!D46 -> 0 | H54: =CNS!E47+CRR!E46 -> -558.89 | I54: =IF(I5=$D$2,Consolidated!I51,0) -> 0 | J54: =IF(J5=$D$2,Consolidated!J51,0) -> 0 | K54: =IF(K5=$D$2,Consolidated!K51,0) -> 0 | L54: =IF(L5=$D$2,Consolidated!L51,0) -> 0 | M54: =IF(M5=$D$2,Consolidated!M51,0) -> 0 | N54: =IF(N5=$D$2,Consolidated!N51,0) -> 0 | O54: =IF(O5=$D$2,Consolidated!O51,0) -> 0 | P54: =IF(P5=$D$2,Consolidated!P51,0) -> 0 | Q54: =SUM(E54:P54) -> -836.98 | R54: =Q54/$Q$10 -> -0.00026483667 | T54: 07.1 Investimentos em Imobilizado | U54: =Q54/$U$8 -> -69.748333
D55: 07.2 Empréstimos e Dívidas | E55: =CNS!B48+CRR!B47 -> -10236.57 | F55: =CNS!C48+CRR!C47 -> -9841.16 | G55: =CNS!D48+CRR!D47 -> -8739.58 | H55: =CNS!E48+CRR!E47 -> -10077.97 | I55: =IF(I5=$D$2,Consolidated!I52,0) -> -9270.03 | J55: =IF(J5=$D$2,Consolidated!J52,0) -> -9126.12 | K55: =IF(K5=$D$2,Consolidated!K52,0) -> -9386.01 | L55: =IF(L5=$D$2,Consolidated!L52,0) -> 0 | M55: =IF(M5=$D$2,Consolidated!M52,0) -> 0 | N55: =IF(N5=$D$2,Consolidated!N52,0) -> 0 | O55: =IF(O5=$D$2,Consolidated!O52,0) -> 0 | P55: =IF(P5=$D$2,Consolidated!P52,0) -> 0 | Q55: =SUM(E55:P55) -> -66677.44 | R55: =Q55/$Q$10 -> -0.021098032 | T55: 07.2 Empréstimos e Dívidas | U55: =Q55/$U$8 -> -5556.4533
D56: 07T Lucro / Prejuízo Final | E56: =CNS!B49+CRR!B48 -> -16305.28 | F56: =CNS!C49+CRR!C48 -> 62114.71 | G56: =CNS!D49+CRR!D48 -> 32959.56 | H56: =CNS!E49+CRR!E48 -> -26786.08 | I56: =I52+I53 -> 37549.3 | J56: =J52+J53 -> 73977.32 | K56: =K52+K53 -> -14288.2 | L56: =L52+L53 -> 24104.143 | M56: =M52+M53 -> 23697.922 | N56: =N52+N53 -> -21908.705 | O56: =O52+O53 -> 22880.023 | P56: =P52+P53 -> 22468.328 | Q56: =SUM(E56:P56) -> 220463.04 | R56: =Q56/$Q$10 -> 0.069758772 | S56: =Q56/$Q$30 -> 0.15353964 | T56: 07T Lucro / Prejuízo Final | U56: =Q56/$U$8 -> 18371.92
D61: EBITDA | E61: =E49+(-E24) -> 96700.12 | F61: =F49+(-F24) -> 97237.61 | G61: =G49+(-G24) -> 69380.73 | H61: =H49+(-H24) -> 74481.45 | I61: =I49+(-I24) -> 69807.3 | J61: =J49+(-J24) -> 111794.45 | K61: =K49+(-K24) -> 103892.87 | L61: =L49+(-L24) -> 67866.887 | ... Q61: =Q49+(-Q24) -> 958548.55 | R61: =Q49/Q61 -> 0.36135579
D62: Caixa | E62: =IF(E5=$D$2,Caixa!F6,'Orçamento 2026'!C129) -> 328679.42 | F62: =IF(F5=$D$2,Caixa!G6,Projeção!E62+'Orçamento 2026'!D53) -> 326651.91 | G62: =IF(G5=$D$2,Caixa!H6,Projeção!F62+'Orçamento 2026'!E53) -> 359161.59 | H62: =IF(H5=$D$2,Caixa!I6,Projeção!G62+'Orçamento 2026'!F53) -> 358806.96 | I62: =IF(I5=$D$2,Caixa!J6,Projeção!H62+'Orçamento 2026'!G53) -> 423235.48 | J62: =IF(J5=$D$2,Caixa!K6,Projeção!I62+'Orçamento 2026'!H53-50000) -> 430815.65 | K62: =IF(K5=$D$2,Caixa!L6,Projeção!J62+'Orçamento 2026'!I53-50000) -> 358819.06 | L62: =IF(L5=$D$2,Caixa!M6,Projeção!K62+'Orçamento 2026'!J53-50000) -> 332923.2 | M62: =IF(M5=$D$2,Caixa!N6,Projeção!L62+'Orçamento 2026'!K53) -> 356621.13 | N62: =IF(N5=$D$2,Caixa!O6,Projeção!M62+'Orçamento 2026'!L53) -> 334712.42 | O62: =IF(O5=$D$2,Caixa!P6,Projeção!N62+'Orçamento 2026'!M53) -> 357592.44 | P62: =IF(P5=$D$2,Caixa!Q6,Projeção!O62+'Orçamento 2026'!N53) -> 380060.77
D63: Caixa projetado | E63: ='Orçamento 2026'!C129 -> 328679.42 | F63: ='Orçamento 2026'!D129 -> 375009.95 | G63: ='Orçamento 2026'!E129 -> 422405.78 | H63: ='Orçamento 2026'!F129 -> 390575.13 | I63: ='Orçamento 2026'!G129 -> 437901.91 | J63: ='Orçamento 2026'!H129 -> 427111.48 | K63: ='Orçamento 2026'!I129 -> 365928.65 | L63: ='Orçamento 2026'!J129 -> 332532.8 | ... P63: ='Orçamento 2026'!N129 -> 372170.37
D64: Variação | E64: =IF(E62>0,E62-E63,0) -> 0 | F64: =IF(F62>0,F62-F63,0) -> -48358.043 | G64: =IF(G62>0,G62-G63,0) -> -63244.188 | H64: =IF(H62>0,H62-H63,0) -> -31768.175 | I64: =IF(I62>0,I62-I63,0) -> -14666.434 | J64: =IF(J62>0,J62-J63,0) -> 3704.1715 | K64: =IF(K62>0,K62-K63,0) -> -7109.5936 | L64: =IF(L62>0,L62-L63,0) -> 390.40642 | ... P64: =IF(P62>0,P62-P63,0) -> 7890.4064
D66: Margem EBITDA | E66: =IF(E61<>0,E61/E10,"") -> 0.34236926 | F66: =IF(F61<>0,F61/F10,"") -> 0.3411891 | G66: =IF(G61<>0,G61/G10,"") -> 0.25433159 | H66: =IF(H61<>0,H61/H10,"") -> 0.27924893 | I66: =IF(I61<>0,I61/I10,"") -> 0.25170788 | J66: =IF(J61<>0,J61/J10,"") -> 0.37072304 | K66: =IF(K61<>0,K61/K10,"") -> 0.37022739 | L66: =IF(L61<>0,L61/L10,"") -> 0.28422486 | ... Q66: =IF(Q61<>0,Q61/Q10,"") -> 0.30330331
D67: Margem Bruta | E67: =IF(E37<>0,E37/E10,"") -> 0.066091065 | F67: =IF(F37<>0,F37/F10,"") -> 0.34168002 | G67: =IF(G37<>0,G37/G10,"") -> 0.24440463 | H67: =IF(H37<>0,H37/H10,"") -> 0.021487127 | I67: =IF(I37<>0,I37/I10,"") -> 0.2424349 | J67: =IF(J37<>0,J37/J10,"") -> 0.35445416 | K67: =IF(K37<>0,K37/K10,"") -> 0.091407042 | L67: =IF(L37<>0,L37/L10,"") -> 0.24514012 | ... Q67: =IF(Q37<>0,Q37/Q10,"") -> 0.20019776
D68: Margem Lucro Liquido | E68: =IF(E52<>0,E52/E10,"") -> -0.021486424 | F68: =IF(F52<>0,F52/F10,"") -> 0.25345584 | G68: =IF(G52<>0,G52/G10,"") -> 0.15285813 | H68: =IF(H52<>0,H52/H10,"") -> -0.060547322 | I68: =IF(I52<>0,I52/I10,"") -> 0.16881894 | J68: =IF(J52<>0,J52/J10,"") -> 0.27558041 | K68: =IF(K52<>0,K52/K10,"") -> -0.017469197 | L68: =IF(L52<>0,L52/L10,"") -> 0.14022486 | ... Q68: =IF(Q52<>0,Q52/Q10,"") -> 0.10595947
D69: Margem Lucro Final | E69: =IF(E56<>0,E56/E10,"") -> -0.057729263 | F69: =IF(F56<>0,F56/F10,"") -> 0.21794923 | G69: =IF(G56<>0,G56/G10,"") -> 0.12082112 | H69: =IF(H56<>0,H56/H10,"") -> -0.10042748 | I69: =IF(I56<>0,I56/I10,"") -> 0.1353935 | J69: =IF(J56<>0,J56/J10,"") -> 0.24531716 | K69: =IF(K56<>0,K56/K10,"") -> -0.050916709 | L69: =IF(L56<>0,L56/L10,"") -> 0.10094756 | ... Q69: =IF(Q56<>0,Q56/Q10,"") -> 0.069758772

Sheet H. Receita
D3: MÊS | E3: 01 Receitas Operacionais | F3: 04T Lucro / Prejuízo Operacional | G3: 06T Lucro / Prejuízo Líquido | H3: 07T Lucro / Prejuízo Final | I3: Lucro acumulado | J3: Caixa | L3: MÊS | M3: Positivo | N3: Negativo | Q3: LUCRO T | R3: Positivo | S3: Negativo
D4: 44562 | E4: 113542.34 | F4: 40630.82 | G4: 39783.24 | H4: 39783.24 | I4: =H4 -> 39783.24 | L4: =D4 -> 44562 | M4: =IF(H4>=0,H4,NA()) -> 39783.24 | N4: =IF(H4<0,H4,NA()) -> #N/A | R4: =NA() -> #N/A | S4: =NA() -> #N/A
D5: 44593 | E5: 88704.79 | F5: 8039.58 | G5: 7270.38 | H5: 7270.38 | I5: =H5+I4 -> 47053.62 | L5: =D5 -> 44593 | M5: =IF(H5>=0,H5,NA()) -> 7270.38 | N5: =IF(H5<0,H5,NA()) -> #N/A | P5: 1T22 | Q5: =SUM(H4:H6) -> 51025.55 | R5: =IF(Q5>=0,Q5,NA()) -> 51025.55 | S5: =IF(Q5<0,Q5,NA()) -> #N/A
D6: 44621 | E6: 101759.95 | F6: 5219.41 | G6: 3971.93 | H6: 3971.93 | I6: =H6+I5 -> 51025.55 | L6: =D6 -> 44621 | M6: =IF(H6>=0,H6,NA()) -> 3971.93 | N6: =IF(H6<0,H6,NA()) -> #N/A
D7: 44652 | E7: 117039.52 | F7: -119450.82 | G7: -120711.43 | H7: -120711.43 | I7: =H7+I6 -> -69685.88 | L7: =D7 -> 44652 | M7: =IF(H7>=0,H7,NA()) -> #N/A | N7: =IF(H7<0,H7,NA()) -> -120711.43
D8: 44682 | E8: 110435.48 | F8: -8858.63 | G8: -10290.1 | H8: -10290.1 | I8: =H8+I7 -> -79975.98 | L8: =D8 -> 44682 | M8: =IF(H8>=0,H8,NA()) -> #N/A | N8: =IF(H8<0,H8,NA()) -> -10290.1 | P8: 2T22 | Q8: =SUM(H7:H9) -> -128684.79 | R8: =IF(Q8>=0,Q8,NA()) -> #N/A | S8: =IF(Q8<0,Q8,NA()) -> -128684.79
D9: 44713 | E9: 111353.54 | F9: 3518.84 | G9: 2316.74 | H9: 2316.74 | I9: =H9+I8 -> -77659.24 | L9: =D9 -> 44713 | M9: =IF(H9>=0,H9,NA()) -> 2316.74 | N9: =IF(H9<0,H9,NA()) -> #N/A
D10: 44743 | E10: 92137.23 | F10: -5657.51 | G10: -6944.53 | H10: -6944.53 | I10: =H10+I9 -> -84603.77 | L10: =D10 -> 44743 | M10: =IF(H10>=0,H10,NA()) -> #N/A | N10: =IF(H10<0,H10,NA()) -> -6944.53
D11: 44774 | E11: 80269.7 | F11: -654.66 | G11: -1944.23 | H11: -1944.23 | I11: =H11+I10 -> -86548 | L11: =D11 -> 44774 | M11: =IF(H11>=0,H11,NA()) -> #N/A | N11: =IF(H11<0,H11,NA()) -> -1944.23 | P11: 3T22 | Q11: =SUM(H10:H12) -> 63263.91 | R11: =IF(Q11>=0,Q11,NA()) -> 63263.91 | S11: =IF(Q11<0,Q11,NA()) -> #N/A
D12: 44805 | E12: 86537.23 | F12: 16906.12 | G12: 15731.66 | H12: 72152.67 | I12: =H12+I11 -> -14395.33 | L12: =D12 -> 44805 | M12: =IF(H12>=0,H12,NA()) -> 72152.67 | N12: =IF(H12<0,H12,NA()) -> #N/A
D13: 44835 | E13: 78188.33 | F13: -28267.99 | G13: -29851.53 | H13: -29851.53 | I13: =H13+I12 -> -44246.86 | L13: =D13 -> 44835 | M13: =IF(H13>=0,H13,NA()) -> #N/A | N13: =IF(H13<0,H13,NA()) -> -29851.53
D14: 44866 | E14: 85108.65 | F14: -5760.45 | G14: -7189.37 | H14: -7189.37 | I14: =H14+I13 -> -51436.23 | L14: =D14 -> 44866 | M14: =IF(H14>=0,H14,NA()) -> #N/A | N14: =IF(H14<0,H14,NA()) -> -7189.37 | P14: 4T22 | Q14: =SUM(H13:H15) -> 2032.56 | R14: =IF(Q14>=0,Q14,NA()) -> 2032.56 | S14: =IF(Q14<0,Q14,NA()) -> #N/A
D15: 44896 | E15: 109383.27 | F15: 40662.77 | G15: 39073.46 | H15: 39073.46 | I15: =H15+I14 -> -12362.77 | L15: =D15 -> 44896 | M15: =IF(H15>=0,H15,NA()) -> 39073.46 | N15: =IF(H15<0,H15,NA()) -> #N/A
D16: 44927 | E16: 101362.42 | F16: -49915.95 | G16: -47179.79 | H16: -50335.23 | I16: =H16+I15 -> -62698 | L16: =D16 -> 44927 | M16: =IF(H16>=0,H16,NA()) -> #N/A | N16: =IF(H16<0,H16,NA()) -> -50335.23
D17: 44958 | E17: 120155.32 | F17: 5492.59 | G17: 11851.73 | H17: 11851.73 | I17: =H17+I16 -> -50846.27 | L17: =D17 -> 44958 | M17: =IF(H17>=0,H17,NA()) -> 11851.73 | N17: =IF(H17<0,H17,NA()) -> #N/A | P17: 1T23 | Q17: =SUM(H16:H18) -> -13021.26 | R17: =IF(Q17>=0,Q17,NA()) -> #N/A | S17: =IF(Q17<0,Q17,NA()) -> -13021.26
D18: 44986 | E18: 131601.09 | F18: 22789.07 | G18: 32241.79 | H18: 25462.24 | I18: =H18+I17 -> -25384.03 | L18: =D18 -> 44986 | M18: =IF(H18>=0,H18,NA()) -> 25462.24 | N18: =IF(H18<0,H18,NA()) -> #N/A
D19: 45017 | E19: 153310.85 | F19: 13660.07 | G19: 28485.49 | H19: 28485.49 | I19: =H19+I18 -> 3101.46 | L19: =D19 -> 45017 | M19: =IF(H19>=0,H19,NA()) -> 28485.49 | N19: =IF(H19<0,H19,NA()) -> #N/A
D20: 45047 | E20: 150438.86 | F20: -1917.51 | G20: 14234.72 | H20: 9723.82 | I20: =H20+I19 -> 12825.28 | L20: =D20 -> 45047 | M20: =IF(H20>=0,H20,NA()) -> 9723.82 | N20: =IF(H20<0,H20,NA()) -> #N/A | P20: 2T23 | Q20: =SUM(H19:H21) -> 1864.09 | R20: =IF(Q20>=0,Q20,NA()) -> 1864.09 | S20: =IF(Q20<0,Q20,NA()) -> #N/A
D21: 45078 | E21: 123015.81 | F21: -4824.1 | G21: 10810.3 | H21: -36345.22 | I21: =H21+I20 -> -23519.94 | L21: =D21 -> 45078 | M21: =IF(H21>=0,H21,NA()) -> #N/A | N21: =IF(H21<0,H21,NA()) -> -36345.22
D22: 45108 | E22: 154929.33 | F22: -4845.62 | G22: 4154.59 | H22: -6132.79 | I22: =H22+I21 -> -29652.73 | L22: =D22 -> 45108 | M22: =IF(H22>=0,H22,NA()) -> #N/A | N22: =IF(H22<0,H22,NA()) -> -6132.79
D23: 45139 | E23: 160989.17 | F23: 20397.21 | G23: 30129.03 | H23: 19875.09 | I23: =H23+I22 -> -9777.64 | L23: =D23 -> 45139 | M23: =IF(H23>=0,H23,NA()) -> 19875.09 | N23: =IF(H23<0,H23,NA()) -> #N/A | P23: 3T23 | Q23: =SUM(H22:H24) -> 10423.43 | R23: =IF(Q23>=0,Q23,NA()) -> 10423.43 | S23: =IF(Q23<0,Q23,NA()) -> #N/A
D24: 45170 | E24: 152116.4 | F24: -505.9 | G24: 7393.6 | H24: -3318.87 | I24: =H24+I23 -> -13096.51 | L24: =D24 -> 45170 | M24: =IF(H24>=0,H24,NA()) -> #N/A | N24: =IF(H24<0,H24,NA()) -> -3318.87
D25: 45200 | E25: 135483.48 | F25: -48111.76 | G25: -34894.88 | H25: -44373.71 | I25: =H25+I24 -> -57470.22 | L25: =D25 -> 45200 | M25: =IF(H25>=0,H25,NA()) -> #N/A | N25: =IF(H25<0,H25,NA()) -> -44373.71
D26: 45231 | E26: 139047.26 | F26: 12770.42 | G26: 19406.36 | H26: 9792.03 | I26: =H26+I25 -> -47678.19 | L26: =D26 -> 45231 | M26: =IF(H26>=0,H26,NA()) -> 9792.03 | N26: =IF(H26<0,H26,NA()) -> #N/A | P26: 4T23 | Q26: =SUM(H25:H27) -> -31621.24 | R26: =IF(Q26>=0,Q26,NA()) -> #N/A | S26: =IF(Q26<0,Q26,NA()) -> -31621.24
D27: 45261 | E27: 140276.36 | F27: 5751.39 | G27: 12271.95 | H27: 2960.44 | I27: =H27+I26 -> -44717.75 | L27: =D27 -> 45261 | M27: =IF(H27>=0,H27,NA()) -> 2960.44 | N27: =IF(H27<0,H27,NA()) -> #N/A
D28: 45292 | E28: 128282.56 | F28: -42077.62 | G28: -35345.51 | H28: -44170.3 | I28: =H28+I27 -> -88888.05 | L28: =D28 -> 45292 | M28: =IF(H28>=0,H28,NA()) -> #N/A | N28: =IF(H28<0,H28,NA()) -> -44170.3
D29: 45323 | E29: 140864.22 | F29: 11259.71 | G29: 21028.93 | H29: 11728.76 | I29: =H29+I28 -> -77159.29 | L29: =D29 -> 45323 | M29: =IF(H29>=0,H29,NA()) -> 11728.76 | N29: =IF(H29<0,H29,NA()) -> #N/A | P29: 1T24 | Q29: =SUM(H28:H30) -> -2864.92 | R29: =IF(Q29>=0,Q29,NA()) -> #N/A | S29: =IF(Q29<0,Q29,NA()) -> -2864.92
D30: 45352 | E30: 153430.67 | F30: 32173.62 | G30: 37674.1 | H30: 29576.62 | I30: =H30+I29 -> -47582.67 | L30: =D30 -> 45352 | M30: =IF(H30>=0,H30,NA()) -> 29576.62 | N30: =IF(H30<0,H30,NA()) -> #N/A
D31: 45383 | E31: 121181.32 | F31: -49515.54 | G31: -43839.76 | H31: -43839.76 | I31: =H31+I30 -> -91422.43 | L31: =D31 -> 45383 | M31: =IF(H31>=0,H31,NA()) -> #N/A | N31: =IF(H31<0,H31,NA()) -> -43839.76
D32: 45413 | E32: 128301.22 | F32: -51121.79 | G32: -46067.2 | H32: -46067.2 | I32: =H32+I31 -> -137489.63 | L32: =D32 -> 45413 | M32: =IF(H32>=0,H32,NA()) -> #N/A | N32: =IF(H32<0,H32,NA()) -> -46067.2 | P32: 2T24 | Q32: =SUM(H31:H33) -> 16410.72 | R32: =IF(Q32>=0,Q32,NA()) -> 16410.72 | S32: =IF(Q32<0,Q32,NA()) -> #N/A
D33: 45444 | E33: 212284.81 | F33: 118543.84 | G33: 123390.63 | H33: 106317.68 | I33: =H33+I32 -> -31171.95 | L33: =D33 -> 45444 | M33: =IF(H33>=0,H33,NA()) -> 106317.68 | N33: =IF(H33<0,H33,NA()) -> #N/A
D34: 45474 | E34: 208372.91 | F34: 22984.71 | G34: 28730.83 | H34: 12336.19 | I34: =H34+I33 -> -18835.76 | L34: =D34 -> 45474 | M34: =IF(H34>=0,H34,NA()) -> 12336.19 | N34: =IF(H34<0,H34,NA()) -> #N/A
D35: 45505 | E35: 163398.57 | F35: 4090.6 | G35: 9492.82 | H35: 578.5 | I35: =H35+I34 -> -18257.26 | L35: =D35 -> 45505 | M35: =IF(H35>=0,H35,NA()) -> 578.5 | N35: =IF(H35<0,H35,NA()) -> #N/A | P35: 3T24 | Q35: =SUM(H34:H36) -> 48719.93 | R35: =IF(Q35>=0,Q35,NA()) -> 48719.93 | S35: =IF(Q35<0,Q35,NA()) -> #N/A
D36: 45536 | E36: 185409.45 | F36: 41326.1 | G36: 46577.43 | H36: 35805.24 | I36: =H36+I35 -> 17547.98 | L36: =D36 -> 45536 | M36: =IF(H36>=0,H36,NA()) -> 35805.24 | N36: =IF(H36<0,H36,NA()) -> #N/A
D37: 45566 | E37: 151135.89 | F37: -31894.02 | G37: -26814.17 | H37: -34959.11 | I37: =H37+I36 -> -17411.13 | L37: =D37 -> 45566 | M37: =IF(H37>=0,H37,NA()) -> #N/A | N37: =IF(H37<0,H37,NA()) -> -34959.11
D38: 45597 | E38: 194161.38 | F38: 43727.26 | G38: 48291.31 | H38: 38762.21 | I38: =H38+I37 -> 21351.08 | L38: =D38 -> 45597 | M38: =IF(H38>=0,H38,NA()) -> 38762.21 | N38: =IF(H38<0,H38,NA()) -> #N/A | P38: 4T24 | Q38: =SUM(H37:H39) -> 57951.05 | R38: =IF(Q38>=0,Q38,NA()) -> 57951.05 | S38: =IF(Q38<0,Q38,NA()) -> #N/A
D39: 45627 | E39: 189113.45 | F39: 57090.7 | G39: 61946.48 | H39: 54147.95 | I39: =H39+I38 -> 75499.03 | L39: =D39 -> 45627 | M39: =IF(H39>=0,H39,NA()) -> 54147.95 | N39: =IF(H39<0,H39,NA()) -> #N/A
D40: 45658 | E40: 161027.96 | F40: -39999.73 | G40: -33686.39 | H40: -45310.3 | I40: =H40+I39 -> 30188.73 | J40: 869353.15 | L40: =D40 -> 45658 | M40: =IF(H40>=0,H40,NA()) -> #N/A | N40: =IF(H40<0,H40,NA()) -> -45310.3
D41: 45689 | E41: 163795.67 | F41: 25835.43 | G41: 31790.25 | H41: 22560.76 | I41: =H41+I40 -> 52749.49 | J41: 872518.9 | L41: =D41 -> 45689 | M41: =IF(H41>=0,H41,NA()) -> 22560.76 | N41: =IF(H41<0,H41,NA()) -> #N/A | P41: 1T25 | Q41: =SUM(H40:H42) -> -4982.59 | R41: =IF(Q41>=0,Q41,NA()) -> #N/A | S41: =IF(Q41<0,Q41,NA()) -> -4982.59
D42: 45717 | E42: 176258.62 | F42: 24683.34 | G42: 26800.81 | H42: 17766.95 | I42: =H42+I41 -> 70516.44 | J42: 309261.36 | L42: =D42 -> 45717 | M42: =IF(H42>=0,H42,NA()) -> 17766.95 | N42: =IF(H42<0,H42,NA()) -> #N/A
D43: 45748 | E43: 193137.79 | F43: -16191.57 | G43: -16496.45 | H43: -27414.7 | I43: =H43+I42 -> 43101.74 | J43: 249098.43 | L43: =D43 -> 45748 | M43: =IF(H43>=0,H43,NA()) -> #N/A | N43: =IF(H43<0,H43,NA()) -> -27414.7
D44: 45778 | E44: 219760.12 | F44: 57117.11 | G44: 57975.77 | H44: 47418.35 | I44: =H44+I43 -> 90520.09 | J44: 289377.28 | L44: =D44 -> 45778 | M44: =IF(H44>=0,H44,NA()) -> 47418.35 | N44: =IF(H44<0,H44,NA()) -> #N/A | P44: 2T25 | Q44: =SUM(H43:H45) -> 42552.48 | R44: =IF(Q44>=0,Q44,NA()) -> 42552.48 | S44: =IF(Q44<0,Q44,NA()) -> #N/A
C45: =E45/E42-1 -> 0.15346217 | D45: 45809 | E45: 203307.65 | F45: 34845.07 | G45: 33993.29 | H45: 22548.83 | I45: =H45+I44 -> 113068.92 | J45: 285593.61 | L45: =D45 -> 45809 | M45: =IF(H45>=0,H45,NA()) -> 22548.83 | N45: =IF(H45<0,H45,NA()) -> #N/A
D46: 45839 | E46: 208517.31 | F46: -21202.64 | G46: -21379.9 | H46: -32580.72 | I46: =H46+I45 -> 80488.2 | J46: 255744.58 | L46: =D46 -> 45839 | M46: =IF(H46>=0,H46,NA()) -> #N/A | N46: =IF(H46<0,H46,NA()) -> -32580.72
D47: 45870 | E47: 252663.96 | F47: 79047.51 | G47: 78402.27 | H47: 64152.09 | I47: =H47+I46 -> 144640.29 | J47: 315482.46 | L47: =D47 -> 45870 | M47: =IF(H47>=0,H47,NA()) -> 64152.09 | N47: =IF(H47<0,H47,NA()) -> #N/A | P47: 3T25 | Q47: =SUM(H46:H48) -> 84772.81 | R47: =IF(Q47>=0,Q47,NA()) -> 84772.81 | S47: =IF(Q47<0,Q47,NA()) -> #N/A
C48: =E48/E45-1 -> 0.26496362 | D48: 45901 | E48: 257176.78 | F48: 69155.96 | G48: 68586.1 | H48: 53201.44 | I48: =H48+I47 -> 197841.73 | J48: 336928.89 | L48: =D48 -> 45901 | M48: =IF(H48>=0,H48,NA()) -> 53201.44 | N48: =IF(H48<0,H48,NA()) -> #N/A
D49: 45931 | E49: 318213.4 | F49: 49650.47 | G49: 49542.29 | H49: 38217.75 | I49: =H49+I48 -> 236059.48 | J49: 382169.31 | L49: =D49 -> 45931 | M49: =IF(H49>=0,H49,NA()) -> 38217.75 | N49: =IF(H49<0,H49,NA()) -> #N/A
D50: 45962 | E50: 256763.5 | F50: 55452.8 | G50: 56066.38 | H50: 45208.13 | I50: =H50+I49 -> 281267.61 | J50: 430109.01 | L50: =D50 -> 45962 | M50: =IF(H50>=0,H50,NA()) -> 45208.13 | N50: =IF(H50<0,H50,NA()) -> #N/A | P50: 4T25 | Q50: =SUM(H49:H51) -> 154229.81 | R50: =IF(Q50>=0,Q50,NA()) -> 154229.81 | S50: =IF(Q50<0,Q50,NA()) -> #N/A
C51: =E51/E48-1 -> 0.14165319 | D51: 45992 | E51: 293606.69 | F51: 79692.3 | G51: 79996.85 | H51: 70803.93 | I51: =H51+I50 -> 352071.54 | J51: 503909.51 | L51: =D51 -> 45992 | M51: =IF(H51>=0,H51,NA()) -> 70803.93 | N51: =IF(H51<0,H51,NA()) -> #N/A
D52: 46023 | E52: =Consolidated!E7 -> 282443.93 | F52: =Consolidated!E46 -> -4814.48 | G52: =Consolidated!E49 -> -6068.71 | H52: =Consolidated!E53 -> -16305.28 | I52: =H52+I51 -> 335766.26 | J52: =Caixa!F6 -> 328679.42 | L52: =D52 -> 46023 | M52: =IF(H52>=0,H52,NA()) -> #N/A | N52: =IF(H52<0,H52,NA()) -> -16305.28
D53: 46054 | E53: =Consolidated!F7 -> 284996.24 | F53: =Consolidated!F46 -> 73205.27 | G53: =Consolidated!F49 -> 72233.96 | H53: =Consolidated!F53 -> 62114.71 | I53: =H53+I52 -> 397880.97 | J53: =Caixa!G6 -> 326651.91 | L53: =D53 -> 46054 | M53: =IF(H53>=0,H53,NA()) -> 62114.71 | N53: =IF(H53<0,H53,NA()) -> #N/A | P53: 1T26 | Q53: =SUM(H52:H54) -> 78768.99 | R53: =IF(Q53>=0,Q53,NA()) -> 78768.99 | S53: =IF(Q53<0,Q53,NA()) -> #N/A
C54: =E54/E51-1 -> -0.07087829 | D54: 46082 | E54: =Consolidated!G7 -> 272796.35 | F54: =Consolidated!G46 -> 42036.29 | G54: =Consolidated!G49 -> 41699.14 | H54: =Consolidated!G53 -> 32959.56 | I54: =H54+I53 -> 430840.53 | J54: =Caixa!H6 -> 359161.59 | L54: =D54 -> 46082 | M54: =IF(H54>=0,H54,NA()) -> 32959.56 | N54: =IF(H54<0,H54,NA()) -> #N/A
D55: 46113 | E55: =Consolidated!H7 -> 266720.63 | F55: =Consolidated!H46 -> -15400.71 | G55: =Consolidated!H49 -> -16149.22 | H55: =Consolidated!H53 -> -26786.08 | I55: =H55+I54 -> 404054.45 | J55: =Caixa!I6 -> 358806.96 | L55: =D55 -> 46113 | M55: =IF(H55>=0,H55,NA()) -> #N/A | N55: =IF(H55<0,H55,NA()) -> -26786.08
D56: 46143 | E56: =Consolidated!I7 -> 277334.58 | F56: =Consolidated!I46 -> 46543.06 | G56: =Consolidated!I49 -> 46819.33 | H56: =Consolidated!I53 -> 37549.3 | I56: =H56+I55 -> 441603.75 | J56: =Caixa!J6 -> 423235.48 | L56: =D56 -> 46143 | M56: =IF(H56>=0,H56,NA()) -> 37549.3 | N56: =IF(H56<0,H56,NA()) -> #N/A | P56: 2T26 | Q56: =SUM(H55:H57) -> 84740.54 | R56: =IF(Q56>=0,Q56,NA()) -> 84740.54 | S56: =IF(Q56<0,Q56,NA()) -> #N/A
C57: =E57/E54-1 -> 0.1054322 | D57: 46174 | E57: =Consolidated!J7 -> 301557.87 | F57: =Consolidated!J46 -> 86619.88 | G57: =Consolidated!J49 -> 83103.44 | H57: =Consolidated!J53 -> 73977.32 | I57: =H57+I56 -> 515581.07 | J57: =Caixa!K6 -> 430815.65 | L57: =D57 -> 46174 | M57: =IF(H57>=0,H57,NA()) -> 73977.32 | N57: =IF(H57<0,H57,NA()) -> #N/A
D58: 46204 | E58: =Consolidated!K7 -> 280619.08 | F58: =Consolidated!K46 -> -4722.47 | G58: =Consolidated!K49 -> -4902.19 | H58: =Consolidated!K53 -> -14288.2 | I58: =H58+I57 -> 501292.87 | J58: =Caixa!L6 -> 358819.06 | L58: =D58 -> 46204 | M58: =IF(H58>=0,H58,NA()) -> #N/A | N58: =IF(H58<0,H58,NA()) -> -14288.2
D59: 46235 | E59: =Consolidated!L7 -> 0 | F59: =Consolidated!L46 -> 0 | G59: =Consolidated!L49 -> 0 | H59: =Consolidated!L53 -> 0 | I59: =H59+I58 -> 501292.87 | L59: =D59 -> 46235 | M59: =IF(H59>=0,H59,NA()) -> 0 | N59: =IF(H59<0,H59,NA()) -> #N/A | P59: 3T26 | Q59: =SUM(H58:H60) -> -14288.2 | R59: =IF(Q59>=0,Q59,NA()) -> #N/A | S59: =IF(Q59<0,Q59,NA()) -> -14288.2
C60: =E60/E57-1 -> -1 | D60: 46266 | E60: =Consolidated!M7 -> 0 | F60: =Consolidated!M46 -> 0 | G60: =Consolidated!M49 -> 0 | H60: =Consolidated!M53 -> 0 | I60: =H60+I59 -> 501292.87 | L60: =D60 -> 46266 | M60: =IF(H60>=0,H60,NA()) -> 0 | N60: =IF(H60<0,H60,NA()) -> #N/A
D61: 46296 | E61: =Consolidated!N7 -> 0 | F61: =Consolidated!N46 -> 0 | G61: =Consolidated!N49 -> 0 | H61: =Consolidated!N53 -> 0 | I61: =H61+I60 -> 501292.87 | L61: =D61 -> 46296 | M61: =IF(H61>=0,H61,NA()) -> 0 | N61: =IF(H61<0,H61,NA()) -> #N/A
D62: 46327 | E62: =Consolidated!O7 -> 0 | F62: =Consolidated!O46 -> 0 | G62: =Consolidated!O49 -> 0 | H62: =Consolidated!O53 -> 0 | I62: =H62+I61 -> 501292.87 | L62: =D62 -> 46327 | M62: =IF(H62>=0,H62,NA()) -> 0 | N62: =IF(H62<0,H62,NA()) -> #N/A | P62: 4T26 | Q62: =SUM(H61:H63) -> 0 | R62: =IF(Q62>=0,Q62,NA()) -> 0 | S62: =IF(Q62<0,Q62,NA()) -> #N/A
C63: =E63/E60-1 -> #DIV/0! | D63: 46357 | E63: =Consolidated!P7 -> 0 | F63: =Consolidated!P46 -> 0 | G63: =Consolidated!P49 -> 0 | H63: =Consolidated!P53 -> 0 | I63: =H63+I62 -> 501292.87 | L63: =D63 -> 46357 | M63: =IF(H63>=0,H63,NA()) -> 0 | N63: =IF(H63<0,H63,NA()) -> #N/A

Sheet AuM
A3: Date - Ano | B3: Date - Mês | C3: soma patrimonio por data | D3: Coluna1 | E3: Coluna2
A4: 2020 | B4: janeiro | C4: 140000 | H4: AUM | I4: 300677305 | J4: des
A5: 2020 | B5: fevereiro | C5: 1670000 | H5: Captação | I5: =C72-C69 -> 13871682
A6: 2020 | B6: março | C6: 7989000 | H6: Ticket Médio | I6: 1330386
A7: 2020 | B7: abril | C7: 10279000 | H7: Clientes | I7: 26
A8: 2020 | B8: maio | C8: 14279000 | H8: Churn | I8: 1138000
A9: 2020 | B9: junho | C9: 23632000
A10: 2020 | B10: julho | C10: 45942000 | J10: des | AB10: des
A11: 2020 | B11: agosto | C11: 52027000
A12: 2020 | B12: setembro | C12: 55488000
A13: 2020 | B13: outubro | C13: 57587000
A14: 2020 | B14: novembro | C14: 62318000
A15: 2020 | B15: dezembro | C15: 73497000 | D15: =Table1[[#This Row],[soma patrimonio por data]] -> 73497000
A16: 2021 | B16: janeiro | C16: 78000000
A17: 2021 | B17: fevereiro | C17: 80132000
A18: 2021 | B18: março | C18: 83345000
A19: 2021 | B19: abril | C19: 85167000
A20: 2021 | B20: maio | C20: 84227000
A21: 2021 | B21: junho | C21: 84040000
A22: 2021 | B22: julho | C22: 83505000
A23: 2021 | B23: agosto | C23: 88412500
A24: 2021 | B24: setembro | C24: 91588500
A25: 2021 | B25: outubro | C25: 89282500
A26: 2021 | B26: novembro | C26: 90211900
A27: 2021 | B27: dezembro | C27: 102791730 | D27: =Table1[[#This Row],[soma patrimonio por data]]/D15-1 -> 0.39858402
A28: 2022 | B28: janeiro | C28: 102901730
A29: 2022 | B29: fevereiro | C29: 104946730
A30: 2022 | B30: março | C30: 108974330
A31: 2022 | B31: abril | C31: 111464130
A32: 2022 | B32: maio | C32: 114549130
A33: 2022 | B33: junho | C33: 110465130
A34: 2022 | B34: julho | C34: 114886703
A35: 2022 | B35: agosto | C35: 121044703
A36: 2022 | B36: setembro | C36: 120045703
A37: 2022 | B37: outubro | C37: 124505703
A38: 2022 | B38: novembro | C38: 124747703
A39: 2022 | B39: dezembro | C39: 132092873 | D39: =Table1[[#This Row],[soma patrimonio por data]]/C27-1 -> 0.28505351
A40: 2023 | B40: janeiro | C40: 139279413
A41: 2023 | B41: fevereiro | C41: 154461413
A42: 2023 | B42: março | C42: 170382813
A43: 2023 | B43: abril | C43: 172774223
A44: 2023 | B44: maio | C44: 177770223
A45: 2023 | B45: junho | C45: 186827868
A46: 2023 | B46: julho | C46: 191841913
A47: 2023 | B47: agosto | C47: 203247793
A48: 2023 | B48: setembro | C48: 189460326
A49: 2023 | B49: outubro | C49: 191324326
A50: 2023 | B50: novembro | C50: 192604326
A51: 2023 | B51: dezembro | C51: 197799896 | D51: =Table1[[#This Row],[soma patrimonio por data]]/C39-1 -> 0.49743049
A52: 2024 | B52: janeiro | C52: 198682357
A53: 2024 | B53: fevereiro | C53: 201650489
A54: 2024 | B54: março | C54: 205117261
A55: 2024 | B55: abril | C55: 214972687
A56: 2024 | B56: maio | C56: 201977250
A57: 2024 | B57: junho | C57: 204036094
A58: 2024 | B58: julho | C58: 206802825
A59: 2024 | B59: agosto | C59: 212110681
A60: 2024 | B60: setembro | C60: 194722394
A61: 2024 | B61: outubro | C61: 197478689
A62: 2024 | B62: novembro | C62: 204031269
A63: 2024 | B63: dezembro | C63: 204764492 | D63: =Table1[[#This Row],[soma patrimonio por data]]/C51-1 -> 0.035210312
A64: 2025 | B64: janeiro | C64: 216093206
A65: 2025 | B65: fevereiro | C65: 240222663
A66: 2025 | B66: março | C66: 245784695
A67: 2025 | B67: abril | C67: 268699101
A68: 2025 | B68: maio | C68: 271198724
A69: 2025 | B69: junho | C69: 286795623
A70: 2025 | B70: julho | C70: 292458969
A71: 2025 | B71: agosto | C71: 295793357
A72: 2025 | B72: setembro | C72: 300667305 | D72: =Table1[[#This Row],[soma patrimonio por data]]/C63-1 -> 0.46835666 | E72: =Table1[[#This Row],[soma patrimonio por data]]-C69 -> 13871682
A73: 2025 | B73: outubro | C73: 304089276
A74: 2025 | B74: novembro | C74: 306823811
A75: 2025 | B75: dezembro | C75: 310965744 | D75: =Table1[[#This Row],[soma patrimonio por data]]/C63-1 -> 0.51865072
A76: 2026 | B76: janeiro | C76: 290504767
A77: 2026 | B77: fevereiro | C77: 304511145
A78: 2026 | B78: março | C78: 309415143 | D78: =Table1[[#This Row],[soma patrimonio por data]]/C75-1 -> -0.0049864045
A79: 2026 | B79: abril | C79: 311856596
A80: 2026 | B80: maio | C80: 312069591
A81: 2026 | B81: junho | C81: 295791970
A82: 2026 | B82: julho | C82: 254401486
A83: 2026 | B83: agosto
A84: 2026 | B84: setembro
A85: 2026 | B85: outubro
A86: 2026 | B86: novembro | H86: Número de clientes (dash) | I86: 255 | K86: Captação Bruta | L86: =L88+L87 -> 28627174 | O86: Churn | P86: =P88+P87 -> 28631328
A87: 2026 | B87: dezembro | H87: Captação líquida | I87: =L86-P86 -> -4154 | K87: Novos contratos | L87: 9922559 | O87: Retiradas | P87: 27316328
H88: Ticket Médio | I88: =C80/I86 -> 1223802.3 | K88: Renovações | L88: 18704615 | O88: Cancelamentos | P88: 1315000
H89: Saldo de clientes | I89: =L89-P89 -> 14 | K89: Entrada de clientes | L89: 23 | O89: Saída de clientes | P89: 9

Sheet Captação
F3: Item | G3: Janeiro | H3: Fevereiro | I3: Março | J3: Abril | K3: Maio | L3: Junho | M3: Julho | N3: Agosto | O3: Setembro | P3: Outubro | Q3: Novembro | R3: Dezembro
F4: AuM | G4: =IF(AuM!C76>0,AuM!C76,"") -> 290504767 | H4: =IF(AuM!C77>0,AuM!C77,"") -> 304511145 | I4: =IF(AuM!C78>0,AuM!C78,"") -> 309415143 | J4: =IF(AuM!C79>0,AuM!C79,"") -> 311856596 | K4: =IF(AuM!C80>0,AuM!C80,"") -> 312069591 | L4: =IF(AuM!C81>0,AuM!C81,0) -> 295791970 | M4: =IF(AuM!C82>0,AuM!C82,0) -> 254401486 | N4: =IF(AuM!C83>0,AuM!C83,0) -> 0 | O4: =IF(AuM!C84>0,AuM!C84,0) -> 0 | P4: =IF(AuM!C85>0,AuM!C85,0) -> 0 | Q4: =IF(AuM!C86>0,AuM!C86,0) -> 0 | R4: =IF(AuM!C87>0,AuM!C87,0) -> 0
F5: Número de clientes (dash) | G5: 247 | H5: 251 | I5: 254 | J5: 257 | K5: 255 | L5: 222 | M5: 184
F6: Captação líquida | G6: =G9-G13 -> -21263977 | H6: =H9-H13 -> 13701377 | I6: =I9-I13 -> 4903998 | J6: =J9-J13 -> 2441453 | K6: =K9-K13 -> 212995 | L6: =L9-L13 -> -15310509 | M6: =M9-M13 -> -34513484 | N6: =N9-N13 -> 0 | ... R6: =R9-R13 -> 0
F7: Ticket Médio | G7: =IF(G4<>0,G4/G5,"") -> 1176132.7 | H7: =IF(H4<>0,H4/H5,"") -> 1213191.8 | I7: =IF(I4<>0,I4/I5,"") -> 1218169.9 | J7: =IF(J4<>0,J4/J5,"") -> 1213449.8 | K7: =IF(K4<>0,K4/K5,"") -> 1223802.3 | L7: 1338425 | M7: =IF(M4<>0,M4/M5,"") -> 1382616.8 | N7: =IF(N4<>0,N4/N5,"") | O7: =IF(O4<>0,O4/O5,"") | P7: =IF(P4<>0,P4/P5,"") | Q7: =IF(Q4<>0,Q4/Q5,"") | R7: =IF(R4<>0,R4/R5,"")
F8: Saldo de clientes | G8: =G12-G16 -> 6 | H8: =H12-H16 -> 4 | I8: =I12-I16 -> 3 | J8: =J12-J16 -> 3 | K8: =K12-K16 -> -2 | L8: =L12-L16 -> -33 | M8: =M12-M16 -> -35 | N8: =N12-N16 -> 0 | ... R8: =R12-R16 -> 0
F9: Captação Bruta | G9: =G11+G10 -> 5736023 | H9: =H11+H10 -> 13701377 | I9: =I11+I10 -> 5520326 | J9: =J11+J10 -> 2441453 | K9: =K11+K10 -> 1227995 | L9: =L11+L10 -> 2314000 | M9: =M11+M10 -> 5317000 | N9: =N11+N10 -> 0 | ... R9: =R11+R10 -> 0
F10: Novos contratos | G10: 5380559 | H10: 1250000 | I10: 2315000 | J10: 977000 | K10: 0 | L10: 0 | M10: 4500000
F11: Renovações | G11: 355464 | H11: 12451377 | I11: 3205326 | J11: 1464453 | K11: 1227995 | L11: 2314000 | M11: 817000
F12: Entrada de clientes | G12: 10 | H12: 4 | I12: 6 | J12: 3 | K12: 0 | L12: 0 | M12: 2
F13: Churn | G13: =G15+G14 -> 27000000 | H13: =H15+H14 -> 0 | I13: =I15+I14 -> 616328 | J13: =J15+J14 -> 0 | K13: =K15+K14 -> 1015000 | L13: =L15+L14 -> 17624509 | M13: =M15+M14 -> 39830484 | N13: =N15+N14 -> 0 | ... R13: =R15+R14 -> 0
F14: Retiradas | G14: 26700000 | H14: 0 | I14: 616328 | J14: 0 | K14: 0 | L14: 0 | M14: 0
F15: Cancelamentos | G15: 300000 | H15: 0 | I15: 0 | J15: 0 | K15: 1015000 | L15: 17624509 | M15: 39830484
F16: Saída de clientes | G16: 4 | H16: 0 | I16: 3 | J16: 0 | K16: 2 | L16: 33 | M16: 37
G20: =AuM!C75 -> 310965744 | H20: =G4 -> 290504767 | I20: =H4 -> 304511145 | J20: =I4 -> 309415143 | K20: =J4 -> 311856596
G21: =G20+G6 -> 289701767 | H21: =H20+H6 -> 304206144 | I21: =I20+I6 -> 309415143 | J21: =J20+J6 -> 311856596 | K21: =K20+K6 -> 312069591
G22: =G4-G21 -> 803000 | H22: =H4-H21 -> 305001 | I22: =I4-I21 -> 0 | J22: =J4-J21 -> 0 | K22: =K4-K21 -> 0

Sheet Receita
G13: Centro de custo | H13: Categoria | J13: Valor total | K13: AV(%) | R13: =Tabela1[[#Totals],[jul./26]] -> 279255.05 | Y13: Total
F14: Empresa | G14: Centro de custos | H14: Categoria | I14: consultor | J14: Coluna1 | K14: 100% | L14: jan./26 | M14: fev./26 | N14: mar./26 | O14: abr./26 | P14: mai./26 | Q14: jun./26 | R14: jul./26 | S14: ago./26 | T14: set./26 | U14: out./26 | V14: nov./26 | W14: dez./26
F15: Consultoria | G15: Consultoria | H15: Consultoria - Augusto | I15: Augusto | J15: =SUM(Tabela1[[#This Row],[jan./26]:[dez./26]]) -> 399506.78 | K15: =Tabela1[[#This Row],[Coluna1]]/Tabela1[[#Totals],[Coluna1]] -> 0.2046279 | L15: 50753.71 | M15: 56342.5 | N15: 57208.41 | O15: 57069.25 | P15: 57868.47 | Q15: 58895.34 | R15: 61369.1
F16: Consultoria | G16: Consultoria | H16: Consultoria - Lamour | I16: Lamour | J16: =SUM(Tabela1[[#This Row],[jan./26]:[dez./26]]) -> 273234.53 | K16: =Tabela1[[#This Row],[Coluna1]]/Tabela1[[#Totals],[Coluna1]] -> 0.13995109 | L16: 37845.62 | M16: 34519.25 | N16: 38219.94 | O16: 42347.39 | P16: 40000.03 | Q16: 40456.3 | R16: 39846 | Y16: {=_xlfn.GROUPBY(Receita!$I$15:$I$143,Receita!$J$15:$J$143,_xleta.SUM,,,-2,,)} -> Augusto | Z16: 586894.7 | AA16: =Z16/$Z$24 -> 0.30060824
F17: Consultoria | G17: Consultoria | H17: Consultoria - Gaioso | I17: Gaioso | J17: =SUM(Tabela1[[#This Row],[jan./26]:[dez./26]]) -> 207490.21 | K17: =Tabela1[[#This Row],[Coluna1]]/Tabela1[[#Totals],[Coluna1]] -> 0.10627676 | L17: 29098.64 | M17: 28086.87 | N17: 28244.31 | O17: 28699.06 | P17: 37481.04 | Q17: 26681.67 | R17: 29198.62 | Y17: Andaluz | Z17: 349680.02 | AA17: =Z17/$Z$24 -> 0.17910657
F18: Consultoria | G18: Consultoria | H18: Consultoria - Sidney | I18: Sidney | J18: =SUM(Tabela1[[#This Row],[jan./26]:[dez./26]]) -> 204622.64 | K18: =Tabela1[[#This Row],[Coluna1]]/Tabela1[[#Totals],[Coluna1]] -> 0.10480799 | L18: 29385.47 | M18: 29374 | N18: 29385.47 | O18: 28993.7 | P18: 29232.47 | Q18: 29237.43 | R18: 29014.1 | Y18: Lamour | Z18: 316972.75 | AA18: =Z18/$Z$24 -> 0.16235386
F19: Consultoria | G19: Tesouro Mato Grosso | H19: Tesouro Mato Grosso | I19: Andaluz | J19: =SUM(Tabela1[[#This Row],[jan./26]:[dez./26]]) -> 176786.4 | K19: =Tabela1[[#This Row],[Coluna1]]/Tabela1[[#Totals],[Coluna1]] -> 0.090550229 | L19: 32368 | M19: 0 | N19: 0 | O19: 0 | P19: 32368 | Q19: 79682.4 | R19: 32368 | Y19: Gaioso | Z19: 227637.25 | AA19: =Z19/$Z$24 -> 0.1165961
F20: Consultoria | G20: Consultoria | H20: Consultoria - Pedro | I20: Pedro | J20: =SUM(Tabela1[[#This Row],[jan./26]:[dez./26]]) -> 96453.85 | K20: =Tabela1[[#This Row],[Coluna1]]/Tabela1[[#Totals],[Coluna1]] -> 0.04940379 | L20: 13312.09 | M20: 14869.96 | N20: 16284.9 | O20: 18975.32 | P20: 15929.8 | Q20: 15331.78 | R20: 1750 | Y20: Sidney | Z20: 224492.17 | AA20: =Z20/$Z$24 -> 0.11498519
F21: Consultoria | G21: Consultoria | H21: Consultoria - Cristiano | I21: Cristiano | J21: =SUM(Tabela1[[#This Row],[jan./26]:[dez./26]]) -> 88110.77 | K21: =Tabela1[[#This Row],[Coluna1]]/Tabela1[[#Totals],[Coluna1]] -> 0.045130453 | L21: 12738.43 | M21: 11614.62 | N21: 12858.35 | O21: 12990.19 | P21: 12990.19 | Q21: 12390.19 | R21: 12528.8 | Y21: Pedro | Z21: 138255.41 | AA21: =Z21/$Z$24 -> 0.070814604
F22: Consultoria | G22: Tesouro Mato Grosso | H22: Receitas de Serviços | I22: Andaluz | J22: =SUM(Tabela1[[#This Row],[jan./26]:[dez./26]]) -> 64736 | K22: =Tabela1[[#This Row],[Coluna1]]/Tabela1[[#Totals],[Coluna1]] -> 0.033157865 | L22: 0 | M22: 0 | N22: 32368 | O22: 32368 | Y22: Cristiano | Z22: 101836.27 | AA22: =Z22/$Z$24 -> 0.052160673
F23: Consultoria | G23: RPPS | H23: RPPS Niterói | I23: Andaluz | J23: =SUM(Tabela1[[#This Row],[jan./26]:[dez./26]]) -> 61392.02 | K23: =Tabela1[[#This Row],[Coluna1]]/Tabela1[[#Totals],[Coluna1]] -> 0.031445074 | L23: 26487.74 | M23: 0 | N23: 0 | O23: 28965.11 | Q23: 5939.17 | Y23: Bruno | Z23: 6588.73 | AA23: =Z23/$Z$24 -> 0.0033747562
F24: Consultoria | G24: Planejamento | H24: Planejamento - Augusto | I24: Augusto | J24: =SUM(Tabela1[[#This Row],[jan./26]:[dez./26]]) -> 26780 | K24: =Tabela1[[#This Row],[Coluna1]]/Tabela1[[#Totals],[Coluna1]] -> 0.013716752 | L24: 4200 | M24: 6720 | N24: 2000 | O24: 3780 | P24: 3360 | R24: 6720 | Y24: Total | Z24: 1952357.3 | AA24: =Z24/$Z$24 -> 1
F25: Consultoria | G25: Planejamento | H25: Planejamento - Lamour | I25: Lamour | J25: =SUM(Tabela1[[#This Row],[jan./26]:[dez./26]]) -> 21400 | K25: =Tabela1[[#This Row],[Coluna1]]/Tabela1[[#Totals],[Coluna1]] -> 0.010961108 | L25: 10500 | M25: 2100 | N25: 0 | O25: 2300 | P25: 2300 | R25: 4200
F26: Consultoria | G26: Planejamento | H26: Planejamento - Pedro | I26: Pedro | J26: =SUM(Tabela1[[#This Row],[jan./26]:[dez./26]]) -> 15330 | K26: =Tabela1[[#This Row],[Coluna1]]/Tabela1[[#Totals],[Coluna1]] -> 0.0078520463 | L26: 0 | M26: 7350 | N26: 7980 | O26: 0
F27: Consultoria | G27: Ganhos Financeiros | H27: Juros investimento | I27: Andaluz | J27: =SUM(Tabela1[[#This Row],[jan./26]:[dez./26]]) -> 12274.51 | K27: =Tabela1[[#This Row],[Coluna1]]/Tabela1[[#Totals],[Coluna1]] -> 0.0062870203 | L27: 1000.33 | M27: 1168.47 | N27: 1870.76 | O27: 1580.63 | P27: 2314.86 | Q27: 1815.28 | R27: 2524.18
F28: Consultoria | G28: Sem centro de custo | H28: Ajuste Financeiro | I28: Andaluz | J28: =SUM(Tabela1[[#This Row],[jan./26]:[dez./26]]) -> 9030.37 | K28: =Tabela1[[#This Row],[Coluna1]]/Tabela1[[#Totals],[Coluna1]] -> 0.0046253675 | L28: 8702.25 | M28: 0.01 | N28: 328.11 | O28: 0 | AS28: 0.693
F29: Consultoria | G29: RPPS | H29: Receitas de Serviços | I29: Andaluz | J29: =SUM(Tabela1[[#This Row],[jan./26]:[dez./26]]) -> 5939.17 | K29: =Tabela1[[#This Row],[Coluna1]]/Tabela1[[#Totals],[Coluna1]] -> 0.0030420508 | L29: 0 | M29: 5939.17 | N29: 0 | O29: 0 | Y29: Centro de custo | Z29: % | AA29: R$ | AS29: 0.088
F30: Consultoria | G30: Consultoria | H30: Consultoria - Bruno | I30: Bruno | J30: =SUM(Tabela1[[#This Row],[jan./26]:[dez./26]]) -> 5250 | K30: =Tabela1[[#This Row],[Coluna1]]/Tabela1[[#Totals],[Coluna1]] -> 0.002689057 | L30: 750 | M30: 750 | N30: 750 | O30: 750 | P30: 750 | Q30: 750 | R30: 750 | Y30: Consultoria | Z30: =Tabela5[[#This Row],[R$]]/Tabela5[[#Totals],[R$]] -> 0.65353979 | AA30: =SUMIF($G$15:$G$143,Y30,$J$15:$J$143) -> 1274668.8 | AC30: Consultoria | AD30: =Tabela5[[#This Row],[%]] -> 0.65353979 | AS30: 0.066
F31: Consultoria | G31: Planejamento | H31: Planejamento - Cristiano | I31: Cristiano | J31: =SUM(Tabela1[[#This Row],[jan./26]:[dez./26]]) -> 3990 | K31: =Tabela1[[#This Row],[Coluna1]]/Tabela1[[#Totals],[Coluna1]] -> 0.0020436833 | R31: 3990 | Y31: Tesouro Mato Grosso | Z31: =Tabela5[[#This Row],[R$]]/Tabela5[[#Totals],[R$]] -> 0.12383178 | AA31: =SUMIF($G$15:$G$143,Y31,$J$15:$J$143) -> 241522.4 | AC31: Institucional | AD31: =Tabela5[[#This Row],[%]]+Z33 -> 0.15835338 | AS31: 0.047
F32: Consultoria | G32: Planejamento | H32: Planejamento - Gaioso | I32: Gaioso | J32: =SUM(Tabela1[[#This Row],[jan./26]:[dez./26]]) -> 3360 | K32: =Tabela1[[#This Row],[Coluna1]]/Tabela1[[#Totals],[Coluna1]] -> 0.0017209965 | R32: 3360 | Y32: Seguro de vida | Z32: =Tabela5[[#This Row],[R$]]/Tabela5[[#Totals],[R$]] -> 0.056014157 | AA32: =SUMIF($G$15:$G$143,Y32,$J$15:$J$143) -> 109250.42 | AC32: Vida | AD32: =Tabela5[[#This Row],[%]] -> 0.056014157 | AS32: 0.04
F33: Consultoria | G33: Consulta | H33: Consulta - Augusto | I33: Augusto | J33: =SUM(Tabela1[[#This Row],[jan./26]:[dez./26]]) -> 1350 | K33: =Tabela1[[#This Row],[Coluna1]]/Tabela1[[#Totals],[Coluna1]] -> 0.00069147179 | L33: 0 | M33: 750 | N33: 600 | O33: 0 | Y33: RPPS | Z33: =Tabela5[[#This Row],[R$]]/Tabela5[[#Totals],[R$]] -> 0.034521605 | AA33: =SUMIF($G$15:$G$143,Y33,$J$15:$J$143) -> 67331.19 | AC33: =Y34 -> Consórcio | AD33: =Z34 -> 0.035685695 | AS33: 0.024 | AU33: =SUM(AS28:AS39) -> 1
F34: Consultoria | G34: Consulta | H34: Consulta - Gaioso | I34: Gaioso | J34: =SUM(Tabela1[[#This Row],[jan./26]:[dez./26]]) -> 1200 | K34: =Tabela1[[#This Row],[Coluna1]]/Tabela1[[#Totals],[Coluna1]] -> 0.00061464159 | L34: 0 | M34: 0 | N34: 0 | O34: 1200 | Y34: Consórcio | Z34: =Tabela5[[#This Row],[R$]]/Tabela5[[#Totals],[R$]] -> 0.035685695 | AA34: =SUMIF($G$15:$G$143,Y34,$J$15:$J$143) -> 69601.64 | AC34: =Y35 -> Planejamento | AD34: =Z35 -> 0.036330873 | AS34: 0.019
F35: Consultoria | G35: Consulta | H35: Consulta - Pedro | I35: Pedro | J35: =SUM(Tabela1[[#This Row],[jan./26]:[dez./26]]) -> 375 | K35: =Tabela1[[#This Row],[Coluna1]]/Tabela1[[#Totals],[Coluna1]] -> 0.0001920755 | L35: 375 | M35: 0 | N35: 0 | O35: 0 | Y35: Planejamento | Z35: =Tabela5[[#This Row],[R$]]/Tabela5[[#Totals],[R$]] -> 0.036330873 | AA35: =SUMIF($G$15:$G$143,Y35,$J$15:$J$143) -> 70860 | AC35: =Y36 -> Previdência | AD35: =Z36 -> 0.015129609 | AS35: 0.012
F36: Consultoria | G36: Ajustes Financeiros | H36: Ajuste Financeiro | I36: Andaluz | J36: =SUM(Tabela1[[#This Row],[jan./26]:[dez./26]]) -> 261.61 | K36: =Tabela1[[#This Row],[Coluna1]]/Tabela1[[#Totals],[Coluna1]] -> 0.00013399699 | L36: 200.7 | M36: 0 | N36: 0 | O36: 0 | P36: 60.91 | Y36: Previdência | Z36: =Tabela5[[#This Row],[R$]]/Tabela5[[#Totals],[R$]] -> 0.015129609 | AA36: =SUMIF($G$15:$G$143,Y36,$J$15:$J$143) -> 29508.9 | AC36: Outros | AD36: =SUM(Z37:Z53) -> 0.044946494 | AS36: 0.005
F37: Consultoria | G37: Ganhos Financeiros | H37: Rendimento conta | I37: Andaluz | J37: =SUM(Tabela1[[#This Row],[jan./26]:[dez./26]]) -> 28.09 | K37: =Tabela1[[#This Row],[Coluna1]]/Tabela1[[#Totals],[Coluna1]] -> 1.4387735e-05 | L37: 1.48 | M37: 1.37 | N37: 2.7 | O37: 4.65 | P37: 2.43 | Q37: 7.15 | R37: 8.31 | Y37: Bancário | Z37: =Tabela5[[#This Row],[R$]]/Tabela5[[#Totals],[R$]] -> 0.013869472 | AA37: =SUMIF($G$15:$G$143,Y37,$J$15:$J$143) -> 27051.12 | AS37: 0.003
F38: Consultoria | G38: Receitas diversas | H38: Reembolso | I38: Andaluz | J38: =SUM(Tabela1[[#This Row],[jan./26]:[dez./26]]) -> 14.57 | K38: =Tabela1[[#This Row],[Coluna1]]/Tabela1[[#Totals],[Coluna1]] -> 7.4627733e-06 | L38: 8.63 | M38: 1.89 | N38: 0.6 | O38: 3.45 | Y38: Sem centro de custo | Z38: =Tabela5[[#This Row],[R$]]/Tabela5[[#Totals],[R$]] -> 0.0065986833 | AA38: =SUMIF($G$15:$G$143,Y38,$J$15:$J$143) -> 12870.12 | AS38: 0.002
F39: Corretora | G39: Consórcio | H39: Consórcio - Augusto | I39: Augusto | J39: =SUM(Tabela1[[#This Row],[jan./26]:[dez./26]]) -> 69601.64 | K39: =Tabela1[[#This Row],[Coluna1]]/Tabela1[[#Totals],[Coluna1]] -> 0.035650052 | L39: 10544.56 | M39: 10544.56 | N39: 10544.56 | O39: 10544.56 | P39: 10544.56 | R39: 16878.84 | Y39: Seguro Residencial | Z39: =Tabela5[[#This Row],[R$]]/Tabela5[[#Totals],[R$]] -> 0.0080072147 | AA39: =SUMIF($G$15:$G$143,Y39,$J$15:$J$143) -> 15617.33 | AS39: 0.001
F40: Corretora | G40: Seguro de vida | H40: Seguro de Vida - Mongeral - Augusto | I40: Augusto | J40: =SUM(Tabela1[[#This Row],[jan./26]:[dez./26]]) -> 25728.57 | K40: =Tabela1[[#This Row],[Coluna1]]/Tabela1[[#Totals],[Coluna1]] -> 0.013178208 | L40: =3153.59+181.22 -> 3334.81 | M40: =3163.05+181.22 -> 3344.27 | N40: =3163.52+181.22 -> 3344.74 | O40: =3169.68+181.22 -> 3350.9 | P40: 2711.06 | Q40: 7242.7 | R40: 2400.09 | Y40: Ganhos Financeiros | Z40: =Tabela5[[#This Row],[R$]]/Tabela5[[#Totals],[R$]] -> 0.0063077081 | AA40: =SUMIF($G$15:$G$143,Y40,$J$15:$J$143) -> 12302.6
F41: Corretora | G41: Seguro de Vida | H41: Seguro de Vida - Prudential - Augusto | I41: Augusto | J41: =SUM(Tabela1[[#This Row],[jan./26]:[dez./26]]) -> 19852.36 | K41: =Tabela1[[#This Row],[Coluna1]]/Tabela1[[#Totals],[Coluna1]] -> 0.010168405 | L41: 2278.55 | M41: 2278.55 | N41: 2278.55 | O41: 2280.51 | P41: 5769.64 | Q41: 2419.61 | R41: 2546.95 | Y41: Seguro Auto | Z41: =Tabela5[[#This Row],[R$]]/Tabela5[[#Totals],[R$]] -> 0.00340554 | AA41: =SUMIF($G$15:$G$143,Y41,$J$15:$J$143) -> 6642.19
F42: Corretora | G42: Bancário | H42: Corban - BTG - Augusto | I42: Augusto | J42: =SUM(Tabela1[[#This Row],[jan./26]:[dez./26]]) -> 17047.63 | K42: =Tabela1[[#This Row],[Coluna1]]/Tabela1[[#Totals],[Coluna1]] -> 0.0087318187 | L42: 1277.69 | M42: 2796.44 | N42: 6802.57 | O42: 2342.42 | P42: 1154.6 | R42: 2673.91 | Y42: Responsabilidade Civil | Z42: =Tabela5[[#This Row],[R$]]/Tabela5[[#Totals],[R$]] -> 0.0028109462 | AA42: =SUMIF($G$15:$G$143,Y42,$J$15:$J$143) -> 5482.49
F43: Corretora | G43: Seguro de vida | H43: Seguro de Vida - Mongeral - Lamour | I43: Lamour | J43: =SUM(Tabela1[[#This Row],[jan./26]:[dez./26]]) -> 15482.88 | K43: =Tabela1[[#This Row],[Coluna1]]/Tabela1[[#Totals],[Coluna1]] -> 0.0079303517 | L43: 9114.18 | M43: 1209.13 | N43: 1209.12 | O43: 1209.13 | P43: 1209.13 | Q43: 1209.13 | R43: 323.06 | Y43: Consulta | Z43: =Tabela5[[#This Row],[R$]]/Tabela5[[#Totals],[R$]] -> 0.0014996868 | AA43: =SUMIF($G$15:$G$143,Y43,$J$15:$J$143) -> 2925
F44: Corretora | G44: Seguro de vida | H44: Seguro de Vida - Azos - Augusto | I44: Augusto | J44: =SUM(Tabela1[[#This Row],[jan./26]:[dez./26]]) -> 12345.28 | K44: =Tabela1[[#This Row],[Coluna1]]/Tabela1[[#Totals],[Coluna1]] -> 0.0063232688 | L44: =198.84+723.81 -> 922.65 | M44: =230.99+913.27 -> 1144.26 | N44: =240.65+1551.77 -> 1792.42 | O44: =271.51+1086.05 -> 1357.56 | P44: 4870.99 | Q44: 1128.45 | R44: 1128.95 | Y44: Título de Capitalização | Z44: =Tabela5[[#This Row],[R$]]/Tabela5[[#Totals],[R$]] -> 0.00058967171 | AA44: =SUMIF($G$15:$G$143,Y44,$J$15:$J$143) -> 1150.1
F45: Corretora | G45: Seguro Residencial | H45: Seguro Residencial - Allianz - Pedro | I45: Pedro | J45: =SUM(Tabela1[[#This Row],[jan./26]:[dez./26]]) -> 8768.8 | K45: =Tabela1[[#This Row],[Coluna1]]/Tabela1[[#Totals],[Coluna1]] -> 0.004491391 | L45: 454.73 | M45: 866.15 | N45: 2258.1 | O45: 1554.79 | P45: 1229.05 | Q45: 299.46 | R45: 2106.52 | Y45: Bonificação | Z45: =Tabela5[[#This Row],[R$]]/Tabela5[[#Totals],[R$]] -> 0.00047678759 | AA45: =SUMIF($G$15:$G$143,Y45,$J$15:$J$143) -> 929.93
F46: Corretora | G46: Previdência | H46: Previdência - Sul America - Andaluz | I46: Andaluz | J46: =SUM(Tabela1[[#This Row],[jan./26]:[dez./26]]) -> 7344.21 | K46: =Tabela1[[#This Row],[Coluna1]]/Tabela1[[#Totals],[Coluna1]] -> 0.0037617141 | L46: =682.59+1.46 -> 684.05 | M46: =619.74+1.69 -> 621.43 | N46: =591.2+1.69 -> 592.89 | O46: =695.83+6.43 -> 702.26 | P46: 648.87 | Q46: 2083.6 | R46: 2011.11 | Y46: Seguro Saúde | Z46: =Tabela5[[#This Row],[R$]]/Tabela5[[#Totals],[R$]] -> 0.00044608631 | AA46: =SUMIF($G$15:$G$143,Y46,$J$15:$J$143) -> 870.05
F47: Corretora | G47: Seguro de vida | H47: Seguro de Vida - Mongeral - Sidney | I47: Sidney | J47: =SUM(Tabela1[[#This Row],[jan./26]:[dez./26]]) -> 7250.14 | K47: =Tabela1[[#This Row],[Coluna1]]/Tabela1[[#Totals],[Coluna1]] -> 0.0037135313 | L47: =101.89+19.62 -> 121.51 | M47: =101.89+19.56 -> 121.45 | N47: =101.88+19.56 -> 121.44 | O47: =101.88+19.56 -> 121.44 | P47: 2521.51 | Q47: 1053.02 | R47: 3189.77 | Y47: Seguro Viagem | Z47: =Tabela5[[#This Row],[R$]]/Tabela5[[#Totals],[R$]] -> 0.00029344127 | AA47: =SUMIF($G$15:$G$143,Y47,$J$15:$J$143) -> 572.33
F48: Corretora | G48: Previdência | H48: Previdência - Sul América - Augusto | I48: Augusto | J48: =SUM(Tabela1[[#This Row],[jan./26]:[dez./26]]) -> 6806.2 | K48: =Tabela1[[#This Row],[Coluna1]]/Tabela1[[#Totals],[Coluna1]] -> 0.0034861447 | L48: 2663.92 | M48: 1064.1 | N48: 2261.08 | O48: 399.16 | P48: 370.18 | Q48: 25.22 | R48: 22.54 | Y48: Ajustes Financeiros | Z48: =Tabela5[[#This Row],[R$]]/Tabela5[[#Totals],[R$]] -> 0.00013413096 | AA48: =SUMIF($G$15:$G$143,Y48,$J$15:$J$143) -> 261.61
F49: Corretora | G49: Seguro de vida | H49: Seguro de Vida - Azos - Gaioso | I49: Gaioso | J49: =SUM(Tabela1[[#This Row],[jan./26]:[dez./26]]) -> 5732.52 | K49: =Tabela1[[#This Row],[Coluna1]]/Tabela1[[#Totals],[Coluna1]] -> 0.0029362044 | R49: 5732.52 | Y49: Seguro Condomínio | Z49: =Tabela5[[#This Row],[R$]]/Tabela5[[#Totals],[R$]] -> 0.0002211333 | AA49: =SUMIF($G$15:$G$143,Y49,$J$15:$J$143) -> 431.3
F50: Corretora | G50: Seguro Residencial | H50: Seguro Residencial - Tokio - Pedro | I50: Pedro | J50: =SUM(Tabela1[[#This Row],[jan./26]:[dez./26]]) -> 5465.27 | K50: =Tabela1[[#This Row],[Coluna1]]/Tabela1[[#Totals],[Coluna1]] -> 0.0027993185 | L50: 984.76 | M50: 957.4 | N50: 769.88 | O50: 833.39 | P50: 667.14 | Q50: 697.78 | R50: 554.92 | Y50: Odontologico | Z50: =Tabela5[[#This Row],[R$]]/Tabela5[[#Totals],[R$]] -> 0.00016275575 | AA50: =SUMIF($G$15:$G$143,Y50,$J$15:$J$143) -> 317.44
F51: Corretora | G51: Previdência | H51: Previdência - Sul América - Sidney | I51: Sidney | J51: =SUM(Tabela1[[#This Row],[jan./26]:[dez./26]]) -> 5063.9 | K51: =Tabela1[[#This Row],[Coluna1]]/Tabela1[[#Totals],[Coluna1]] -> 0.0025937363 | L51: 874.06 | M51: 785.84 | N51: 603.08 | O51: 740.61 | P51: 560.44 | Q51: 907.66 | R51: 592.21 | Y51: Empresarial | Z51: =Tabela5[[#This Row],[R$]]/Tabela5[[#Totals],[R$]] -> 0.00010722376 | AA51: =SUMIF($G$15:$G$143,Y51,$J$15:$J$143) -> 209.13
F52: Corretora | G52: Previdência | H52: Previdência - Sul América - Pedro | I52: Pedro | J52: =SUM(Tabela1[[#This Row],[jan./26]:[dez./26]]) -> 4532.01 | K52: =Tabela1[[#This Row],[Coluna1]]/Tabela1[[#Totals],[Coluna1]] -> 0.0023213015 | L52: 0 | M52: 1862.01 | N52: 2005.06 | O52: 664.94 | Y52: Seguro Pet | Z52: =Tabela5[[#This Row],[R$]]/Tabela5[[#Totals],[R$]] -> 8.5418056e-06 | AA52: =SUMIF($G$15:$G$143,Y52,$J$15:$J$143) -> 16.66
F53: Corretora | G53: Seguro de vida | H53: Seguro de Vida - Mongeral - Gaioso | I53: Gaioso | J53: =SUM(Tabela1[[#This Row],[jan./26]:[dez./26]]) -> 4519.97 | K53: =Tabela1[[#This Row],[Coluna1]]/Tabela1[[#Totals],[Coluna1]] -> 0.0023151346 | L53: 705.78 | M53: 707.01 | N53: 707.02 | O53: 578.96 | P53: 581.48 | Q53: 570.18 | R53: 669.54 | Y53: Receitas diversas | Z53: =Tabela5[[#This Row],[R$]]/Tabela5[[#Totals],[R$]] -> 7.4702346e-06 | AA53: =SUMIF($G$15:$G$143,Y53,$J$15:$J$143) -> 14.57
F54: Corretora | G54: Sem centro de custo | H54: Estorno Pagamentos Diversos | I54: Andaluz | J54: =SUM(Tabela1[[#This Row],[jan./26]:[dez./26]]) -> 3839.75 | K54: =Tabela1[[#This Row],[Coluna1]]/Tabela1[[#Totals],[Coluna1]] -> 0.001966725 | L54: 0 | M54: 980 | N54: 0 | O54: 0 | P54: 2859.75 | Y54: Total | Z54: =SUBTOTAL(109,Tabela5[%]) -> 1 | AA54: =SUBTOTAL(109,Tabela5[R$]) -> 1950407.3
F55: Corretora | G55: Bancário | H55: Corban - BTG - Sidney | I55: Sidney | J55: =SUM(Tabela1[[#This Row],[jan./26]:[dez./26]]) -> 3760.86 | K55: =Tabela1[[#This Row],[Coluna1]]/Tabela1[[#Totals],[Coluna1]] -> 0.0019263175 | L55: 374.66 | M55: 392.52 | N55: 276.98 | O55: 475.88 | P55: 843.73 | R55: 1397.09
F56: Corretora | G56: Seguro de vida | H56: Seguro de Vida - Mongeral - Pedro | I56: Pedro | J56: =SUM(Tabela1[[#This Row],[jan./26]:[dez./26]]) -> 3189.9 | K56: =Tabela1[[#This Row],[Coluna1]]/Tabela1[[#Totals],[Coluna1]] -> 0.001633871 | L56: =333.93+212.59 -> 546.52 | M56: =333.9+212.59 -> 546.49 | N56: =203.73+212.59 -> 416.32 | O56: =127.51+212.59 -> 340.1 | P56: 203.72 | Q56: 711.43 | R56: 425.32
F57: Corretora | G57: Bancário | H57: Corban - BTG - Lamour | I57: Lamour | J57: =SUM(Tabela1[[#This Row],[jan./26]:[dez./26]]) -> 2766.88 | K57: =Tabela1[[#This Row],[Coluna1]]/Tabela1[[#Totals],[Coluna1]] -> 0.0014171996 | L57: 121.15 | M57: 123.43 | N57: 150.55 | O57: 124.69 | P57: 1809.31 | R57: 437.75
F58: Corretora | G58: Seguro de vida | H58: Seguro de Vida - Azos - Lamour | I58: Lamour | J58: =SUM(Tabela1[[#This Row],[jan./26]:[dez./26]]) -> 2750.1 | K58: =Tabela1[[#This Row],[Coluna1]]/Tabela1[[#Totals],[Coluna1]] -> 0.0014086049 | L58: =123.72+114.88 -> 238.6 | M58: =180.18+114.88 -> 295.06 | N58: =182.04+113.97 -> 296.01 | O58: =189.05+114.88 -> 303.93 | P58: 304.75 | Q58: 304.75 | R58: 1007
F59: Corretora | G59: Seguro de vida | H59: Seguro de Vida - Azos - Cristiano | I59: Cristiano | J59: =SUM(Tabela1[[#This Row],[jan./26]:[dez./26]]) -> 2732.19 | K59: =Tabela1[[#This Row],[Coluna1]]/Tabela1[[#Totals],[Coluna1]] -> 0.0013994313 | L59: =232.31+122.47 -> 354.78 | M59: =135.49+122.47 -> 257.96 | N59: =248.25+122.47 -> 370.72 | O59: =345.07+309.36 -> 654.43 | P59: 277.54 | Q59: 373.03 | R59: 443.73
F60: Corretora | G60: Previdência | H60: Previdência - Sul América - Cristiano | I60: Cristiano | J60: =SUM(Tabela1[[#This Row],[jan./26]:[dez./26]]) -> 2660 | K60: =Tabela1[[#This Row],[Coluna1]]/Tabela1[[#Totals],[Coluna1]] -> 0.0013624555 | L60: 0 | M60: 0 | N60: 0 | O60: 2660
F61: Corretora | G61: Seguro de Vida | H61: Seguro de Vida - Prudential - Sidney | I61: Sidney | J61: =SUM(Tabela1[[#This Row],[jan./26]:[dez./26]]) -> 1968.58 | K61: =Tabela1[[#This Row],[Coluna1]]/Tabela1[[#Totals],[Coluna1]] -> 0.0010083093 | L61: 38.22 | M61: 38.22 | N61: 1777.45 | O61: 38.25 | P61: 38.22 | Q61: 38.22
F62: Corretora | G62: Financiamentos | H62: Financiamentos - Gaioso | I62: Gaioso | J62: =SUM(Tabela1[[#This Row],[jan./26]:[dez./26]]) -> 1950 | K62: =Tabela1[[#This Row],[Coluna1]]/Tabela1[[#Totals],[Coluna1]] -> 0.00099879259 | R62: 1950
F63: Corretora | G63: Bancário | H63: Corban - BTG - Andaluz | I63: Andaluz | J63: =SUM(Tabela1[[#This Row],[jan./26]:[dez./26]]) -> 1757.06 | K63: =Tabela1[[#This Row],[Coluna1]]/Tabela1[[#Totals],[Coluna1]] -> 0.00089996846 | L63: 116.11 | M63: 454.62 | N63: 308.51 | O63: 130.17 | P63: 230.04 | R63: 517.61
F64: Corretora | G64: Seguro de vida | H64: Seguro de Vida - Prudential - Cristiano | I64: Cristiano | J64: =SUM(Tabela1[[#This Row],[jan./26]:[dez./26]]) -> 1632.36 | K64: =Tabela1[[#This Row],[Coluna1]]/Tabela1[[#Totals],[Coluna1]] -> 0.00083609696 | L64: =152.8+644.8 -> 797.6 | M64: =152.8-107.7 -> 45.1 | N64: =152.81+107.69 -> 260.5 | O64: =152.94-107.79 -> 45.15 | P64: 260.5 | Q64: 158.32 | R64: 65.19
F65: Corretora | G65: Previdência | H65: Previdência - Saks - Andaluz | I65: Andaluz | J65: =SUM(Tabela1[[#This Row],[jan./26]:[dez./26]]) -> 1479.09 | K65: =Tabela1[[#This Row],[Coluna1]]/Tabela1[[#Totals],[Coluna1]] -> 0.00075759186 | L65: 0 | M65: 117.16 | N65: 247.3 | O65: 297.35 | P65: 276.8 | Q65: 260.32 | R65: 280.16
F66: Corretora | G66: Seguro de vida | H66: Seguro de Vida - Mongeral - Cristiano | I66: Cristiano | J66: =SUM(Tabela1[[#This Row],[jan./26]:[dez./26]]) -> 1190.22 | K66: =Tabela1[[#This Row],[Coluna1]]/Tabela1[[#Totals],[Coluna1]] -> 0.00060963226 | L66: 178.95 | M66: 168.55 | N66: 168.54 | O66: 168.55 | P66: 168.55 | Q66: 168.54 | R66: 168.54
F67: Corretora | G67: Título de Capitalização | H67: Título de Capitalização - Icatu - Augusto | I67: Augusto | J67: =SUM(Tabela1[[#This Row],[jan./26]:[dez./26]]) -> 1150.1 | K67: =Tabela1[[#This Row],[Coluna1]]/Tabela1[[#Totals],[Coluna1]] -> 0.00058908275 | Q67: 1150.1
F68: Corretora | G68: Seguro Auto | H68: Seguro Auto - Porto Seguro - Augusto | I68: Augusto | J68: =SUM(Tabela1[[#This Row],[jan./26]:[dez./26]]) -> 1103.39 | K68: =Tabela1[[#This Row],[Coluna1]]/Tabela1[[#Totals],[Coluna1]] -> 0.00056515782 | L68: 35.39 | M68: 20.71 | N68: 20.71 | O68: 20.72 | P68: 999.89 | Q68: 5.97
F69: Corretora | G69: Seguro de vida | H69: Seguro de Vida - Azos - Pedro | I69: Pedro | J69: =SUM(Tabela1[[#This Row],[jan./26]:[dez./26]]) -> 1029.07 | K69: =Tabela1[[#This Row],[Coluna1]]/Tabela1[[#Totals],[Coluna1]] -> 0.00052709102 | L69: 147.01 | M69: 147.01 | N69: 147.01 | O69: 147.01 | P69: 147.01 | R69: 294.02
F70: Corretora | G70: Responsabilidade Civil | H70: Responsabilidade Civil - Porto - Augusto | I70: Augusto | J70: =SUM(Tabela1[[#This Row],[jan./26]:[dez./26]]) -> 976.46 | K70: =Tabela1[[#This Row],[Coluna1]]/Tabela1[[#Totals],[Coluna1]] -> 0.00050014411 | L70: 359.36 | M70: 73.24 | N70: 73.24 | O70: 73.24 | P70: 356.02 | Q70: 20.68 | R70: 20.68
F71: Corretora | G71: Seguro de vida | H71: Seguro de Vida - Metlife - Augusto | I71: Augusto | J71: =SUM(Tabela1[[#This Row],[jan./26]:[dez./26]]) -> 956.48 | K71: =Tabela1[[#This Row],[Coluna1]]/Tabela1[[#Totals],[Coluna1]] -> 0.00048991033 | L71: 239.12 | M71: 0 | N71: 119.56 | O71: 239.12 | Q71: 119.56 | R71: 239.12
F72: Corretora | G72: Seguro de vida | H72: Seguro de Vida - Mongeral - Andaluz | I72: Andaluz | J72: =SUM(Tabela1[[#This Row],[jan./26]:[dez./26]]) -> 934.52 | K72: =Tabela1[[#This Row],[Coluna1]]/Tabela1[[#Totals],[Coluna1]] -> 0.00047866238 | L72: =212.05+18.95 -> 231 | M72: 105.72 | N72: 158.24 | O72: 105.73 | P72: 105.73 | Q72: 44.69 | R72: 183.41
F73: Corretora | G73: Bonificação | H73: Bonificação - Allianz - Andaluz | I73: Andaluz | J73: =SUM(Tabela1[[#This Row],[jan./26]:[dez./26]]) -> 929.93 | K73: =Tabela1[[#This Row],[Coluna1]]/Tabela1[[#Totals],[Coluna1]] -> 0.00047631138 | L73: 0 | M73: 0 | N73: 427.8 | O73: 0 | P73: 502.13
F74: Corretora | G74: Bancário | H74: Corban - BTG - Gaioso | I74: Gaioso | J74: =SUM(Tabela1[[#This Row],[jan./26]:[dez./26]]) -> 901.12 | K74: =Tabela1[[#This Row],[Coluna1]]/Tabela1[[#Totals],[Coluna1]] -> 0.00046155486 | L74: 127.7 | M74: 147.27 | N74: 102.5 | O74: 94.41 | P74: 90.62 | R74: 338.62
F75: Corretora | G75: Seguro de Vida | H75: Seguro de Vida - Azos - Andaluz | I75: Andaluz | J75: =SUM(Tabela1[[#This Row],[jan./26]:[dez./26]]) -> 860.97 | K75: =Tabela1[[#This Row],[Coluna1]]/Tabela1[[#Totals],[Coluna1]] -> 0.00044098998 | L75: 89.29 | M75: 89.29 | N75: 142.3 | O75: 143.73 | P75: 149.6 | Q75: 96.35 | R75: 150.41
F76: Corretora | G76: Previdência | H76: Previdência - BTG - Andaluz | I76: Andaluz | J76: =SUM(Tabela1[[#This Row],[jan./26]:[dez./26]]) -> 857.87 | K76: =Tabela1[[#This Row],[Coluna1]]/Tabela1[[#Totals],[Coluna1]] -> 0.00043940215 | L76: 131.31 | M76: 141.57 | N76: 291.13 | O76: 133.48 | P76: 160.38
F77: Corretora | G77: Responsabilidade Civil | H77: Responsabilidade Civil - Chubb - Augusto | I77: Augusto | J77: =SUM(Tabela1[[#This Row],[jan./26]:[dez./26]]) -> 850.07 | K77: =Tabela1[[#This Row],[Coluna1]]/Tabela1[[#Totals],[Coluna1]] -> 0.00043540698 | P77: 850.07
F78: Corretora | G78: Responsabilidade Civil | H78: Responsabilidade Civil - Fairfax - Augusto | I78: Augusto | J78: =SUM(Tabela1[[#This Row],[jan./26]:[dez./26]]) -> 837.73 | K78: =Tabela1[[#This Row],[Coluna1]]/Tabela1[[#Totals],[Coluna1]] -> 0.00042908642 | L78: 320.32 | M78: 124.37 | N78: 124.37 | O78: 124.37 | P78: 48.1 | Q78: 48.1 | R78: 48.1
F79: Corretora | G79: Responsabilidade Civil | H79: Responsabilidade Civil - Akad - Pedro | I79: Pedro | J79: =SUM(Tabela1[[#This Row],[jan./26]:[dez./26]]) -> 815.6 | K79: =Tabela1[[#This Row],[Coluna1]]/Tabela1[[#Totals],[Coluna1]] -> 0.0004177514 | L79: 36.21 | M79: 16.97 | N79: =16.97+15.61 -> 32.58 | O79: =258.55+15.61 -> 274.16 | P79: 304.13 | Q79: 70.7 | R79: 80.85
F80: Corretora | G80: Seguro Auto | H80: Seguro Auto - Allianz - Sidney | I80: Sidney | J80: =SUM(Tabela1[[#This Row],[jan./26]:[dez./26]]) -> 742.49 | K80: =Tabela1[[#This Row],[Coluna1]]/Tabela1[[#Totals],[Coluna1]] -> 0.00038030436 | L80: 0 | M80: 214.1 | N80: 0 | O80: 0 | Q80: 528.39
F81: Corretora | G81: Seguro Saúde | H81: Seguro Saúde - Sulamérica - Gaioso | I81: Gaioso | J81: =SUM(Tabela1[[#This Row],[jan./26]:[dez./26]]) -> 738.64 | K81: =Tabela1[[#This Row],[Coluna1]]/Tabela1[[#Totals],[Coluna1]] -> 0.00037833239 | L81: =41.77+174.83 -> 216.6 | M81: =40.74+41.95 -> 82.69 | N81: 37.87 | O81: =44.99+119.64 -> 164.63 | P81: 119.64 | R81: 117.21
F82: Corretora | G82: Seguro Auto | H82: Seguro Auto - Yellum - Lamour | I82: Lamour | J82: =SUM(Tabela1[[#This Row],[jan./26]:[dez./26]]) -> 724.22 | K82: =Tabela1[[#This Row],[Coluna1]]/Tabela1[[#Totals],[Coluna1]] -> 0.00037094645 | L82: 222.04 | M82: 0 | N82: 0 | O82: 0 | R82: 502.18
F83: Corretora | G83: Seguro Auto | H83: Seguro Auto - Porto Seguro - Pedro | I83: Pedro | J83: =SUM(Tabela1[[#This Row],[jan./26]:[dez./26]]) -> 576.94 | K83: =Tabela1[[#This Row],[Coluna1]]/Tabela1[[#Totals],[Coluna1]] -> 0.00029550943 | L83: 151.13 | M83: 41.12 | N83: 81.26 | O83: 81.27 | P83: 75.22 | Q83: 64.59 | R83: 82.35
F84: Corretora | G84: Responsabilidade Civil | H84: Responsabilidade Civil - Chubb - Gaioso | I84: Gaioso | J84: =SUM(Tabela1[[#This Row],[jan./26]:[dez./26]]) -> 565.56 | K84: =Tabela1[[#This Row],[Coluna1]]/Tabela1[[#Totals],[Coluna1]] -> 0.00028968058 | L84: 0 | M84: 0 | N84: 104.83 | O84: 104.83 | P84: 355.9
F85: Corretora | G85: Responsabilidade Civil | H85: Responsabilidade Civil - Fator - Augusto | I85: Augusto | J85: =SUM(Tabela1[[#This Row],[jan./26]:[dez./26]]) -> 526.48 | K85: =Tabela1[[#This Row],[Coluna1]]/Tabela1[[#Totals],[Coluna1]] -> 0.00026966375 | L85: 116.08 | M85: 66 | N85: 212.4 | O85: 66 | Q85: 66 | Z85: =Tabela5[[#Totals],[R$]]-Z82 -> 1950407.3
F86: Corretora | G86: Previdência | H86: Previdência - Sul América - Gaioso | I86: Gaioso | J86: =SUM(Tabela1[[#This Row],[jan./26]:[dez./26]]) -> 520.2 | K86: =Tabela1[[#This Row],[Coluna1]]/Tabela1[[#Totals],[Coluna1]] -> 0.00026644713 | L86: 157.93 | M86: 38.12 | N86: 35.38 | O86: 41.96 | P86: 82.96 | Q86: 83.94 | R86: 79.91
F87: Corretora | G87: Bancário | H87: Corban - BTG - Cristiano | I87: Cristiano | J87: =SUM(Tabela1[[#This Row],[jan./26]:[dez./26]]) -> 485.69 | K87: =Tabela1[[#This Row],[Coluna1]]/Tabela1[[#Totals],[Coluna1]] -> 0.00024877106 | L87: 52.12 | M87: 59.02 | N87: 79.45 | O87: 92.88 | P87: 59.88 | R87: 142.34
F88: Corretora | G88: Seguro Auto | H88: Seguro Auto - Allianz - Augusto | I88: Augusto | J88: =SUM(Tabela1[[#This Row],[jan./26]:[dez./26]]) -> 480.33 | K88: =Tabela1[[#This Row],[Coluna1]]/Tabela1[[#Totals],[Coluna1]] -> 0.00024602566 | Q88: 468.03 | R88: 12.3
F89: Corretora | G89: Seguro Residencial | H89: Seguro Residencial - Tokio - Andaluz | I89: Andaluz | J89: =SUM(Tabela1[[#This Row],[jan./26]:[dez./26]]) -> 452.74 | K89: =Tabela1[[#This Row],[Coluna1]]/Tabela1[[#Totals],[Coluna1]] -> 0.00023189403 | R89: 452.74
F90: Corretora | G90: Seguro Auto | H90: Seguro Auto - Yellum - Bruno | I90: Bruno | J90: =SUM(Tabela1[[#This Row],[jan./26]:[dez./26]]) -> 442.8 | K90: =Tabela1[[#This Row],[Coluna1]]/Tabela1[[#Totals],[Coluna1]] -> 0.00022680275 | L90: 160.17 | M90: 0 | N90: 0 | O90: 197.84 | P90: 84.79
F91: Corretora | G91: Seguro Condomínio | H91: Seguro Condomínio - Allianz - Pedro | I91: Pedro | J91: =SUM(Tabela1[[#This Row],[jan./26]:[dez./26]]) -> 431.3 | K91: =Tabela1[[#This Row],[Coluna1]]/Tabela1[[#Totals],[Coluna1]] -> 0.00022091243 | Q91: 217.49 | R91: =98.26+115.55 -> 213.81
F92: Corretora | G92: Seguro Auto | H92: Seguro Auto - Bradesco - Pedro | I92: Pedro | J92: =SUM(Tabela1[[#This Row],[jan./26]:[dez./26]]) -> 398.96 | K92: =Tabela1[[#This Row],[Coluna1]]/Tabela1[[#Totals],[Coluna1]] -> 0.00020434784 | L92: 41.28 | M92: 0 | N92: 0 | O92: 0 | R92: 357.68
F93: Corretora | G93: Seguro Auto | H93: Seguro Auto - Porto Seguro - Sidney | I93: Sidney | J93: =SUM(Tabela1[[#This Row],[jan./26]:[dez./26]]) -> 335.98 | K93: =Tabela1[[#This Row],[Coluna1]]/Tabela1[[#Totals],[Coluna1]] -> 0.0001720894 | L93: 21.61 | M93: 142.32 | N93: 34.52 | O93: 34.51 | P93: 34.52 | Q93: 33.99 | R93: 34.51
F94: Corretora | G94: Bancário | H94: Corban - BTG - Pedro | I94: Pedro | J94: =SUM(Tabela1[[#This Row],[jan./26]:[dez./26]]) -> 331.88 | K94: =Tabela1[[#This Row],[Coluna1]]/Tabela1[[#Totals],[Coluna1]] -> 0.00016998938 | L94: 27.85 | M94: 45.5 | N94: 43.79 | O94: 47.68 | P94: 81.81 | R94: 85.25
F95: Corretora | G95: Seguro de Vida | H95: Seguro de Vida - Azos - Bruno | I95: Bruno | J95: =SUM(Tabela1[[#This Row],[jan./26]:[dez./26]]) -> 325.36 | K95: =Tabela1[[#This Row],[Coluna1]]/Tabela1[[#Totals],[Coluna1]] -> 0.00016664982 | L95: 46.48 | M95: 46.48 | N95: 46.48 | O95: 46.48 | P95: 46.48 | Q95: 46.48 | R95: 46.48
F96: Corretora | G96: Responsabilidade Civil | H96: Responsabilidade Civil - Akad - Augusto | I96: Augusto | J96: =SUM(Tabela1[[#This Row],[jan./26]:[dez./26]]) -> 307.42 | K96: =Tabela1[[#This Row],[Coluna1]]/Tabela1[[#Totals],[Coluna1]] -> 0.00015746093 | L96: 0 | M96: 0 | N96: 307.42 | O96: 0
F97: Corretora | G97: Seguro Auto | H97: Seguro Auto - Yellum - Cristiano | I97: Cristiano | J97: =SUM(Tabela1[[#This Row],[jan./26]:[dez./26]]) -> 287.53 | K97: =Tabela1[[#This Row],[Coluna1]]/Tabela1[[#Totals],[Coluna1]] -> 0.00014727325 | P97: 287.53
F98: Corretora | G98: Seguro de Vida | H98: Seguro de Vida - Mongeral - Bruno | I98: Bruno | J98: =SUM(Tabela1[[#This Row],[jan./26]:[dez./26]]) -> 279.92 | K98: =Tabela1[[#This Row],[Coluna1]]/Tabela1[[#Totals],[Coluna1]] -> 0.0001433754 | L98: 279.92 | M98: 0 | N98: 0 | O98: 0
F99: Corretora | G99: Odontologico | H99: Odontologico - Metlife - Andaluz | I99: Andaluz | J99: =SUM(Tabela1[[#This Row],[jan./26]:[dez./26]]) -> 256.44 | K99: =Tabela1[[#This Row],[Coluna1]]/Tabela1[[#Totals],[Coluna1]] -> 0.00013134891 | L99: 47.86 | M99: 30.97 | N99: 35.36 | O99: 35.36 | P99: 35.36 | Q99: 0.81 | R99: 70.72
F100: Corretora | G100: Seguro Auto | H100: Seguro Auto - Yellum - Augusto | I100: Augusto | J100: =SUM(Tabela1[[#This Row],[jan./26]:[dez./26]]) -> 244.35 | K100: =Tabela1[[#This Row],[Coluna1]]/Tabela1[[#Totals],[Coluna1]] -> 0.00012515639 | P100: 244.35
F101: Corretora | G101: Seguro Residencial | H101: Seguro Residencial - HDI - Augusto | I101: Augusto | J101: =SUM(Tabela1[[#This Row],[jan./26]:[dez./26]]) -> 237.13 | K101: =Tabela1[[#This Row],[Coluna1]]/Tabela1[[#Totals],[Coluna1]] -> 0.0001214583 | R101: 237.13
F102: Corretora | G102: Seguro Viagem | H102: Seguro Viagem - Chubb - Cristiano | I102: Cristiano | J102: =SUM(Tabela1[[#This Row],[jan./26]:[dez./26]]) -> 234.62 | K102: =Tabela1[[#This Row],[Coluna1]]/Tabela1[[#Totals],[Coluna1]] -> 0.00012017268 | L102: 0 | M102: 0 | N102: 234.62 | O102: 0
F103: Corretora | G103: Responsabilidade Civil | H103: Responsabilidade Civil - Fairfax - Gaioso | I103: Gaioso | J103: =SUM(Tabela1[[#This Row],[jan./26]:[dez./26]]) -> 228.62 | K103: =Tabela1[[#This Row],[Coluna1]]/Tabela1[[#Totals],[Coluna1]] -> 0.00011709947 | L103: 0 | M103: 65.32 | N103: 32.66 | O103: 32.66 | P103: 32.66 | Q103: 32.66 | R103: 32.66
F104: Corretora | G104: Seguro Auto | H104: Seguro Auto - Yellum - Pedro | I104: Pedro | J104: =SUM(Tabela1[[#This Row],[jan./26]:[dez./26]]) -> 223.15 | K104: =Tabela1[[#This Row],[Coluna1]]/Tabela1[[#Totals],[Coluna1]] -> 0.00011429773 | L104: 0 | M104: 0 | N104: 0 | O104: 223.15
F105: Corretora | G105: Seguro Auto | H105: Seguro Auto - Allianz - Andaluz | I105: Andaluz | J105: =SUM(Tabela1[[#This Row],[jan./26]:[dez./26]]) -> 213.06 | K105: =Tabela1[[#This Row],[Coluna1]]/Tabela1[[#Totals],[Coluna1]] -> 0.00010912961 | Q105: 213.06
F106: Corretora | G106: Previdência | H106: Previdência - Sul América - Bruno | I106: Bruno | J106: =SUM(Tabela1[[#This Row],[jan./26]:[dez./26]]) -> 199.49 | K106: =Tabela1[[#This Row],[Coluna1]]/Tabela1[[#Totals],[Coluna1]] -> 0.00010217904 | L106: 199.49 | M106: 0 | N106: 0 | O106: 0
F107: Corretora | G107: Seguro Residencial | H107: Seguro Residencial - Allianz - Lamour | I107: Lamour | J107: =SUM(Tabela1[[#This Row],[jan./26]:[dez./26]]) -> 197.06 | K107: =Tabela1[[#This Row],[Coluna1]]/Tabela1[[#Totals],[Coluna1]] -> 0.00010093439 | L107: 94.59 | M107: 0 | N107: 0 | O107: 0 | P107: 71.21 | Q107: 31.26
F108: Corretora | G108: Seguro de vida | H108: Seguro de Vida - Sul América - Sidney | I108: Sidney | J108: =SUM(Tabela1[[#This Row],[jan./26]:[dez./26]]) -> 188.36 | K108: =Tabela1[[#This Row],[Coluna1]]/Tabela1[[#Totals],[Coluna1]] -> 9.6478242e-05 | L108: 37.5 | M108: 0 | N108: 75.43 | O108: 37.71 | P108: 37.72
F109: Corretora | G109: Seguro Auto | H109: Seguro Auto - Tokio - Sidney | I109: Sidney | J109: =SUM(Tabela1[[#This Row],[jan./26]:[dez./26]]) -> 185.85 | K109: =Tabela1[[#This Row],[Coluna1]]/Tabela1[[#Totals],[Coluna1]] -> 9.5192617e-05 | L109: 154.82 | M109: 31.03 | N109: 0 | O109: 0
F110: Corretora | G110: Responsabilidade Civil | H110: Responsabilidade Civil - Fator - Cristiano | I110: Cristiano | J110: =SUM(Tabela1[[#This Row],[jan./26]:[dez./26]]) -> 184.97 | K110: =Tabela1[[#This Row],[Coluna1]]/Tabela1[[#Totals],[Coluna1]] -> 9.4741879e-05 | L110: 0 | M110: 0 | N110: 46.24 | O110: 46.24 | Q110: 46.24 | R110: 46.25
F111: Corretora | G111: Seguro Auto | H111: Seguro Auto - Allianz - Lamour | I111: Lamour | J111: =SUM(Tabela1[[#This Row],[jan./26]:[dez./26]]) -> 170.01 | K111: =Tabela1[[#This Row],[Coluna1]]/Tabela1[[#Totals],[Coluna1]] -> 8.7079348e-05 | L111: 0 | M111: 0 | N111: 138.91 | O111: 0.01 | R111: 31.09
F112: Corretora | G112: Seguro Auto | H112: Seguro Auto - Mapfre - Gaioso | I112: Gaioso | J112: =SUM(Tabela1[[#This Row],[jan./26]:[dez./26]]) -> 155.76 | K112: =Tabela1[[#This Row],[Coluna1]]/Tabela1[[#Totals],[Coluna1]] -> 7.9780479e-05 | L112: 0 | M112: 0 | N112: 51.92 | O112: 51.92 | P112: 51.92
...

Sheet Gastos
AC10: Retirados do estudo
E13: =Tabela8[[#Totals],[YTD]] -> 1810248 | M13: =Tabela8[[#Totals],[Média]] -> 339828.84 | N13: =Tabela8[[#Totals],[YTD]] -> 1810248 | O13: AV(%) | P13: =Tabela8[[#Totals],[jan./26]] -> 435967 | Q13: =Tabela8[[#Totals],[fev./26]] -> 177386.35 | R13: =Tabela8[[#Totals],[mar./26]] -> 204640.9 | S13: =Tabela8[[#Totals],[abr./26]] -> 248353.36 | T13: =Tabela8[[#Totals],[mai/26]] -> 202282.22 | U13: =Tabela8[[#Totals],[jun/26]] -> 234725.29 | V13: =Tabela8[[#Totals],[jul/26]] -> 306892.84 | W13: =Tabela8[[#Totals],[ago/26]] -> 0 | X13: =Tabela8[[#Totals],[set/26]] -> 0 | Y13: =Tabela8[[#Totals],[out/26]] -> 0 | Z13: =Tabela8[[#Totals],[nov/26]] -> 0 | AA13: =Tabela8[[#Totals],[dez/26]] -> 0
F14: Empresa | G14: Centro de custos | H14: Categoria | I14: Destino | J14: Natureza | K14: Utilidade | L14: Obs | M14: Média | N14: YTD | O14: 100% | P14: jan./26 | Q14: fev./26 | R14: mar./26 | S14: abr./26 | T14: mai/26 | U14: jun/26 | V14: jul/26 | W14: ago/26 | X14: set/26 | Y14: out/26 | Z14: nov/26 | AA14: dez/26 | AC14: Centro de Custos | AD14: % | AE14: Valor | AG14: Destino | AH14: R$ | AI14: Coluna1 | AJ14: % | AL14: Natureza | AM14: R$ | AN14: /6 | AO14: %
F15: Consultoria | G15: Impostos sobre Vendas e sobre Serviços | H15: IRPJ sobre Faturamento | I15: Impostos | J15: Variavel | K15: No choice | M15: =AVERAGE(Tabela8[[#This Row],[jan./26]:[dez/26]]) -> 27672.654 | N15: =SUM(Tabela8[[#This Row],[jan./26]:[dez/26]]) -> 138363.27 | O15: =Tabela8[[#This Row],[YTD]]/Tabela8[[#Totals],[YTD]] -> 0.076433325 | P15: 46113.85 | Q15: 0 | R15: 0 | S15: 43652.51 | V15: 48596.91 | AC15: Despesas regulatórias | AD15: =Tabela4[[#This Row],[Valor]]/Tabela4[[#Totals],[Valor]] -> 0 | AE15: =SUMIF($G$15:$G$132,AC15,$N$15:$N$132) -> 0 | AG15: Impostos | AH15: =SUMIF(Tabela8[Destino],Tabela10[[#This Row],[Destino]],Tabela8[YTD]) -> 384408.56 | AI15: =Tabela10[[#This Row],[R$]]/6 -> 64068.093 | AJ15: =Tabela10[[#This Row],[R$]]/Tabela10[[#Totals],[R$]] -> 0.19684957 | AL15: Variavel | AM15: =SUMIF(Tabela8[Natureza],Tabela11[[#This Row],[Natureza]],Tabela8[YTD]) -> 510059.32 | AN15: =Tabela11[[#This Row],[R$]]/6 -> 85009.887 | AO15: =Tabela11[[#This Row],[R$]]/Tabela11[[#Totals],[R$]] -> 0.24454555
F16: Consultoria | G16: Investimento estratégico | H16: Recompra de cotas | I16: Queima caixa | J16: Extraordinario | K16: - | M16: =AVERAGE(Tabela8[[#This Row],[jan./26]:[dez/26]]) -> 47191.02 | N16: =SUM(Tabela8[[#This Row],[jan./26]:[dez/26]]) -> 94382.04 | U16: 50000 | V16: 44382.04 | AC16: Despesas com Diretoria | AD16: =Tabela4[[#This Row],[Valor]]/Tabela4[[#Totals],[Valor]] -> 0 | AE16: =SUMIF($G$15:$G$132,AC16,$N$15:$N$132) -> 0 | AG16: Custo | AH16: =SUMIF(Tabela8[Destino],Tabela10[[#This Row],[Destino]],Tabela8[YTD]) -> 304491.75 | AI16: =Tabela10[[#This Row],[R$]]/6 -> 50748.625 | AJ16: =Tabela10[[#This Row],[R$]]/Tabela10[[#Totals],[R$]] -> 0.15592543 | AL16: Fixo | AM16: =SUMIF(Tabela8[Natureza],Tabela11[[#This Row],[Natureza]],Tabela8[YTD]) -> 546469.69 | AN16: =Tabela11[[#This Row],[R$]]/6 -> 91078.282 | AO16: =Tabela11[[#This Row],[R$]]/Tabela11[[#Totals],[R$]] -> 0.26200233
F17: Consultoria | G17: Comissões | H17: Comissão Augusto | I17: Augusto | J17: Comissão | K17: Comissão | M17: =AVERAGE(Tabela8[[#This Row],[jan./26]:[dez/26]]) -> 23881.181 | N17: =SUM(Tabela8[[#This Row],[jan./26]:[dez/26]]) -> 167168.27 | O17: =Tabela8[[#This Row],[YTD]]/Tabela8[[#Totals],[YTD]] -> 0.092345509 | P17: 21632.2 | Q17: 21927.62 | R17: 25996.57 | S17: 24328.67 | T17: 24718.15 | U17: 24898.87 | V17: 23666.19 | AC17: Despesas com serviços | AD17: =Tabela4[[#This Row],[Valor]]/Tabela4[[#Totals],[Valor]] -> 0 | AE17: =SUMIF($G$15:$G$132,AC17,$N$15:$N$132) -> 0 | AG17: Augusto | AH17: =SUMIF(Tabela8[Destino],Tabela10[[#This Row],[Destino]],Tabela8[YTD]) -> 266340.2 | AI17: =Tabela10[[#This Row],[R$]]/6 -> 44390.033 | AJ17: =Tabela10[[#This Row],[R$]]/Tabela10[[#Totals],[R$]] -> 0.13638862 | AL17: Extraordinario | AM17: =SUMIF(Tabela8[Natureza],Tabela11[[#This Row],[Natureza]],Tabela8[YTD]) -> 318191.41 | AN17: =Tabela11[[#This Row],[R$]]/6 -> 53031.902 | AO17: =Tabela11[[#This Row],[R$]]/Tabela11[[#Totals],[R$]] -> 0.15255538
F18: Consultoria | G18: Impostos sobre Vendas e sobre Serviços | H18: CSLL sobre Faturamento | I18: Impostos | J18: Variavel | K18: No choice | M18: =AVERAGE(Tabela8[[#This Row],[jan./26]:[dez/26]]) -> 13099.062 | N18: =SUM(Tabela8[[#This Row],[jan./26]:[dez/26]]) -> 65495.31 | O18: =Tabela8[[#This Row],[YTD]]/Tabela8[[#Totals],[YTD]] -> 0.036180298 | P18: 22134.44 | Q18: 0 | R18: 0 | S18: 20062.59 | V18: 23298.28 | AC18: Despesas com Colaboradores | AD18: =Tabela4[[#This Row],[Valor]]/Tabela4[[#Totals],[Valor]] -> 0 | AE18: =SUMIF($G$15:$G$132,AC18,$N$15:$N$132) -> 0 | AG18: PLR | AH18: =SUMIF(Tabela8[Destino],Tabela10[[#This Row],[Destino]],Tabela8[YTD]) -> 176017.16 | AI18: =Tabela10[[#This Row],[R$]]/6 -> 29336.193 | AJ18: =Tabela10[[#This Row],[R$]]/Tabela10[[#Totals],[R$]] -> 0.090135615 | AL18: - | AM18: =SUMIF(Tabela8[Natureza],Tabela11[[#This Row],[Natureza]],Tabela8[YTD]) -> 24886.61 | AN18: =Tabela11[[#This Row],[R$]]/6 -> 4147.7683 | AO18: =Tabela11[[#This Row],[R$]]/Tabela11[[#Totals],[R$]] -> 0.011931769
F19: Consultoria | G19: Comissões | H19: Comissão Gaioso | I19: Gaioso | J19: Comissão | K19: Comissão | M19: =AVERAGE(Tabela8[[#This Row],[jan./26]:[dez/26]]) -> 15145.406 | N19: =SUM(Tabela8[[#This Row],[jan./26]:[dez/26]]) -> 106017.84 | O19: =Tabela8[[#This Row],[YTD]]/Tabela8[[#Totals],[YTD]] -> 0.058565369 | P19: 15044.78 | Q19: 15000 | R19: 15183.32 | S19: 15183.05 | T19: 15332.8 | U19: 15091.16 | V19: 15182.73 | AC19: Despesas com Imóvel | AD19: =Tabela4[[#This Row],[Valor]]/Tabela4[[#Totals],[Valor]] -> 0 | AE19: =SUMIF($G$15:$G$132,AC19,$N$15:$N$132) -> 0 | AG19: Despesa | AH19: =SUMIF(Tabela8[Destino],Tabela10[[#This Row],[Destino]],Tabela8[YTD]) -> 126213.17 | AI19: =Tabela10[[#This Row],[R$]]/6 -> 21035.528 | AJ19: =Tabela10[[#This Row],[R$]]/Tabela10[[#Totals],[R$]] -> 0.064631776 | AL19: Comissão | AM19: =SUMIF(Tabela8[Natureza],Tabela11[[#This Row],[Natureza]],Tabela8[YTD]) -> 686136.56 | AN19: =Tabela11[[#This Row],[R$]]/6 -> 114356.09 | AO19: =Tabela11[[#This Row],[R$]]/Tabela11[[#Totals],[R$]] -> 0.32896496
F20: Consultoria | G20: Comissões | H20: Comissão Sidney | I20: Sidney | J20: Comissão | K20: Comissão | M20: =AVERAGE(Tabela8[[#This Row],[jan./26]:[dez/26]]) -> 13619.894 | N20: =SUM(Tabela8[[#This Row],[jan./26]:[dez/26]]) -> 95339.26 | O20: =Tabela8[[#This Row],[YTD]]/Tabela8[[#Totals],[YTD]] -> 0.052666409 | P20: 11936.26 | Q20: 11942.71 | R20: 18966.67 | S20: 11953.33 | T20: 10540.29 | U20: 15000 | V20: 15000 | AC20: Despesas Financeiras | AD20: =Tabela4[[#This Row],[Valor]]/Tabela4[[#Totals],[Valor]] -> 0 | AE20: =SUMIF($G$15:$G$132,AC20,$N$15:$N$132) -> 0 | AG20: Lamour | AH20: =SUMIF(Tabela8[Destino],Tabela10[[#This Row],[Destino]],Tabela8[YTD]) -> 114538.52 | AI20: =Tabela10[[#This Row],[R$]]/6 -> 19089.753 | AJ20: =Tabela10[[#This Row],[R$]]/Tabela10[[#Totals],[R$]] -> 0.058653372 | AL20: Total | AM20: =SUBTOTAL(109,Tabela11[R$]) -> 2085743.6 | AN20: =SUBTOTAL(109,Tabela11[/6]) -> 347623.93
F21: Consultoria | G21: Comissões | H21: Comissão Lamour | I21: Lamour | J21: Comissão | K21: Comissão | M21: =AVERAGE(Tabela8[[#This Row],[jan./26]:[dez/26]]) -> 15288.451 | N21: =SUM(Tabela8[[#This Row],[jan./26]:[dez/26]]) -> 107019.16 | O21: =Tabela8[[#This Row],[YTD]]/Tabela8[[#Totals],[YTD]] -> 0.059118509 | P21: 15538.48 | Q21: 17683.57 | R21: 13426.48 | S21: 13992.28 | T21: 16322.97 | U21: 15481.37 | V21: 14574.01 | AC21: Despesas com Sistemas | AD21: =Tabela4[[#This Row],[Valor]]/Tabela4[[#Totals],[Valor]] -> 0 | AE21: =SUMIF($G$15:$G$132,AC21,$N$15:$N$132) -> 0 | AG21: Gaioso | AH21: =SUMIF(Tabela8[Destino],Tabela10[[#This Row],[Destino]],Tabela8[YTD]) -> 106993.15 | AI21: =Tabela10[[#This Row],[R$]]/6 -> 17832.192 | AJ21: =Tabela10[[#This Row],[R$]]/Tabela10[[#Totals],[R$]] -> 0.054789507
F22: Consultoria | G22: Impostos sobre Vendas e sobre Serviços | H22: ISS sobre Faturamento | I22: Impostos | J22: Variavel | K22: No choice | M22: =AVERAGE(Tabela8[[#This Row],[jan./26]:[dez/26]]) -> 12325.454 | N22: =SUM(Tabela8[[#This Row],[jan./26]:[dez/26]]) -> 86278.18 | O22: =Tabela8[[#This Row],[YTD]]/Tabela8[[#Totals],[YTD]] -> 0.047660973 | P22: 13010.69 | Q22: 11339.32 | R22: 13477.14 | S22: 10014.48 | T22: 11165.35 | U22: 13000.98 | V22: 14270.22 | AC22: Despesas com Salários e Encargos | AD22: =Tabela4[[#This Row],[Valor]]/Tabela4[[#Totals],[Valor]] -> 0 | AE22: =SUMIF($G$15:$G$132,AC22,$N$15:$N$132) -> 0 | AG22: Sidney | AH22: =SUMIF(Tabela8[Destino],Tabela10[[#This Row],[Destino]],Tabela8[YTD]) -> 100894.4 | AI22: =Tabela10[[#This Row],[R$]]/6 -> 16815.733 | AJ22: =Tabela10[[#This Row],[R$]]/Tabela10[[#Totals],[R$]] -> 0.051666433
F23: Consultoria | G23: Serviços | H23: Honorários Advocatícios | I23: Despesa | J23: Fixo | K23: Revisável | M23: =AVERAGE(Tabela8[[#This Row],[jan./26]:[dez/26]]) -> 3071.4286 | N23: =SUM(Tabela8[[#This Row],[jan./26]:[dez/26]]) -> 21500 | O23: =Tabela8[[#This Row],[YTD]]/Tabela8[[#Totals],[YTD]] -> 0.011876826 | P23: 2000 | Q23: 2000 | R23: 2000 | S23: 2000 | T23: 2000 | U23: 2000 | V23: 9500 | AC23: Encargos | AD23: =Tabela4[[#This Row],[Valor]]/Tabela4[[#Totals],[Valor]] -> 5.1179836e-07 | AE23: =SUMIF($G$15:$G$132,AC23,$N$15:$N$132) -> 0.8 | AG23: Queima caixa | AH23: =SUMIF(Tabela8[Destino],Tabela10[[#This Row],[Destino]],Tabela8[YTD]) -> 125217.57 | AI23: =Tabela10[[#This Row],[R$]]/6 -> 20869.595 | AJ23: =Tabela10[[#This Row],[R$]]/Tabela10[[#Totals],[R$]] -> 0.064121945
F24: Consultoria | G24: Financeiras | H24: Empréstimos de Outras Instituições | I24: Dívida | J24: Fixo | K24: No choice | M24: =AVERAGE(Tabela8[[#This Row],[jan./26]:[dez/26]]) -> 9525.3486 | N24: =SUM(Tabela8[[#This Row],[jan./26]:[dez/26]]) -> 66677.44 | O24: =Tabela8[[#This Row],[YTD]]/Tabela8[[#Totals],[YTD]] -> 0.036833319 | P24: 10236.57 | Q24: 9841.16 | R24: 8739.58 | S24: 10077.97 | T24: 9270.03 | U24: 9126.12 | V24: 9386.01 | AC24: Imobilizados e equipamentos | AD24: =Tabela4[[#This Row],[Valor]]/Tabela4[[#Totals],[Valor]] -> 0.00053545624 | AE24: =SUMIF($G$15:$G$132,AC24,$N$15:$N$132) -> 836.98 | AG24: Institucional | AH24: =SUMIF(Tabela8[Destino],Tabela10[[#This Row],[Destino]],Tabela8[YTD]) -> 84566.01 | AI24: =Tabela10[[#This Row],[R$]]/6 -> 14094.335 | AJ24: =Tabela10[[#This Row],[R$]]/Tabela10[[#Totals],[R$]] -> 0.043304921
F25: Corretora | G25: Comissões | H25: Comissão - Augusto | I25: Augusto | J25: Comissão | K25: Comissão | M25: =AVERAGE(Tabela8[[#This Row],[jan./26]:[dez/26]]) -> 8453.1329 | N25: =SUM(Tabela8[[#This Row],[jan./26]:[dez/26]]) -> 59171.93 | O25: =Tabela8[[#This Row],[YTD]]/Tabela8[[#Totals],[YTD]] -> 0.032687196 | P25: 5488.47 | Q25: 8429.14 | R25: 8905.17 | S25: 11479.03 | T25: 8636.46 | U25: 11075.68 | V25: 5157.98 | AC25: Despesas Comerciais | AD25: =Tabela4[[#This Row],[Valor]]/Tabela4[[#Totals],[Valor]] -> 0.00082108451 | AE25: =SUMIF($G$15:$G$132,AC25,$N$15:$N$132) -> 1283.45 | AG25: Igor Araujo | AH25: =SUMIF(Tabela8[Destino],Tabela10[[#This Row],[Destino]],Tabela8[YTD]) -> 81049.64 | AI25: =Tabela10[[#This Row],[R$]]/6 -> 13508.273 | AJ25: =Tabela10[[#This Row],[R$]]/Tabela10[[#Totals],[R$]] -> 0.041504244
F26: Consultoria | G26: Impostos sobre Vendas e sobre Serviços | H26: COFINS sobre Faturamento | I26: Impostos | J26: Variavel | K26: No choice | M26: =AVERAGE(Tabela8[[#This Row],[jan./26]:[dez/26]]) -> 7395.2614 | N26: =SUM(Tabela8[[#This Row],[jan./26]:[dez/26]]) -> 51766.83 | O26: =Tabela8[[#This Row],[YTD]]/Tabela8[[#Totals],[YTD]] -> 0.028596541 | P26: 7806.41 | Q26: 6803.59 | R26: 8086.27 | S26: 6008.67 | T26: 6699.2 | U26: 7800.57 | V26: 8562.12 | AC26: Despesas com Vendas | AD26: =Tabela4[[#This Row],[Valor]]/Tabela4[[#Totals],[Valor]] -> 0.0021226261 | AE26: =SUMIF($G$15:$G$132,AC26,$N$15:$N$132) -> 3317.91 | AG26: Dívida | AH26: =SUMIF(Tabela8[Destino],Tabela10[[#This Row],[Destino]],Tabela8[YTD]) -> 66677.44 | AI26: =Tabela10[[#This Row],[R$]]/6 -> 11112.907 | AJ26: =Tabela10[[#This Row],[R$]]/Tabela10[[#Totals],[R$]] -> 0.034144467 | AL26: Utilidade | AM26: R$ | AN26: /6 | AO26: %
F27: Corretora | G27: Salários e Encargos | H27: Salários | I27: Custo | J27: Fixo | K27: Revisável | M27: =AVERAGE(Tabela8[[#This Row],[jan./26]:[dez/26]]) -> 7408.2017 | N27: =SUM(Tabela8[[#This Row],[jan./26]:[dez/26]]) -> 44449.21 | O27: =Tabela8[[#This Row],[YTD]]/Tabela8[[#Totals],[YTD]] -> 0.024554211 | P27: 7120.49 | Q27: 7284.04 | R27: 5797.65 | S27: 5238.46 | T27: 11747.78 | V27: 7260.79 | AC27: Sem centro de custo | AD27: =Tabela4[[#This Row],[Valor]]/Tabela4[[#Totals],[Valor]] -> 0.0042688461 | AE27: =SUMIF($G$15:$G$132,AC27,$N$15:$N$132) -> 6672.7 | AG27: Pedro | AH27: =SUMIF(Tabela8[Destino],Tabela10[[#This Row],[Destino]],Tabela8[YTD]) -> 51890.27 | AI27: =Tabela10[[#This Row],[R$]]/6 -> 8648.3783 | AJ27: =Tabela10[[#This Row],[R$]]/Tabela10[[#Totals],[R$]] -> 0.02657219 | AL27: No choice | AM27: =SUMIF(Tabela8[Utilidade],Tabela12[[#This Row],[Utilidade]],Tabela8[YTD]) -> 465538.04 | AN27: =Tabela12[[#This Row],[R$]]/6 -> 77589.673 | AO27: =Tabela12[[#This Row],[R$]]/Tabela12[[#Totals],[R$]] -> 0.2873327
F28: Consultoria | G28: Tesouro Mato Grosso | H28: Comissão Consultoria - Tesouro Mato Grosso | I28: Institucional | J28: Fixo | K28: Obrigatório | M28: =AVERAGE(Tabela8[[#This Row],[jan./26]:[dez/26]]) -> 7100 | N28: =SUM(Tabela8[[#This Row],[jan./26]:[dez/26]]) -> 49700 | O28: =Tabela8[[#This Row],[YTD]]/Tabela8[[#Totals],[YTD]] -> 0.027454802 | P28: 7100 | Q28: 7100 | R28: 7100 | S28: 7100 | T28: 7100 | U28: 7100 | V28: 7100 | AC28: Estornos | AD28: =Tabela4[[#This Row],[Valor]]/Tabela4[[#Totals],[Valor]] -> 0.0073284791 | AE28: =SUMIF($G$15:$G$132,AC28,$N$15:$N$132) -> 11455.26 | AG28: Cristiano | AH28: =SUMIF(Tabela8[Destino],Tabela10[[#This Row],[Destino]],Tabela8[YTD]) -> 45607.46 | AI28: =Tabela10[[#This Row],[R$]]/6 -> 7601.2433 | AJ28: =Tabela10[[#This Row],[R$]]/Tabela10[[#Totals],[R$]] -> 0.023354862 | AL28: Obrigatório | AM28: =SUMIF(Tabela8[Utilidade],Tabela12[[#This Row],[Utilidade]],Tabela8[YTD]) -> 199542.97 | AN28: =Tabela12[[#This Row],[R$]]/6 -> 33257.162 | AO28: =Tabela12[[#This Row],[R$]]/Tabela12[[#Totals],[R$]] -> 0.12315905
F29: Consultoria | G29: Comissões | H29: Salário Igor Araujo | I29: Igor Araujo | J29: Comissão | K29: Comissão | M29: =AVERAGE(Tabela8[[#This Row],[jan./26]:[dez/26]]) -> 6578.52 | N29: =SUM(Tabela8[[#This Row],[jan./26]:[dez/26]]) -> 46049.64 | O29: =Tabela8[[#This Row],[YTD]]/Tabela8[[#Totals],[YTD]] -> 0.025438305 | P29: 5749.27 | Q29: 5695.28 | R29: 7461.4 | S29: 5965.22 | T29: 8479.87 | U29: 6239.61 | V29: 6458.99 | AC29: Despesas Administrativas | AD29: =Tabela4[[#This Row],[Valor]]/Tabela4[[#Totals],[Valor]] -> 0.014171959 | AE29: =SUMIF($G$15:$G$132,AC29,$N$15:$N$132) -> 22152.41 | AG29: Antigo | AH29: =SUMIF(Tabela8[Destino],Tabela10[[#This Row],[Destino]],Tabela8[YTD]) -> 24886.61 | AI29: =Tabela10[[#This Row],[R$]]/6 -> 4147.7683 | AJ29: =Tabela10[[#This Row],[R$]]/Tabela10[[#Totals],[R$]] -> 0.012744041 | AL29: Preferencial | AM29: =SUMIF(Tabela8[Utilidade],Tabela12[[#This Row],[Utilidade]],Tabela8[YTD]) -> 10694.52 | AN29: =Tabela12[[#This Row],[R$]]/6 -> 1782.42 | AO29: =Tabela12[[#This Row],[R$]]/Tabela12[[#Totals],[R$]] -> 0.006600718
F30: Consultoria | G30: Imóvel | H30: Aluguel | I30: Custo | J30: Fixo | K30: Obrigatório | M30: =AVERAGE(Tabela8[[#This Row],[jan./26]:[dez/26]]) -> 5646.62 | N30: =SUM(Tabela8[[#This Row],[jan./26]:[dez/26]]) -> 39526.34 | O30: =Tabela8[[#This Row],[YTD]]/Tabela8[[#Totals],[YTD]] -> 0.021834766 | P30: 5646.62 | Q30: 5646.62 | R30: 5646.62 | S30: 5646.62 | T30: 5646.62 | U30: 5646.62 | V30: 5646.62 | AC30: Investimento estratégico | AD30: =Tabela4[[#This Row],[Valor]]/Tabela4[[#Totals],[Valor]] -> 0.062386691 | AE30: =SUMIF($G$15:$G$132,AC30,$N$15:$N$132) -> 97517.61 | AG30: Prejuízo | AH30: =SUMIF(Tabela8[Destino],Tabela10[[#This Row],[Destino]],Tabela8[YTD]) -> 18128.76 | AI30: =Tabela10[[#This Row],[R$]]/6 -> 3021.46 | AJ30: =Tabela10[[#This Row],[R$]]/Tabela10[[#Totals],[R$]] -> 0.0092834524 | AL30: Revisável | AM30: =SUMIF(Tabela8[Utilidade],Tabela12[[#This Row],[Utilidade]],Tabela8[YTD]) -> 247474.22 | AN30: =Tabela12[[#This Row],[R$]]/6 -> 41245.703 | AO30: =Tabela12[[#This Row],[R$]]/Tabela12[[#Totals],[R$]] -> 0.15274248
F31: Consultoria | G31: Sistemas | H31: Sistemas Consolidação | I31: Custo | J31: Variavel | K31: Obrigatório | M31: =AVERAGE(Tabela8[[#This Row],[jan./26]:[dez/26]]) -> 3626.88 | N31: =SUM(Tabela8[[#This Row],[jan./26]:[dez/26]]) -> 25388.16 | O31: =Tabela8[[#This Row],[YTD]]/Tabela8[[#Totals],[YTD]] -> 0.014024686 | P31: 0 | Q31: 0 | R31: 5093 | S31: 5180.31 | T31: 4977.79 | U31: 5081.03 | V31: 5056.03 | AC31: Tesouro Mato Grosso | AD31: =Tabela4[[#This Row],[Valor]]/Tabela4[[#Totals],[Valor]] -> 0.1110385 | AE31: =SUMIF($G$15:$G$132,AC31,$N$15:$N$132) -> 173566.01 | AG31: Bruno | AH31: =SUMIF(Tabela8[Destino],Tabela10[[#This Row],[Destino]],Tabela8[YTD]) -> 4762.84 | AI31: =Tabela10[[#This Row],[R$]]/6 -> 793.80667 | AJ31: =Tabela10[[#This Row],[R$]]/Tabela10[[#Totals],[R$]] -> 0.0024389753 | AL31: Dispensável | AM31: =SUMIF(Tabela8[Utilidade],Tabela12[[#This Row],[Utilidade]],Tabela8[YTD]) -> 46495.56 | AN31: =Tabela12[[#This Row],[R$]]/6 -> 7749.26 | AO31: =Tabela12[[#This Row],[R$]]/Tabela12[[#Totals],[R$]] -> 0.028697322
F32: Consultoria | G32: Tesouro Mato Grosso | H32: Comissão Augusto - Tesouro Mato Grosso | I32: Augusto | J32: Variavel | K32: Comissão | M32: =AVERAGE(Tabela8[[#This Row],[jan./26]:[dez/26]]) -> 5714.2857 | N32: =SUM(Tabela8[[#This Row],[jan./26]:[dez/26]]) -> 40000 | O32: =Tabela8[[#This Row],[YTD]]/Tabela8[[#Totals],[YTD]] -> 0.02209642 | P32: 5000 | Q32: 5000 | R32: 5000 | S32: 5000 | T32: 10000 | U32: 5000 | V32: 5000 | AC32: PLR e Bônus | AD32: =Tabela4[[#This Row],[Valor]]/Tabela4[[#Totals],[Valor]] -> 0.11363021 | AE32: =SUMIF($G$15:$G$132,AC32,$N$15:$N$132) -> 177617.16 | AG32: Israel | AH32: =SUMIF(Tabela8[Destino],Tabela10[[#This Row],[Destino]],Tabela8[YTD]) -> 2449.82 | AI32: =Tabela10[[#This Row],[R$]]/6 -> 408.30333 | AJ32: =Tabela10[[#This Row],[R$]]/Tabela10[[#Totals],[R$]] -> 0.0012545142 | AL32: Comissão | AM32: =SUMIF(Tabela8[Utilidade],Tabela12[[#This Row],[Utilidade]],Tabela8[YTD]) -> 775136.56 | AN32: =Tabela12[[#This Row],[R$]]/6 -> 129189.43 | AO32: =Tabela12[[#This Row],[R$]]/Tabela12[[#Totals],[R$]] -> 0.47841865
F33: Consultoria | G33: Tesouro Mato Grosso | H33: Salário Igor Araujo - Tesouro Mato Grosso | I33: Igor Araujo | J33: Variavel | K33: Comissão | M33: =AVERAGE(Tabela8[[#This Row],[jan./26]:[dez/26]]) -> 5000 | N33: =SUM(Tabela8[[#This Row],[jan./26]:[dez/26]]) -> 35000 | O33: =Tabela8[[#This Row],[YTD]]/Tabela8[[#Totals],[YTD]] -> 0.019334368 | P33: 5000 | Q33: 5000 | R33: 5000 | S33: 5000 | T33: 5000 | U33: 5000 | V33: 5000 | AC33: Impostos sobre Vendas e sobre Serviços | AD33: =Tabela4[[#This Row],[Valor]]/Tabela4[[#Totals],[Valor]] -> 0.24535287 | AE33: =SUMIF($G$15:$G$132,AC33,$N$15:$N$132) -> 383514.9 | AG33: Mario | AH33: =SUMIF(Tabela8[Destino],Tabela10[[#This Row],[Destino]],Tabela8[YTD]) -> 610.26 | AI33: =Tabela10[[#This Row],[R$]]/6 -> 101.71 | AJ33: =Tabela10[[#This Row],[R$]]/Tabela10[[#Totals],[R$]] -> 0.00031250453 | AL33: - | AM33: =SUMIF(Tabela8[Utilidade],Tabela12[[#This Row],[Utilidade]],Tabela8[YTD]) -> 340861.72 | AN33: =Tabela12[[#This Row],[R$]]/6 -> 56810.287 | AO33: =Tabela12[[#This Row],[R$]]/Tabela12[[#Totals],[R$]] -> 0.21038178
F34: Consultoria | G34: Comissões | H34: Comissão Cristiano | I34: Cristiano | J34: Comissão | K34: Comissão | M34: =AVERAGE(Tabela8[[#This Row],[jan./26]:[dez/26]]) -> 4044.4543 | N34: =SUM(Tabela8[[#This Row],[jan./26]:[dez/26]]) -> 28311.18 | O34: =Tabela8[[#This Row],[YTD]]/Tabela8[[#Totals],[YTD]] -> 0.015639393 | P34: 3903.32 | Q34: 4141.68 | R34: 3785.34 | S34: 4184.38 | T34: 4221.49 | U34: 4226.02 | V34: 3848.95 | AC34: Comissões | AD34: =Tabela4[[#This Row],[Valor]]/Tabela4[[#Totals],[Valor]] -> 0.44343269 | AE34: =SUMIF($G$15:$G$132,AC34,$N$15:$N$132) -> 693136.56 | AG34: Total | AH34: =SUBTOTAL(109,Tabela10[R$]) -> 1952803.7 | AI34: =SUBTOTAL(109,Tabela10[Coluna1]) -> 325467.28 | AL34: Total | AM34: =SUBTOTAL(109,Tabela12[R$]) -> 1620205.5 | AN34: =SUBTOTAL(109,Tabela12[/6]) -> 270034.26
F35: Corretora | G35: Salários e Encargos | H35: Rescisões | I35: Despesa | J35: Extraordinario | K35: - | M35: =AVERAGE(Tabela8[[#This Row],[jan./26]:[dez/26]]) -> 4815.58 | N35: =SUM(Tabela8[[#This Row],[jan./26]:[dez/26]]) -> 4815.58 | U35: 4815.58 | AC35: Total | AD35: =SUBTOTAL(109,Tabela4[%]) -> 1 | AE35: =SUBTOTAL(109,Tabela4[Valor]) -> 1563115.6
F36: Corretora | G36: Despesas Administrativas | H36: Salários | I36: Custo | J36: Fixo | K36: Revisável | M36: =AVERAGE(Tabela8[[#This Row],[jan./26]:[dez/26]]) -> 4430.482 | N36: =SUM(Tabela8[[#This Row],[jan./26]:[dez/26]]) -> 22152.41 | O36: =Tabela8[[#This Row],[YTD]]/Tabela8[[#Totals],[YTD]] -> 0.012237224 | P36: 2730.6 | Q36: 2735.42 | R36: 2735.42 | S36: 2735.42 | U36: 11215.55
F37: Corretora | G37: Salários e Encargos | H37: INSS sobre Salários - GPS | I37: Custo | J37: Fixo | K37: Revisável | M37: =AVERAGE(Tabela8[[#This Row],[jan./26]:[dez/26]]) -> 4173.1943 | N37: =SUM(Tabela8[[#This Row],[jan./26]:[dez/26]]) -> 29212.36 | O37: =Tabela8[[#This Row],[YTD]]/Tabela8[[#Totals],[YTD]] -> 0.016137215 | P37: 4432.18 | Q37: 3631.49 | R37: 3585.52 | S37: 4143.32 | T37: 4826.27 | U37: 4894.77 | V37: 3698.81
F38: Consultoria | G38: Salários e Encargos | H38: Vale-Alimentação | I38: Custo | J38: Fixo | K38: Revisável | M38: =AVERAGE(Tabela8[[#This Row],[jan./26]:[dez/26]]) -> 1971.1667 | N38: =SUM(Tabela8[[#This Row],[jan./26]:[dez/26]]) -> 11827 | O38: =Tabela8[[#This Row],[YTD]]/Tabela8[[#Totals],[YTD]] -> 0.0065333591 | P38: 1387 | Q38: 1606 | R38: 1460 | S38: 2174 | T38: 1680 | V38: 3520 | AC38: Consultor | AD38: Total
F39: Consultoria | G39: Salários e Encargos | H39: Salários | I39: Custo | J39: fixo | K39: Revisável | M39: =AVERAGE(Tabela8[[#This Row],[jan./26]:[dez/26]]) -> 3431.0014 | N39: =SUM(Tabela8[[#This Row],[jan./26]:[dez/26]]) -> 24017.01 | O39: =Tabela8[[#This Row],[YTD]]/Tabela8[[#Totals],[YTD]] -> 0.013267249 | P39: 3441.9 | Q39: 3799.19 | R39: 3413.14 | S39: 2710.65 | T39: 3973.75 | U39: 3368.59 | V39: 3309.79 | AC39: Augusto | AD39: =SUMIF(Tabela8[Destino],Tabela9[[#This Row],[Consultor]],Tabela8[YTD]) -> 266340.2
F40: Consultoria | G40: Salários e Encargos | H40: Bolsa Estágio | I40: Custo | J40: Fixo | K40: Dispensável | M40: =AVERAGE(Tabela8[[#This Row],[jan./26]:[dez/26]]) -> 2360.2543 | N40: =SUM(Tabela8[[#This Row],[jan./26]:[dez/26]]) -> 16521.78 | O40: =Tabela8[[#This Row],[YTD]]/Tabela8[[#Totals],[YTD]] -> 0.0091268049 | P40: 0 | Q40: 1521.78 | R40: 3000 | S40: 3000 | T40: 3000 | U40: 3000 | V40: 3000 | AC40: Lamour | AD40: =SUMIF(Tabela8[Destino],Tabela9[[#This Row],[Consultor]],Tabela8[YTD]) -> 114538.52
F41: Consultoria | G41: Sistemas | H41: Sistemas Corporativos | I41: Despesa | J41: Fixo | K41: Obrigatório | M41: =AVERAGE(Tabela8[[#This Row],[jan./26]:[dez/26]]) -> 2475.6729 | N41: =SUM(Tabela8[[#This Row],[jan./26]:[dez/26]]) -> 17329.71 | O41: =Tabela8[[#This Row],[YTD]]/Tabela8[[#Totals],[YTD]] -> 0.009573114 | P41: 0 | Q41: 0 | R41: 5819.9 | S41: 2941.14 | T41: 2913.08 | U41: 2920.55 | V41: 2735.04 | AC41: Gaioso | AD41: =SUMIF(Tabela8[Destino],Tabela9[[#This Row],[Consultor]],Tabela8[YTD]) -> 106993.15
F42: Consultoria | G42: Administrativas | H42: Neoenergia | I42: Custo | J42: Fixo | K42: Obrigatório | M42: =AVERAGE(Tabela8[[#This Row],[jan./26]:[dez/26]]) -> 1286.798 | N42: =SUM(Tabela8[[#This Row],[jan./26]:[dez/26]]) -> 6433.99 | O42: =Tabela8[[#This Row],[YTD]]/Tabela8[[#Totals],[YTD]] -> 0.0035542037 | P42: 995.58 | Q42: 743.23 | R42: 996.52 | S42: 1033.39 | V42: 2665.27 | AC42: Sidney | AD42: =SUMIF(Tabela8[Destino],Tabela9[[#This Row],[Consultor]],Tabela8[YTD]) -> 100894.4
F43: Corretora | G43: Salários e Encargos | H43: Vale-Alimentação | I43: Custo | J43: Fixo | K43: Revisável | M43: =AVERAGE(Tabela8[[#This Row],[jan./26]:[dez/26]]) -> 2822.515 | N43: =SUM(Tabela8[[#This Row],[jan./26]:[dez/26]]) -> 16935.09 | O43: =Tabela8[[#This Row],[YTD]]/Tabela8[[#Totals],[YTD]] -> 0.0093551217 | P43: 2414.57 | Q43: 1823.27 | R43: 2487.57 | S43: 3601.57 | T43: 2787.57 | V43: 3820.54 | AC43: Pedro | AD43: =SUMIF(Tabela8[Destino],Tabela9[[#This Row],[Consultor]],Tabela8[YTD]) -> 51890.27
F44: Consultoria | G44: Tesouro Mato Grosso | H44: Comissão Cristiano - Tesouro Mato Grosso | I44: Cristiano | J44: Variavel | K44: Comissão | M44: =AVERAGE(Tabela8[[#This Row],[jan./26]:[dez/26]]) -> 2000 | N44: =SUM(Tabela8[[#This Row],[jan./26]:[dez/26]]) -> 14000 | O44: =Tabela8[[#This Row],[YTD]]/Tabela8[[#Totals],[YTD]] -> 0.0077337471 | P44: 2000 | Q44: 2000 | R44: 2000 | S44: 2000 | T44: 2000 | U44: 2000 | V44: 2000 | AC44: Igor Araujo | AD44: =SUMIF(Tabela8[Destino],Tabela9[[#This Row],[Consultor]],Tabela8[YTD]) -> 81049.64
F45: Consultoria | G45: Serviços | H45: Honorários Contábeis | I45: Despesa | J45: Fixo | K45: Revisável | L45: reduzir CNPJ's | M45: =AVERAGE(Tabela8[[#This Row],[jan./26]:[dez/26]]) -> 1907.4643 | N45: =SUM(Tabela8[[#This Row],[jan./26]:[dez/26]]) -> 13352.25 | O45: =Tabela8[[#This Row],[YTD]]/Tabela8[[#Totals],[YTD]] -> 0.0073759232 | P45: 1802.61 | Q45: 1924.94 | R45: 1924.94 | S45: 1924.94 | T45: 1924.94 | U45: 1924.94 | V45: 1924.94 | AC45: Cristiano | AD45: =SUMIF(Tabela8[Destino],Tabela9[[#This Row],[Consultor]],Tabela8[YTD]) -> 45607.46
F46: Consultoria | G46: Salários e Encargos | H46: Vale-Transporte | I46: Custo | J46: Fixo | K46: Revisável | M46: =AVERAGE(Tabela8[[#This Row],[jan./26]:[dez/26]]) -> 995.83333 | N46: =SUM(Tabela8[[#This Row],[jan./26]:[dez/26]]) -> 5975 | O46: =Tabela8[[#This Row],[YTD]]/Tabela8[[#Totals],[YTD]] -> 0.0033006528 | P46: 374 | Q46: 968 | R46: 1364 | S46: 440 | T46: 924 | V46: 1905 | AC46: Bruno | AD46: =SUMIF(Tabela8[Destino],Tabela9[[#This Row],[Consultor]],Tabela8[YTD]) -> 4762.84
F47: Consultoria | G47: Impostos sobre Vendas e sobre Serviços | H47: PIS sobre Faturamento | I47: Impostos | J47: Variavel | K47: No choice | M47: =AVERAGE(Tabela8[[#This Row],[jan./26]:[dez/26]]) -> 1602.3057 | N47: =SUM(Tabela8[[#This Row],[jan./26]:[dez/26]]) -> 11216.14 | O47: =Tabela8[[#This Row],[YTD]]/Tabela8[[#Totals],[YTD]] -> 0.0061959136 | P47: 1691.39 | Q47: 1474.11 | R47: 1752.03 | S47: 1301.88 | T47: 1451.49 | U47: 1690.12 | V47: 1855.12 | AC47: Israel | AD47: =SUMIF(Tabela8[Destino],Tabela9[[#This Row],[Consultor]],Tabela8[YTD]) -> 2449.82
